Workbook

Sheet Sản phẩm
A1: Mã sản phẩm | B1: Tên sản phẩm | C1: DS - ĐV | D1: OEM - DS - ĐV | E1: MSG - DS - NK - ĐV
A2: 2150294 | B2: Xúc xích Romas Light (50g) 500g | C2: Food Đức Việt | D2: Food Đức Việt | E2: Food Đức Việt
A3: 2150295 | B3: Xúc xích Romas Light (62g) 500g | C3: Food Đức Việt | D3: Food Đức Việt | E3: Food Đức Việt
A4: 2149882 | B4: Chả giò da xốp nhân thịt 300g | C4: Food Đức Việt | D4: Food Đức Việt | E4: Food Đức Việt
A5: 2149883 | B5: Chả giò da xốp hải sản 300g | C5: Food Đức Việt | D5: Food Đức Việt | E5: Food Đức Việt
A6: 1108036 | B6: Rong biển giòn trộn khô gà 100g * 30EA (HD) | C6: Food Daesang | D6: Food Daesang | E6: Food Daesang
A7: 2150337 | B7: O'food chả giò da xốp nhân thịt 300g | C7: Food Đức Việt | D7: Food Đức Việt | E7: Food Đức Việt
A8: 2150338 | B8: O'food chả giò da xốp hải sản 300g | C8: Food Đức Việt | D8: Food Đức Việt | E8: Food Đức Việt
A9: 1108084 | B9: Bánh gạo Hàn Quốc 30g (Micoem) | C9: Food Daesang | D9: Food Daesang | E9: Food Daesang
A10: 2146426 | B10: Bánh bao bò nướng Bulgogi 200g * 20EA | C10: Food Đức Việt | D10: Food Đức Việt | E10: Food Đức Việt
A11: 2146431 | B11: Sủi cảo nhân thịt heo rau củ 450g * 24EA | C11: Food Đức Việt | D11: Food Đức Việt | E11: Food Đức Việt
A12: 1107847 | B12: Tteokbokki Hàn Quốc Mix vị Tân Việt - XK Ba Lan (gói) 140g *32EA | C12: Food Daesang | D12: Food Daesang | E12: Food Daesang
... A982: 2153300 | B982: Tokpokki chả cá 350g | C982: Food Đức Việt | D982: Food Đức Việt | E982: Food Đức Việt

Sheet Giá gốc
A1: Mã Barcode | B1: Mã sản phẩm | C1: Tên sản phẩm | D1: Giá gốc | E1: Hệ thống
A2: 8935304200226 | B2: 1023739 | C2: Lá Kim tẩm dầu Oliu 5g lốc 3 * 36 lốc (HD) | D2: 26095 | E2: Win+
A3: 8935304201810 | B3: 1024697 | C3: Lá Kim Trẻ em 5g lốc 3 * 36 lốc (HD) | D3: 29645 | E3: Win+
A4: 8935304201841 | B4: 1024696 | C4: Lá Kim Tảo biển cao cấp 5g lốc 3 * 36 lốc (HD) | D4: 29645 | E4: Win+
A5: 8935304200769 | B5: 1106055 | C5: Rong biển giòn trộn khô gà 40G KM lá kim tẩm dầu oliu 4G (30 lốc) HD | D5: 29568 | E5: Win+
A6: 8935304200240 | B6: 1106048 | C6: Rong biển giòn trộn gia vị 40g KM lá kim tẩm dầu oliu 4g (30 lốc) HD | D6: 27600 | E6: Win+
A7: 8935304200837 | B7: 1106056 | C7: Rong biển giòn trộn hạt óc chó, hạnh nhân 40G KM lá kim tẩm dầu oliu 4G (30 lốc) HD | D7: 29568 | E7: Win+
A8: 8935304200783 | B8: 1106049 | C8: Rong biển giòn trộn hải sản 40G KM lá kim tẩm dầu oliu 4G (30 lốc) HD | D8: 29568 | E8: Win+
A9: 8935304200219 | B9: 1023643 | C9: Lá Kim tẩm dầu Ô liu 5g lốc 2 (2 tặng 1) * 40 lốc (HD) | D9: 18768 | E9: Win+
A10: 8801052029450 | B10: 2015475 | C10: Lá Kim tẩm dầu Oliu 4.5g lốc 2 (40 lốc) | D10: 19571 | E10: Win+
A11: 8935304200141 | B11: 1021862 | C11: Tokpokki Hàn Quốc vị phô mai (hộp) 105g * 24EA (HD | D11: 24960 | E11: Win+
A12: 8935304200233 | B12: 1021808 | C12: Lá Kim cuốn cơm 10g * 64EA (HD) | D12: 20064 | E12: Win+
A13: 8935304200608 | B13: 1022846 | C13: Tokpokki Hàn Quốc tròn vị phô mai - Không cay (hộp) 105g*24EA(HD) | D13: 24960 | E13: Win+
... A237: 8935101608164 | B237: 2145716 | C237: Viên mực rong biển 300g | D237: 20000 | E237: Toàn bộ

Sheet Chương trình khuyến mãi
A1: STT | B1: Tên chương trình | C1: Hệ thống | D1: Phạm vi | E1: Ngày áp dụng | F1: Ngày kết thúc | G1: Barcode | H1: Mã sản phẩm | I1: Tên sản phẩm | J1: Giá gốc | K1: % Giảm giá | L1: Giá khuyến mại | M1: Chương trình KM | N1: Mã hàng tặng | O1: Tên hàng tặng | P1: Chương trình KAM | Q1: Loại hàng
A2: =ROW()-1 -> 1 | B2: POST 05 - PHÁI ĐẸP TỎA SÁNG | C2: Toàn bộ | D2: Toàn quốc | E2: 18/02/2026 | F2: 18/03/2026 | G2: 8935101600250 | H2: =VLOOKUP(gia_khuyen_mai[[#This Row],[Barcode]],'Giá gốc'!$A:$B,2,0) -> 2145686 | I2: =VLOOKUP(gia_khuyen_mai[[#This Row],[Mã sản phẩm]],'Giá gốc'!$B:$C,2,0) -> Xúc xích hong khói 450g | J2: =VLOOKUP(gia_khuyen_mai[[#This Row],[Mã sản phẩm]],'Giá gốc'!B:D,3,0) -> 79100 | L2: =ROUND((1-gia_khuyen_mai[[#This Row],[% Giảm giá]]) * gia_khuyen_mai[[#This Row],[Giá gốc]], 0) -> 79100 | M2: Mua 1 tặng 1 | N2: 2145765 | O2: =IFERROR(VLOOKUP(gia_khuyen_mai[[#This Row],[Mã hàng tặng]],'Giá gốc'!B:C,2,0),"") -> Xúc xích Hotdog 200g | Q2: =VLOOKUP(gia_khuyen_mai[[#This Row],[Mã sản phẩm]],product[[Mã sản phẩm]:[DS - ĐV]],3,0) -> Food Đức Việt
A3: =ROW()-1 -> 2 | B3: POST 05 - PHÁI ĐẸP TỎA SÁNG | C3: Toàn bộ | D3: Toàn quốc | E3: 18/02/2026 | F3: 18/03/2026 | G3: 8935101608478 | H3: =VLOOKUP(gia_khuyen_mai[[#This Row],[Barcode]],'Giá gốc'!$A:$B,2,0) -> 2150337 | I3: =VLOOKUP(gia_khuyen_mai[[#This Row],[Mã sản phẩm]],'Giá gốc'!$B:$C,2,0) -> O'food Chả giò da xốp nhân thịt 300g | J3: =VLOOKUP(gia_khuyen_mai[[#This Row],[Mã sản phẩm]],'Giá gốc'!B:D,3,0) -> 31524 | K3: 0.3 | L3: =ROUND((1-gia_khuyen_mai[[#This Row],[% Giảm giá]]) * gia_khuyen_mai[[#This Row],[Giá gốc]], 0) -> 22067 | O3: =IFERROR(VLOOKUP(gia_khuyen_mai[[#This Row],[Mã hàng tặng]],'Giá gốc'!B:C,2,0),"") | Q3: =VLOOKUP(gia_khuyen_mai[[#This Row],[Mã sản phẩm]],product[[Mã sản phẩm]:[DS - ĐV]],3,0) -> Food Đức Việt
A4: =ROW()-1 -> 3 | B4: POST 05 - PHÁI ĐẸP TỎA SÁNG | C4: Toàn bộ | D4: Toàn quốc | E4: 18/02/2026 | F4: 17/03/2026 | G4: 8935101608072 | H4: =VLOOKUP(gia_khuyen_mai[[#This Row],[Barcode]],'Giá gốc'!$A:$B,2,0) -> 2145743 | I4: =VLOOKUP(gia_khuyen_mai[[#This Row],[Mã sản phẩm]],'Giá gốc'!$B:$C,2,0) -> Xúc xích sụn nướng Bulgogi 450g | J4: =VLOOKUP(gia_khuyen_mai[[#This Row],[Mã sản phẩm]],'Giá gốc'!B:D,3,0) -> 74500 | K4: 0.3 | L4: =ROUND((1-gia_khuyen_mai[[#This Row],[% Giảm giá]]) * gia_khuyen_mai[[#This Row],[Giá gốc]], 0) -> 52150 | O4: =IFERROR(VLOOKUP(gia_khuyen_mai[[#This Row],[Mã hàng tặng]],'Giá gốc'!B:C,2,0),"") | Q4: =VLOOKUP(gia_khuyen_mai[[#This Row],[Mã sản phẩm]],product[[Mã sản phẩm]:[DS - ĐV]],3,0) -> Food Đức Việt
A5: =ROW()-1 -> 4 | B5: POST 05 - PHÁI ĐẸP TỎA SÁNG | C5: Toàn bộ | D5: Toàn quốc | E5: 18/02/2026 | F5: 18/03/2026 | G5: 8935101607938 | H5: =VLOOKUP(gia_khuyen_mai[[#This Row],[Barcode]],'Giá gốc'!$A:$B,2,0) -> 2145726 | I5: =VLOOKUP(gia_khuyen_mai[[#This Row],[Mã sản phẩm]],'Giá gốc'!$B:$C,2,0) -> Xúc xích phô mai Cheesy 250g | J5: =VLOOKUP(gia_khuyen_mai[[#This Row],[Mã sản phẩm]],'Giá gốc'!B:D,3,0) -> 49400 | K5: 0.3 | L5: =ROUND((1-gia_khuyen_mai[[#This Row],[% Giảm giá]]) * gia_khuyen_mai[[#This Row],[Giá gốc]], 0) -> 34580 | O5: =IFERROR(VLOOKUP(gia_khuyen_mai[[#This Row],[Mã hàng tặng]],'Giá gốc'!B:C,2,0),"") | Q5: =VLOOKUP(gia_khuyen_mai[[#This Row],[Mã sản phẩm]],product[[Mã sản phẩm]:[DS - ĐV]],3,0) -> Food Đức Việt
A6: =ROW()-1 -> 5 | B6: POST 05 - PHÁI ĐẸP TỎA SÁNG | C6: Toàn bộ | D6: Toàn quốc | E6: 18/02/2026 | F6: 18/03/2026 | G6: 8935101608102 | H6: =VLOOKUP(gia_khuyen_mai[[#This Row],[Barcode]],'Giá gốc'!$A:$B,2,0) -> 2145622 | I6: =VLOOKUP(gia_khuyen_mai[[#This Row],[Mã sản phẩm]],'Giá gốc'!$B:$C,2,0) -> Kim chi 450 | J6: =VLOOKUP(gia_khuyen_mai[[#This Row],[Mã sản phẩm]],'Giá gốc'!B:D,3,0) -> 35500 | K6: 0.3 | L6: =ROUND((1-gia_khuyen_mai[[#This Row],[% Giảm giá]]) * gia_khuyen_mai[[#This Row],[Giá gốc]], 0) -> 24850 | O6: =IFERROR(VLOOKUP(gia_khuyen_mai[[#This Row],[Mã hàng tặng]],'Giá gốc'!B:C,2,0),"") | Q6: =VLOOKUP(gia_khuyen_mai[[#This Row],[Mã sản phẩm]],product[[Mã sản phẩm]:[DS - ĐV]],3,0) -> Food Đức Việt
A7: =ROW()-1 -> 6 | B7: POST 05 - PHÁI ĐẸP TỎA SÁNG | C7: Toàn bộ | D7: Toàn quốc | E7: 18/02/2026 | F7: 18/03/2026 | G7: 8935101605118 | H7: =VLOOKUP(gia_khuyen_mai[[#This Row],[Barcode]],'Giá gốc'!$A:$B,2,0) -> 2145783 | I7: =VLOOKUP(gia_khuyen_mai[[#This Row],[Mã sản phẩm]],'Giá gốc'!$B:$C,2,0) -> Xúc xích Romas ( 50g) 500g | J7: =VLOOKUP(gia_khuyen_mai[[#This Row],[Mã sản phẩm]],'Giá gốc'!B:D,3,0) -> 53900 | K7: 0.25 | L7: =ROUND((1-gia_khuyen_mai[[#This Row],[% Giảm giá]]) * gia_khuyen_mai[[#This Row],[Giá gốc]], 0) -> 40425 | O7: =IFERROR(VLOOKUP(gia_khuyen_mai[[#This Row],[Mã hàng tặng]],'Giá gốc'!B:C,2,0),"") | Q7: =VLOOKUP(gia_khuyen_mai[[#This Row],[Mã sản phẩm]],product[[Mã sản phẩm]:[DS - ĐV]],3,0) -> Food Đức Việt
A8: =ROW()-1 -> 7 | B8: POST 05 - PHÁI ĐẸP TỎA SÁNG | C8: Toàn bộ | D8: Toàn quốc | E8: 18/02/2026 | F8: 18/03/2026 | G8: 8935101605989 | H8: =VLOOKUP(gia_khuyen_mai[[#This Row],[Barcode]],'Giá gốc'!$A:$B,2,0) -> 2145774 | I8: =VLOOKUP(gia_khuyen_mai[[#This Row],[Mã sản phẩm]],'Giá gốc'!$B:$C,2,0) -> Xúc xích Pari (50g) 500g | J8: =VLOOKUP(gia_khuyen_mai[[#This Row],[Mã sản phẩm]],'Giá gốc'!B:D,3,0) -> 55600 | K8: 0.22 | L8: =ROUND((1-gia_khuyen_mai[[#This Row],[% Giảm giá]]) * gia_khuyen_mai[[#This Row],[Giá gốc]], 0) -> 43368 | O8: =IFERROR(VLOOKUP(gia_khuyen_mai[[#This Row],[Mã hàng tặng]],'Giá gốc'!B:C,2,0),"") | Q8: =VLOOKUP(gia_khuyen_mai[[#This Row],[Mã sản phẩm]],product[[Mã sản phẩm]:[DS - ĐV]],3,0) -> Food Đức Việt
A9: =ROW()-1 -> 8 | B9: Post Aging | C9: Win+ | D9: Toàn quốc | E9: 18/02/2026 | F9: 27/02/2026 | G9: 8935101600427 | H9: =VLOOKUP(gia_khuyen_mai[[#This Row],[Barcode]],'Giá gốc'!$A:$B,2,0) -> 2145691 | I9: =VLOOKUP(gia_khuyen_mai[[#This Row],[Mã sản phẩm]],'Giá gốc'!$B:$C,2,0) -> Xúc xích viên hong khói 450g * 1EA | J9: =VLOOKUP(gia_khuyen_mai[[#This Row],[Mã sản phẩm]],'Giá gốc'!B:D,3,0) -> 84200 | L9: =ROUND((1-gia_khuyen_mai[[#This Row],[% Giảm giá]]) * gia_khuyen_mai[[#This Row],[Giá gốc]], 0) -> 84200 | M9: Mua 1 tặng 1 | N9: 2145740 | O9: =IFERROR(VLOOKUP(gia_khuyen_mai[[#This Row],[Mã hàng tặng]],'Giá gốc'!B:C,2,0),"") -> Xúc xích phô mai Cheesy 70g * 30EA | Q9: =VLOOKUP(gia_khuyen_mai[[#This Row],[Mã sản phẩm]],product[[Mã sản phẩm]:[DS - ĐV]],3,0) -> Food Đức Việt
A10: =ROW()-1 -> 9 | B10: POST 06 - Bếp vui, Giá tốt mỗi ngày | C10: Toàn bộ | D10: Toàn quốc | E10: 05/03/2026 | F10: 31/03/2026 | G10: 8935101608348 | H10: =VLOOKUP(gia_khuyen_mai[[#This Row],[Barcode]],'Giá gốc'!$A:$B,2,0) -> 2145744 | I10: =VLOOKUP(gia_khuyen_mai[[#This Row],[Mã sản phẩm]],'Giá gốc'!$B:$C,2,0) -> Xúc xích bắp phô mai 250g | J10: =VLOOKUP(gia_khuyen_mai[[#This Row],[Mã sản phẩm]],'Giá gốc'!B:D,3,0) -> 49400 | K10: 0.3 | L10: =ROUND((1-gia_khuyen_mai[[#This Row],[% Giảm giá]]) * gia_khuyen_mai[[#This Row],[Giá gốc]], 0) -> 34580 | O10: =IFERROR(VLOOKUP(gia_khuyen_mai[[#This Row],[Mã hàng tặng]],'Giá gốc'!B:C,2,0),"") | Q10: =VLOOKUP(gia_khuyen_mai[[#This Row],[Mã sản phẩm]],product[[Mã sản phẩm]:[DS - ĐV]],3,0) -> Food Đức Việt
A11: =ROW()-1 -> 10 | B11: POST 06 - Bếp vui, Giá tốt mỗi ngày | C11: Toàn bộ | D11: Toàn quốc | E11: 05/03/2026 | F11: 01/04/2026 | G11: 8935101607877 | H11: =VLOOKUP(gia_khuyen_mai[[#This Row],[Barcode]],'Giá gốc'!$A:$B,2,0) -> 2145699 | I11: =VLOOKUP(gia_khuyen_mai[[#This Row],[Mã sản phẩm]],'Giá gốc'!$B:$C,2,0) -> Seoul's Hotdog Chiên xù 250g (Đ) | J11: =VLOOKUP(gia_khuyen_mai[[#This Row],[Mã sản phẩm]],'Giá gốc'!B:D,3,0) -> 39150 | K11: 0.22 | L11: =ROUND((1-gia_khuyen_mai[[#This Row],[% Giảm giá]]) * gia_khuyen_mai[[#This Row],[Giá gốc]], 0) -> 30537 | O11: =IFERROR(VLOOKUP(gia_khuyen_mai[[#This Row],[Mã hàng tặng]],'Giá gốc'!B:C,2,0),"") | Q11: =VLOOKUP(gia_khuyen_mai[[#This Row],[Mã sản phẩm]],product[[Mã sản phẩm]:[DS - ĐV]],3,0) -> Food Đức Việt
A12: =ROW()-1 -> 11 | B12: POST 06 - Bếp vui, Giá tốt mỗi ngày | C12: Toàn bộ | D12: Toàn quốc | E12: 05/03/2026 | F12: 31/03/2026 | G12: 8935101600960 | H12: =VLOOKUP(gia_khuyen_mai[[#This Row],[Barcode]],'Giá gốc'!$A:$B,2,0) -> 2145745 | I12: =VLOOKUP(gia_khuyen_mai[[#This Row],[Mã sản phẩm]],'Giá gốc'!$B:$C,2,0) -> Jăm bông hấp 200g | J12: =VLOOKUP(gia_khuyen_mai[[#This Row],[Mã sản phẩm]],'Giá gốc'!B:D,3,0) -> 37000 | K12: 0.15 | L12: =ROUND((1-gia_khuyen_mai[[#This Row],[% Giảm giá]]) * gia_khuyen_mai[[#This Row],[Giá gốc]], 0) -> 31450 | O12: =IFERROR(VLOOKUP(gia_khuyen_mai[[#This Row],[Mã hàng tặng]],'Giá gốc'!B:C,2,0),"") | Q12: =VLOOKUP(gia_khuyen_mai[[#This Row],[Mã sản phẩm]],product[[Mã sản phẩm]:[DS - ĐV]],3,0) -> Food Đức Việt
A13: =ROW()-1 -> 12 | B13: POST 06 - Bếp vui, Giá tốt mỗi ngày | C13: Toàn bộ | D13: Toàn quốc | E13: 05/03/2026 | F13: 01/04/2026 | G13: 8935101604883 | H13: =VLOOKUP(gia_khuyen_mai[[#This Row],[Barcode]],'Giá gốc'!$A:$B,2,0) -> 2145765 | I13: =VLOOKUP(gia_khuyen_mai[[#This Row],[Mã sản phẩm]],'Giá gốc'!$B:$C,2,0) -> Xúc xích Hotdog 200g | J13: =VLOOKUP(gia_khuyen_mai[[#This Row],[Mã sản phẩm]],'Giá gốc'!B:D,3,0) -> 20100 | K13: 0.2 | L13: =ROUND((1-gia_khuyen_mai[[#This Row],[% Giảm giá]]) * gia_khuyen_mai[[#This Row],[Giá gốc]], 0) -> 16080 | O13: =IFERROR(VLOOKUP(gia_khuyen_mai[[#This Row],[Mã hàng tặng]],'Giá gốc'!B:C,2,0),"") | Q13: =VLOOKUP(gia_khuyen_mai[[#This Row],[Mã sản phẩm]],product[[Mã sản phẩm]:[DS - ĐV]],3,0) -> Food Đức Việt
A14: =ROW()-1 -> 13 | B14: POST 06 - Bếp vui, Giá tốt mỗi ngày | C14: Toàn bộ | D14: Toàn quốc | E14: 05/03/2026 | F14: 01/04/2026 | G14: 8935101600380 | H14: =VLOOKUP(gia_khuyen_mai[[#This Row],[Barcode]],'Giá gốc'!$A:$B,2,0) -> 2145690 | I14: =VLOOKUP(gia_khuyen_mai[[#This Row],[Mã sản phẩm]],'Giá gốc'!$B:$C,2,0) -> Xúc xích vườn bia 200g * 1EA | J14: =VLOOKUP(gia_khuyen_mai[[#This Row],[Mã sản phẩm]],'Giá gốc'!B:D,3,0) -> 38400 | K14: 0.2 | L14: =ROUND((1-gia_khuyen_mai[[#This Row],[% Giảm giá]]) * gia_khuyen_mai[[#This Row],[Giá gốc]], 0) -> 30720 | O14: =IFERROR(VLOOKUP(gia_khuyen_mai[[#This Row],[Mã hàng tặng]],'Giá gốc'!B:C,2,0),"") | Q14: =VLOOKUP(gia_khuyen_mai[[#This Row],[Mã sản phẩm]],product[[Mã sản phẩm]:[DS - ĐV]],3,0) -> Food Đức Việt
A15: =ROW()-1 -> 14 | B15: POST 06 - Bếp vui, Giá tốt mỗi ngày | C15: Toàn bộ | D15: Toàn quốc | E15: 05/03/2026 | F15: 01/04/2026 | G15: 8935101604913 | H15: =VLOOKUP(gia_khuyen_mai[[#This Row],[Barcode]],'Giá gốc'!$A:$B,2,0) -> 2145762 | I15: =VLOOKUP(gia_khuyen_mai[[#This Row],[Mã sản phẩm]],'Giá gốc'!$B:$C,2,0) -> Xúc xích Cocktail 200g | J15: =VLOOKUP(gia_khuyen_mai[[#This Row],[Mã sản phẩm]],'Giá gốc'!B:D,3,0) -> 21100 | K15: 0.2 | L15: =ROUND((1-gia_khuyen_mai[[#This Row],[% Giảm giá]]) * gia_khuyen_mai[[#This Row],[Giá gốc]], 0) -> 16880 | O15: =IFERROR(VLOOKUP(gia_khuyen_mai[[#This Row],[Mã hàng tặng]],'Giá gốc'!B:C,2,0),"") | Q15: =VLOOKUP(gia_khuyen_mai[[#This Row],[Mã sản phẩm]],product[[Mã sản phẩm]:[DS - ĐV]],3,0) -> Food Đức Việt
A16: =ROW()-1 -> 15 | B16: POST 06 - Bếp vui, Giá tốt mỗi ngày | C16: Toàn bộ | D16: Toàn quốc | E16: 05/03/2026 | F16: 31/03/2026 | G16: 8935101608461 | H16: =VLOOKUP(gia_khuyen_mai[[#This Row],[Barcode]],'Giá gốc'!$A:$B,2,0) -> 2150338 | I16: =VLOOKUP(gia_khuyen_mai[[#This Row],[Mã sản phẩm]],'Giá gốc'!$B:$C,2,0) -> O'food Chả giò da xốp hải sản 300g | J16: =VLOOKUP(gia_khuyen_mai[[#This Row],[Mã sản phẩm]],'Giá gốc'!B:D,3,0) -> 31524 | K16: 0.3 | L16: =ROUND((1-gia_khuyen_mai[[#This Row],[% Giảm giá]]) * gia_khuyen_mai[[#This Row],[Giá gốc]], 0) -> 22067 | O16: =IFERROR(VLOOKUP(gia_khuyen_mai[[#This Row],[Mã hàng tặng]],'Giá gốc'!B:C,2,0),"") | Q16: =VLOOKUP(gia_khuyen_mai[[#This Row],[Mã sản phẩm]],product[[Mã sản phẩm]:[DS - ĐV]],3,0) -> Food Đức Việt
A17: =ROW()-1 -> 16 | B17: POST 06 - Bếp vui, Giá tốt mỗi ngày | C17: Toàn bộ | D17: Toàn quốc | E17: 05/03/2026 | F17: 01/04/2026 | G17: 8935101600427 | H17: =VLOOKUP(gia_khuyen_mai[[#This Row],[Barcode]],'Giá gốc'!$A:$B,2,0) -> 2145691 | I17: =VLOOKUP(gia_khuyen_mai[[#This Row],[Mã sản phẩm]],'Giá gốc'!$B:$C,2,0) -> Xúc xích viên hong khói 450g * 1EA | J17: =VLOOKUP(gia_khuyen_mai[[#This Row],[Mã sản phẩm]],'Giá gốc'!B:D,3,0) -> 84200 | L17: =ROUND((1-gia_khuyen_mai[[#This Row],[% Giảm giá]]) * gia_khuyen_mai[[#This Row],[Giá gốc]], 0) -> 84200 | M17: Mua 1 tặng 1 | N17: 2145765 | O17: =IFERROR(VLOOKUP(gia_khuyen_mai[[#This Row],[Mã hàng tặng]],'Giá gốc'!B:C,2,0),"") -> Xúc xích Hotdog 200g | Q17: =VLOOKUP(gia_khuyen_mai[[#This Row],[Mã sản phẩm]],product[[Mã sản phẩm]:[DS - ĐV]],3,0) -> Food Đức Việt
A18: =ROW()-1 -> 17 | B18: POST 07 | C18: Toàn bộ | D18: Toàn quốc | E18: 18/03/2026 | F18: 15/04/2026 | G18: 8935101600625 | H18: =VLOOKUP(gia_khuyen_mai[[#This Row],[Barcode]],'Giá gốc'!$A:$B,2,0) -> 2145689 | I18: =VLOOKUP(gia_khuyen_mai[[#This Row],[Mã sản phẩm]],'Giá gốc'!$B:$C,2,0) -> Xúc xích vườn bia 450g * 1EA | J18: =VLOOKUP(gia_khuyen_mai[[#This Row],[Mã sản phẩm]],'Giá gốc'!B:D,3,0) -> 84200 | L18: =ROUND((1-gia_khuyen_mai[[#This Row],[% Giảm giá]]) * gia_khuyen_mai[[#This Row],[Giá gốc]], 0) -> 84200 | M18: Mua 1 tặng 1 | N18: 2145765 | O18: =IFERROR(VLOOKUP(gia_khuyen_mai[[#This Row],[Mã hàng tặng]],'Giá gốc'!B:C,2,0),"") -> Xúc xích Hotdog 200g | Q18: =VLOOKUP(gia_khuyen_mai[[#This Row],[Mã sản phẩm]],product[[Mã sản phẩm]:[DS - ĐV]],3,0) -> Food Đức Việt
A19: =ROW()-1 -> 18 | B19: POST 07 | C19: Toàn bộ | D19: Toàn quốc | E19: 18/03/2026 | F19: 15/04/2026 | G19: 8935101608072 | H19: =VLOOKUP(gia_khuyen_mai[[#This Row],[Barcode]],'Giá gốc'!$A:$B,2,0) -> 2145743 | I19: =VLOOKUP(gia_khuyen_mai[[#This Row],[Mã sản phẩm]],'Giá gốc'!$B:$C,2,0) -> Xúc xích sụn nướng Bulgogi 450g | J19: =VLOOKUP(gia_khuyen_mai[[#This Row],[Mã sản phẩm]],'Giá gốc'!B:D,3,0) -> 74500 | K19: 0.3 | L19: =ROUND((1-gia_khuyen_mai[[#This Row],[% Giảm giá]]) * gia_khuyen_mai[[#This Row],[Giá gốc]], 0) -> 52150 | O19: =IFERROR(VLOOKUP(gia_khuyen_mai[[#This Row],[Mã hàng tặng]],'Giá gốc'!B:C,2,0),"") | Q19: =VLOOKUP(gia_khuyen_mai[[#This Row],[Mã sản phẩm]],product[[Mã sản phẩm]:[DS - ĐV]],3,0) -> Food Đức Việt
A20: =ROW()-1 -> 19 | B20: POST 07 | C20: Toàn bộ | D20: Toàn quốc | E20: 18/03/2026 | F20: 15/04/2026 | G20: 8935101600366 | H20: =VLOOKUP(gia_khuyen_mai[[#This Row],[Barcode]],'Giá gốc'!$A:$B,2,0) -> 2145688 | I20: =VLOOKUP(gia_khuyen_mai[[#This Row],[Mã sản phẩm]],'Giá gốc'!$B:$C,2,0) -> Xúc xích hong khói 200g * 1EA | J20: =VLOOKUP(gia_khuyen_mai[[#This Row],[Mã sản phẩm]],'Giá gốc'!B:D,3,0) -> 35200 | K20: 0.2 | L20: =ROUND((1-gia_khuyen_mai[[#This Row],[% Giảm giá]]) * gia_khuyen_mai[[#This Row],[Giá gốc]], 0) -> 28160 | O20: =IFERROR(VLOOKUP(gia_khuyen_mai[[#This Row],[Mã hàng tặng]],'Giá gốc'!B:C,2,0),"") | Q20: =VLOOKUP(gia_khuyen_mai[[#This Row],[Mã sản phẩm]],product[[Mã sản phẩm]:[DS - ĐV]],3,0) -> Food Đức Việt
A21: =ROW()-1 -> 20 | B21: POST 07 | C21: Toàn bộ | D21: Toàn quốc | E21: 18/03/2026 | F21: 15/04/2026 | G21: 8935101607105 | H21: =VLOOKUP(gia_khuyen_mai[[#This Row],[Barcode]],'Giá gốc'!$A:$B,2,0) -> 2145648 | I21: =VLOOKUP(gia_khuyen_mai[[#This Row],[Mã sản phẩm]],'Giá gốc'!$B:$C,2,0) -> Đức Việt Handy - xúc xích ăn liền vị heo 105g * 20EA | J21: =VLOOKUP(gia_khuyen_mai[[#This Row],[Mã sản phẩm]],'Giá gốc'!B:D,3,0) -> 9300 | K21: 0.22 | L21: =ROUND((1-gia_khuyen_mai[[#This Row],[% Giảm giá]]) * gia_khuyen_mai[[#This Row],[Giá gốc]], 0) -> 7254 | O21: =IFERROR(VLOOKUP(gia_khuyen_mai[[#This Row],[Mã hàng tặng]],'Giá gốc'!B:C,2,0),"") | Q21: =VLOOKUP(gia_khuyen_mai[[#This Row],[Mã sản phẩm]],product[[Mã sản phẩm]:[DS - ĐV]],3,0) -> Food Đức Việt
A22: =ROW()-1 -> 21 | B22: POST 07 | C22: Toàn bộ | D22: Toàn quốc | E22: 18/03/2026 | F22: 15/04/2026 | G22: 8935101607129 | H22: =VLOOKUP(gia_khuyen_mai[[#This Row],[Barcode]],'Giá gốc'!$A:$B,2,0) -> 2145657 | I22: =VLOOKUP(gia_khuyen_mai[[#This Row],[Mã sản phẩm]],'Giá gốc'!$B:$C,2,0) -> Đức Việt Handy - xúc xích ăn liền vị bò 105g * 20EA | J22: =VLOOKUP(gia_khuyen_mai[[#This Row],[Mã sản phẩm]],'Giá gốc'!B:D,3,0) -> 9300 | K22: 0.22 | L22: =ROUND((1-gia_khuyen_mai[[#This Row],[% Giảm giá]]) * gia_khuyen_mai[[#This Row],[Giá gốc]], 0) -> 7254 | O22: =IFERROR(VLOOKUP(gia_khuyen_mai[[#This Row],[Mã hàng tặng]],'Giá gốc'!B:C,2,0),"") | Q22: =VLOOKUP(gia_khuyen_mai[[#This Row],[Mã sản phẩm]],product[[Mã sản phẩm]:[DS - ĐV]],3,0) -> Food Đức Việt
A23: =ROW()-1 -> 22 | B23: POST 07 | C23: Toàn bộ | D23: Toàn quốc | E23: 18/03/2026 | F23: 15/04/2026 | G23: 8935101601028 | H23: =VLOOKUP(gia_khuyen_mai[[#This Row],[Barcode]],'Giá gốc'!$A:$B,2,0) -> 2145735 | I23: =VLOOKUP(gia_khuyen_mai[[#This Row],[Mã sản phẩm]],'Giá gốc'!$B:$C,2,0) -> Xúc xích tỏi 200g | J23: =VLOOKUP(gia_khuyen_mai[[#This Row],[Mã sản phẩm]],'Giá gốc'!B:D,3,0) -> 37000 | K23: 0.15 | L23: =ROUND((1-gia_khuyen_mai[[#This Row],[% Giảm giá]]) * gia_khuyen_mai[[#This Row],[Giá gốc]], 0) -> 31450 | O23: =IFERROR(VLOOKUP(gia_khuyen_mai[[#This Row],[Mã hàng tặng]],'Giá gốc'!B:C,2,0),"") | Q23: =VLOOKUP(gia_khuyen_mai[[#This Row],[Mã sản phẩm]],product[[Mã sản phẩm]:[DS - ĐV]],3,0) -> Food Đức Việt
A24: =ROW()-1 -> 23 | B24: POST 07 | C24: Toàn bộ | D24: Toàn quốc | E24: 18/03/2026 | F24: 15/04/2026 | G24: 8935101606078 | H24: =VLOOKUP(gia_khuyen_mai[[#This Row],[Barcode]],'Giá gốc'!$A:$B,2,0) -> 2145695 | I24: =VLOOKUP(gia_khuyen_mai[[#This Row],[Mã sản phẩm]],'Giá gốc'!$B:$C,2,0) -> Seoul's Hotdog 350g | J24: =VLOOKUP(gia_khuyen_mai[[#This Row],[Mã sản phẩm]],'Giá gốc'!B:D,3,0) -> 48384 | K24: 0.25 | L24: =ROUND((1-gia_khuyen_mai[[#This Row],[% Giảm giá]]) * gia_khuyen_mai[[#This Row],[Giá gốc]], 0) -> 36288 | O24: =IFERROR(VLOOKUP(gia_khuyen_mai[[#This Row],[Mã hàng tặng]],'Giá gốc'!B:C,2,0),"") | Q24: =VLOOKUP(gia_khuyen_mai[[#This Row],[Mã sản phẩm]],product[[Mã sản phẩm]:[DS - ĐV]],3,0) -> Food Đức Việt
A25: =ROW()-1 -> 24 | B25: POST 07 | C25: Toàn bộ | D25: Toàn quốc | E25: 18/03/2026 | F25: 15/04/2026 | G25: 8935101607099 | H25: =VLOOKUP(gia_khuyen_mai[[#This Row],[Barcode]],'Giá gốc'!$A:$B,2,0) -> 2145697 | I25: =VLOOKUP(gia_khuyen_mai[[#This Row],[Mã sản phẩm]],'Giá gốc'!$B:$C,2,0) -> Seoul nhân phô mai 250g | J25: =VLOOKUP(gia_khuyen_mai[[#This Row],[Mã sản phẩm]],'Giá gốc'!B:D,3,0) -> 42000 | K25: 0.25 | L25: =ROUND((1-gia_khuyen_mai[[#This Row],[% Giảm giá]]) * gia_khuyen_mai[[#This Row],[Giá gốc]], 0) -> 31500 | O25: =IFERROR(VLOOKUP(gia_khuyen_mai[[#This Row],[Mã hàng tặng]],'Giá gốc'!B:C,2,0),"") | Q25: =VLOOKUP(gia_khuyen_mai[[#This Row],[Mã sản phẩm]],product[[Mã sản phẩm]:[DS - ĐV]],3,0) -> Food Đức Việt
A26: =ROW()-1 -> 25 | B26: POST 07 | C26: Toàn bộ | D26: Toàn quốc | E26: 18/03/2026 | F26: 15/04/2026 | G26: 8935101607952 | H26: =VLOOKUP(gia_khuyen_mai[[#This Row],[Barcode]],'Giá gốc'!$A:$B,2,0) -> 2145740 | I26: =VLOOKUP(gia_khuyen_mai[[#This Row],[Mã sản phẩm]],'Giá gốc'!$B:$C,2,0) -> Xúc xích phô mai Cheesy 70g * 30EA | J26: =VLOOKUP(gia_khuyen_mai[[#This Row],[Mã sản phẩm]],'Giá gốc'!B:D,3,0) -> 17100 | K26: 0.2 | L26: =ROUND((1-gia_khuyen_mai[[#This Row],[% Giảm giá]]) * gia_khuyen_mai[[#This Row],[Giá gốc]], 0) -> 13680 | O26: =IFERROR(VLOOKUP(gia_khuyen_mai[[#This Row],[Mã hàng tặng]],'Giá gốc'!B:C,2,0),"") | Q26: =VLOOKUP(gia_khuyen_mai[[#This Row],[Mã sản phẩm]],product[[Mã sản phẩm]:[DS - ĐV]],3,0) -> Food Đức Việt
A27: =ROW()-1 -> 26 | B27: POST 07 | C27: Toàn bộ | D27: Toàn quốc | E27: 18/03/2026 | F27: 15/04/2026 | G27: 8935101607969 | H27: =VLOOKUP(gia_khuyen_mai[[#This Row],[Barcode]],'Giá gốc'!$A:$B,2,0) -> 2145791 | I27: =VLOOKUP(gia_khuyen_mai[[#This Row],[Mã sản phẩm]],'Giá gốc'!$B:$C,2,0) -> Xúc xích Romas 70g * 30EA | J27: =VLOOKUP(gia_khuyen_mai[[#This Row],[Mã sản phẩm]],'Giá gốc'!B:D,3,0) -> 13100 | K27: 0.2 | L27: =ROUND((1-gia_khuyen_mai[[#This Row],[% Giảm giá]]) * gia_khuyen_mai[[#This Row],[Giá gốc]], 0) -> 10480 | O27: =IFERROR(VLOOKUP(gia_khuyen_mai[[#This Row],[Mã hàng tặng]],'Giá gốc'!B:C,2,0),"") | Q27: =VLOOKUP(gia_khuyen_mai[[#This Row],[Mã sản phẩm]],product[[Mã sản phẩm]:[DS - ĐV]],3,0) -> Food Đức Việt
A28: =ROW()-1 -> 27 | B28: POST 07 | C28: Toàn bộ | D28: Toàn quốc | E28: 18/03/2026 | F28: 15/04/2026 | G28: 8935101605804 | H28: =VLOOKUP(gia_khuyen_mai[[#This Row],[Barcode]],'Giá gốc'!$A:$B,2,0) -> 2145767 | I28: =VLOOKUP(gia_khuyen_mai[[#This Row],[Mã sản phẩm]],'Giá gốc'!$B:$C,2,0) -> Xúc xích Mỹ 500g | J28: =VLOOKUP(gia_khuyen_mai[[#This Row],[Mã sản phẩm]],'Giá gốc'!B:D,3,0) -> 55600 | K28: 0.22 | L28: =ROUND((1-gia_khuyen_mai[[#This Row],[% Giảm giá]]) * gia_khuyen_mai[[#This Row],[Giá gốc]], 0) -> 43368 | O28: =IFERROR(VLOOKUP(gia_khuyen_mai[[#This Row],[Mã hàng tặng]],'Giá gốc'!B:C,2,0),"") | Q28: =VLOOKUP(gia_khuyen_mai[[#This Row],[Mã sản phẩm]],product[[Mã sản phẩm]:[DS - ĐV]],3,0) -> Food Đức Việt
A29: =ROW()-1 -> 28 | B29: POST 08 | C29: Toàn bộ | D29: Toàn quốc | E29: 01/04/2026 | F29: 03/05/2026 | G29: 8935101604180 | H29: =VLOOKUP(gia_khuyen_mai[[#This Row],[Barcode]],'Giá gốc'!$A:$B,2,0) -> 2146417 | I29: =VLOOKUP(gia_khuyen_mai[[#This Row],[Mã sản phẩm]],'Giá gốc'!$B:$C,2,0) -> Chân giò hong khói rút xương 300g | J29: =VLOOKUP(gia_khuyen_mai[[#This Row],[Mã sản phẩm]],'Giá gốc'!B:D,3,0) -> 67700 | K29: 0.2 | L29: =ROUND((1-gia_khuyen_mai[[#This Row],[% Giảm giá]]) * gia_khuyen_mai[[#This Row],[Giá gốc]], 0) -> 54160 | O29: =IFERROR(VLOOKUP(gia_khuyen_mai[[#This Row],[Mã hàng tặng]],'Giá gốc'!B:C,2,0),"") | Q29: =VLOOKUP(gia_khuyen_mai[[#This Row],[Mã sản phẩm]],product[[Mã sản phẩm]:[DS - ĐV]],3,0) -> Food Đức Việt
A30: =ROW()-1 -> 29 | B30: POST 08 | C30: Toàn bộ | D30: Toàn quốc | E30: 01/04/2026 | F30: 03/05/2026 | G30: 8935101600960 | H30: =VLOOKUP(gia_khuyen_mai[[#This Row],[Barcode]],'Giá gốc'!$A:$B,2,0) -> 2145745 | I30: =VLOOKUP(gia_khuyen_mai[[#This Row],[Mã sản phẩm]],'Giá gốc'!$B:$C,2,0) -> Jăm bông hấp 200g | J30: =VLOOKUP(gia_khuyen_mai[[#This Row],[Mã sản phẩm]],'Giá gốc'!B:D,3,0) -> 37000 | K30: 0.15 | L30: =ROUND((1-gia_khuyen_mai[[#This Row],[% Giảm giá]]) * gia_khuyen_mai[[#This Row],[Giá gốc]], 0) -> 31450 | O30: =IFERROR(VLOOKUP(gia_khuyen_mai[[#This Row],[Mã hàng tặng]],'Giá gốc'!B:C,2,0),"") | Q30: =VLOOKUP(gia_khuyen_mai[[#This Row],[Mã sản phẩm]],product[[Mã sản phẩm]:[DS - ĐV]],3,0) -> Food Đức Việt
... A48: =ROW()-1 -> 47 | B48: Mã mới | C48: Winmart | D48: Toàn quốc | E48: 09/04/2026 | F48: 13/05/2026 | G48: 8935101608126 | H48: =VLOOKUP(gia_khuyen_mai[[#This Row],[Barcode]],'Giá gốc'!$A:$B,2,0) -> 2145625 | I48: =VLOOKUP(gia_khuyen_mai[[#This Row],[Mã sản phẩm]],'Giá gốc'!$B:$C,2,0) -> Jongga Kim chi cải thảo cắt lát 1kg | J48: =VLOOKUP(gia_khuyen_mai[[#This Row],[Mã sản phẩm]],'Giá gốc'!B:D,3,0) -> 70000 | K48: 0.33 | L48: =ROUND((1-gia_khuyen_mai[[#This Row],[% Giảm giá]]) * gia_khuyen_mai[[#This Row],[Giá gốc]], 0) -> 46900 | O48: =IFERROR(VLOOKUP(gia_khuyen_mai[[#This Row],[Mã hàng tặng]],'Giá gốc'!B:C,2,0),"") | Q48: =VLOOKUP(gia_khuyen_mai[[#This Row],[Mã sản phẩm]],product[[Mã sản phẩm]:[DS - ĐV]],3,0) -> Food Đức Việt
A49: =ROW()-1 -> 48 | B49: Mã mới | C49: Winmart | D49: Toàn quốc | E49: 09/04/2026 | F49: 13/05/2026 | G49: 8935101608515 | H49: =VLOOKUP(gia_khuyen_mai[[#This Row],[Barcode]],'Giá gốc'!$A:$B,2,0) -> 2151032 | I49: =VLOOKUP(gia_khuyen_mai[[#This Row],[Mã sản phẩm]],'Giá gốc'!$B:$C,2,0) -> Jongga Kim chi Củ cải 450g | J49: =VLOOKUP(gia_khuyen_mai[[#This Row],[Mã sản phẩm]],'Giá gốc'!B:D,3,0) -> 42000 | L49: =ROUND((1-gia_khuyen_mai[[#This Row],[% Giảm giá]]) * gia_khuyen_mai[[#This Row],[Giá gốc]], 0) -> 42000 | M49: Mua 1 tặng 1 | N49: =VLOOKUP(gia_khuyen_mai[[#This Row],[Barcode]],'Giá gốc'!$A:$B,2,0) -> 2151032 | O49: =IFERROR(VLOOKUP(gia_khuyen_mai[[#This Row],[Mã hàng tặng]],'Giá gốc'!B:C,2,0),"") -> Jongga Kim chi Củ cải 450g | Q49: =VLOOKUP(gia_khuyen_mai[[#This Row],[Mã sản phẩm]],product[[Mã sản phẩm]:[DS - ĐV]],3,0) -> Food Đức Việt
A50: =ROW()-1 -> 49 | B50: Mã mới | C50: Winmart | D50: Toàn quốc | E50: 09/04/2026 | F50: 13/05/2026 | G50: 8935101608522 | H50: =VLOOKUP(gia_khuyen_mai[[#This Row],[Barcode]],'Giá gốc'!$A:$B,2,0) -> 2151140 | I50: =VLOOKUP(gia_khuyen_mai[[#This Row],[Mã sản phẩm]],'Giá gốc'!$B:$C,2,0) -> Jongga Kim chi Củ cải 150g | J50: =VLOOKUP(gia_khuyen_mai[[#This Row],[Mã sản phẩm]],'Giá gốc'!B:D,3,0) -> 16500 | K50: 0.33 | L50: =ROUND((1-gia_khuyen_mai[[#This Row],[% Giảm giá]]) * gia_khuyen_mai[[#This Row],[Giá gốc]], 0) -> 11055 | O50: =IFERROR(VLOOKUP(gia_khuyen_mai[[#This Row],[Mã hàng tặng]],'Giá gốc'!B:C,2,0),"") | Q50: =VLOOKUP(gia_khuyen_mai[[#This Row],[Mã sản phẩm]],product[[Mã sản phẩm]:[DS - ĐV]],3,0) -> Food Đức Việt
A51: =ROW()-1 -> 50 | B51: Mã mới | C51: Winmart | D51: Toàn quốc | E51: 09/04/2026 | F51: 13/05/2026 | G51: 8935101608546 | H51: =VLOOKUP(gia_khuyen_mai[[#This Row],[Barcode]],'Giá gốc'!$A:$B,2,0) -> 2151765 | I51: =VLOOKUP(gia_khuyen_mai[[#This Row],[Mã sản phẩm]],'Giá gốc'!$B:$C,2,0) -> Ức gà hong khói 100g | J51: =VLOOKUP(gia_khuyen_mai[[#This Row],[Mã sản phẩm]],'Giá gốc'!B:D,3,0) -> 26000 | K51: 0.25 | L51: =ROUND((1-gia_khuyen_mai[[#This Row],[% Giảm giá]]) * gia_khuyen_mai[[#This Row],[Giá gốc]], 0) -> 19500 | O51: =IFERROR(VLOOKUP(gia_khuyen_mai[[#This Row],[Mã hàng tặng]],'Giá gốc'!B:C,2,0),"") | Q51: =VLOOKUP(gia_khuyen_mai[[#This Row],[Mã sản phẩm]],product[[Mã sản phẩm]:[DS - ĐV]],3,0) -> Food Đức Việt
A52: =ROW()-1 -> 51 | B52: Mã mới | C52: Winmart | D52: Toàn quốc | E52: 09/04/2026 | F52: 13/05/2026 | G52: 8935101607945 | H52: =VLOOKUP(gia_khuyen_mai[[#This Row],[Barcode]],'Giá gốc'!$A:$B,2,0) -> 2145747 | I52: =VLOOKUP(gia_khuyen_mai[[#This Row],[Mã sản phẩm]],'Giá gốc'!$B:$C,2,0) -> Xúc xích thịt heo Bragenwurst 400g | J52: =VLOOKUP(gia_khuyen_mai[[#This Row],[Mã sản phẩm]],'Giá gốc'!B:D,3,0) -> 82080 | K52: 0.3 | L52: =ROUND((1-gia_khuyen_mai[[#This Row],[% Giảm giá]]) * gia_khuyen_mai[[#This Row],[Giá gốc]], 0) -> 57456 | O52: =IFERROR(VLOOKUP(gia_khuyen_mai[[#This Row],[Mã hàng tặng]],'Giá gốc'!B:C,2,0),"") | Q52: =VLOOKUP(gia_khuyen_mai[[#This Row],[Mã sản phẩm]],product[[Mã sản phẩm]:[DS - ĐV]],3,0) -> Food Đức Việt
A53: =ROW()-1 -> 52 | B53: Mã mới | C53: Winmart | D53: Toàn quốc | E53: 09/04/2026 | F53: 13/05/2026 | G53: 8935101607976 | H53: =VLOOKUP(gia_khuyen_mai[[#This Row],[Barcode]],'Giá gốc'!$A:$B,2,0) -> 2145682 | I53: =VLOOKUP(gia_khuyen_mai[[#This Row],[Mã sản phẩm]],'Giá gốc'!$B:$C,2,0) -> O'Food - Xúc xích xốt Spaghetti 64g | J53: =VLOOKUP(gia_khuyen_mai[[#This Row],[Mã sản phẩm]],'Giá gốc'!B:D,3,0) -> 8837 | L53: =ROUND((1-gia_khuyen_mai[[#This Row],[% Giảm giá]]) * gia_khuyen_mai[[#This Row],[Giá gốc]], 0) -> 8837 | M53: Mua 1 tặng 1 | N53: =VLOOKUP(gia_khuyen_mai[[#This Row],[Barcode]],'Giá gốc'!$A:$B,2,0) -> 2145682 | O53: =IFERROR(VLOOKUP(gia_khuyen_mai[[#This Row],[Mã hàng tặng]],'Giá gốc'!B:C,2,0),"") -> O'Food - Xúc xích xốt Spaghetti 64g | Q53: =VLOOKUP(gia_khuyen_mai[[#This Row],[Mã sản phẩm]],product[[Mã sản phẩm]:[DS - ĐV]],3,0) -> Food Đức Việt
A54: =ROW()-1 -> 53 | B54: Mã mới | C54: Winmart | D54: Toàn quốc | E54: 09/04/2026 | F54: 13/05/2026 | G54: 8935101607990 | H54: =VLOOKUP(gia_khuyen_mai[[#This Row],[Barcode]],'Giá gốc'!$A:$B,2,0) -> 2145684 | I54: =VLOOKUP(gia_khuyen_mai[[#This Row],[Mã sản phẩm]],'Giá gốc'!$B:$C,2,0) -> O'Food - Xúc xích xốt Tokpokki vị phô mai Hàn Quốc 64g | J54: =VLOOKUP(gia_khuyen_mai[[#This Row],[Mã sản phẩm]],'Giá gốc'!B:D,3,0) -> 8837 | L54: =ROUND((1-gia_khuyen_mai[[#This Row],[% Giảm giá]]) * gia_khuyen_mai[[#This Row],[Giá gốc]], 0) -> 8837 | M54: Mua 1 tặng 1 | N54: =VLOOKUP(gia_khuyen_mai[[#This Row],[Barcode]],'Giá gốc'!$A:$B,2,0) -> 2145684 | O54: =IFERROR(VLOOKUP(gia_khuyen_mai[[#This Row],[Mã hàng tặng]],'Giá gốc'!B:C,2,0),"") -> O'Food - Xúc xích xốt Tokpokki vị phô mai Hàn Quốc 64g | Q54: =VLOOKUP(gia_khuyen_mai[[#This Row],[Mã sản phẩm]],product[[Mã sản phẩm]:[DS - ĐV]],3,0) -> Food Đức Việt
A55: =ROW()-1 -> 54 | B55: Mã mới | C55: Winmart | D55: Toàn quốc | E55: 09/04/2026 | F55: 13/05/2026 | G55: 8935101608492 | H55: =VLOOKUP(gia_khuyen_mai[[#This Row],[Barcode]],'Giá gốc'!$A:$B,2,0) -> 2149794 | I55: =VLOOKUP(gia_khuyen_mai[[#This Row],[Mã sản phẩm]],'Giá gốc'!$B:$C,2,0) -> Xúc xích Romas Light 500g | J55: =VLOOKUP(gia_khuyen_mai[[#This Row],[Mã sản phẩm]],'Giá gốc'!B:D,3,0) -> 44000 | L55: =ROUND((1-gia_khuyen_mai[[#This Row],[% Giảm giá]]) * gia_khuyen_mai[[#This Row],[Giá gốc]], 0) -> 44000 | M55: Mua 1 tặng 1 | N55: 2145740 | O55: =IFERROR(VLOOKUP(gia_khuyen_mai[[#This Row],[Mã hàng tặng]],'Giá gốc'!B:C,2,0),"") -> Xúc xích phô mai Cheesy 70g * 30EA | Q55: =VLOOKUP(gia_khuyen_mai[[#This Row],[Mã sản phẩm]],product[[Mã sản phẩm]:[DS - ĐV]],3,0) -> Food Đức Việt
A56: =ROW()-1 -> 55 | B56: Mã mới | C56: Win+ | D56: Toàn quốc | E56: 11/05/2026 | F56: 09/06/2026 | G56: 8935101608515 | H56: =VLOOKUP(gia_khuyen_mai[[#This Row],[Barcode]],'Giá gốc'!$A:$B,2,0) -> 2151032 | I56: =VLOOKUP(gia_khuyen_mai[[#This Row],[Mã sản phẩm]],'Giá gốc'!$B:$C,2,0) -> Jongga Kim chi Củ cải 450g | J56: =VLOOKUP(gia_khuyen_mai[[#This Row],[Mã sản phẩm]],'Giá gốc'!B:D,3,0) -> 42000 | L56: =ROUND((1-gia_khuyen_mai[[#This Row],[% Giảm giá]]) * gia_khuyen_mai[[#This Row],[Giá gốc]], 0) -> 42000 | M56: Mua 1 tặng 1 | N56: =VLOOKUP(gia_khuyen_mai[[#This Row],[Barcode]],'Giá gốc'!$A:$B,2,0) -> 2151032 | O56: =IFERROR(VLOOKUP(gia_khuyen_mai[[#This Row],[Mã hàng tặng]],'Giá gốc'!B:C,2,0),"") -> Jongga Kim chi Củ cải 450g | Q56: =VLOOKUP(gia_khuyen_mai[[#This Row],[Mã sản phẩm]],product[[Mã sản phẩm]:[DS - ĐV]],3,0) -> Food Đức Việt
A57: =ROW()-1 -> 56 | B57: Mã mới | C57: Win+ | D57: Toàn quốc | E57: 27/05/2026 | F57: 24/06/2026 | G57: 8935101608522 | H57: =VLOOKUP(gia_khuyen_mai[[#This Row],[Barcode]],'Giá gốc'!$A:$B,2,0) -> 2151140 | I57: =VLOOKUP(gia_khuyen_mai[[#This Row],[Mã sản phẩm]],'Giá gốc'!$B:$C,2,0) -> Jongga Kim chi Củ cải 150g | J57: =VLOOKUP(gia_khuyen_mai[[#This Row],[Mã sản phẩm]],'Giá gốc'!B:D,3,0) -> 16500 | K57: 0.33 | L57: =ROUND((1-gia_khuyen_mai[[#This Row],[% Giảm giá]]) * gia_khuyen_mai[[#This Row],[Giá gốc]], 0) -> 11055 | O57: =IFERROR(VLOOKUP(gia_khuyen_mai[[#This Row],[Mã hàng tặng]],'Giá gốc'!B:C,2,0),"") | Q57: =VLOOKUP(gia_khuyen_mai[[#This Row],[Mã sản phẩm]],product[[Mã sản phẩm]:[DS - ĐV]],3,0) -> Food Đức Việt
A58: =ROW()-1 -> 57 | B58: Mã mới | C58: Win+ | D58: Toàn quốc | E58: 24/04/2026 | F58: 09/06/2026 | G58: 8935101608546 | H58: =VLOOKUP(gia_khuyen_mai[[#This Row],[Barcode]],'Giá gốc'!$A:$B,2,0) -> 2151765 | I58: =VLOOKUP(gia_khuyen_mai[[#This Row],[Mã sản phẩm]],'Giá gốc'!$B:$C,2,0) -> Ức gà hong khói 100g | J58: =VLOOKUP(gia_khuyen_mai[[#This Row],[Mã sản phẩm]],'Giá gốc'!B:D,3,0) -> 26000 | K58: 0.25 | L58: =ROUND((1-gia_khuyen_mai[[#This Row],[% Giảm giá]]) * gia_khuyen_mai[[#This Row],[Giá gốc]], 0) -> 19500 | O58: =IFERROR(VLOOKUP(gia_khuyen_mai[[#This Row],[Mã hàng tặng]],'Giá gốc'!B:C,2,0),"") | Q58: =VLOOKUP(gia_khuyen_mai[[#This Row],[Mã sản phẩm]],product[[Mã sản phẩm]:[DS - ĐV]],3,0) -> Food Đức Việt
A59: =ROW()-1 -> 58 | B59: Mã mới | C59: Win+ | D59: Toàn quốc | E59: 24/04/2026 | F59: 27/05/2026 | G59: 8935101607945 | H59: =VLOOKUP(gia_khuyen_mai[[#This Row],[Barcode]],'Giá gốc'!$A:$B,2,0) -> 2145747 | I59: =VLOOKUP(gia_khuyen_mai[[#This Row],[Mã sản phẩm]],'Giá gốc'!$B:$C,2,0) -> Xúc xích thịt heo Bragenwurst 400g | J59: =VLOOKUP(gia_khuyen_mai[[#This Row],[Mã sản phẩm]],'Giá gốc'!B:D,3,0) -> 82080 | K59: 0.3 | L59: =ROUND((1-gia_khuyen_mai[[#This Row],[% Giảm giá]]) * gia_khuyen_mai[[#This Row],[Giá gốc]], 0) -> 57456 | O59: =IFERROR(VLOOKUP(gia_khuyen_mai[[#This Row],[Mã hàng tặng]],'Giá gốc'!B:C,2,0),"") | Q59: =VLOOKUP(gia_khuyen_mai[[#This Row],[Mã sản phẩm]],product[[Mã sản phẩm]:[DS - ĐV]],3,0) -> Food Đức Việt
A60: =ROW()-1 -> 59 | B60: Mã mới | C60: Win+ | D60: Toàn quốc | E60: 14/05/2026 | F60: 24/06/2026 | G60: 8935101607976 | H60: =VLOOKUP(gia_khuyen_mai[[#This Row],[Barcode]],'Giá gốc'!$A:$B,2,0) -> 2145682 | I60: =VLOOKUP(gia_khuyen_mai[[#This Row],[Mã sản phẩm]],'Giá gốc'!$B:$C,2,0) -> O'Food - Xúc xích xốt Spaghetti 64g | J60: =VLOOKUP(gia_khuyen_mai[[#This Row],[Mã sản phẩm]],'Giá gốc'!B:D,3,0) -> 8837 | L60: =ROUND((1-gia_khuyen_mai[[#This Row],[% Giảm giá]]) * gia_khuyen_mai[[#This Row],[Giá gốc]], 0) -> 8837 | M60: Mua 1 tặng 1 | N60: =VLOOKUP(gia_khuyen_mai[[#This Row],[Barcode]],'Giá gốc'!$A:$B,2,0) -> 2145682 | O60: =IFERROR(VLOOKUP(gia_khuyen_mai[[#This Row],[Mã hàng tặng]],'Giá gốc'!B:C,2,0),"") -> O'Food - Xúc xích xốt Spaghetti 64g | Q60: =VLOOKUP(gia_khuyen_mai[[#This Row],[Mã sản phẩm]],product[[Mã sản phẩm]:[DS - ĐV]],3,0) -> Food Đức Việt
A61: =ROW()-1 -> 60 | B61: Mã mới | C61: Win+ | D61: Toàn quốc | E61: 14/05/2026 | F61: 24/06/2026 | G61: 8935101607990 | H61: =VLOOKUP(gia_khuyen_mai[[#This Row],[Barcode]],'Giá gốc'!$A:$B,2,0) -> 2145684 | I61: =VLOOKUP(gia_khuyen_mai[[#This Row],[Mã sản phẩm]],'Giá gốc'!$B:$C,2,0) -> O'Food - Xúc xích xốt Tokpokki vị phô mai Hàn Quốc 64g | J61: =VLOOKUP(gia_khuyen_mai[[#This Row],[Mã sản phẩm]],'Giá gốc'!B:D,3,0) -> 8837 | L61: =ROUND((1-gia_khuyen_mai[[#This Row],[% Giảm giá]]) * gia_khuyen_mai[[#This Row],[Giá gốc]], 0) -> 8837 | M61: Mua 1 tặng 1 | N61: =VLOOKUP(gia_khuyen_mai[[#This Row],[Barcode]],'Giá gốc'!$A:$B,2,0) -> 2145684 | O61: =IFERROR(VLOOKUP(gia_khuyen_mai[[#This Row],[Mã hàng tặng]],'Giá gốc'!B:C,2,0),"") -> O'Food - Xúc xích xốt Tokpokki vị phô mai Hàn Quốc 64g | Q61: =VLOOKUP(gia_khuyen_mai[[#This Row],[Mã sản phẩm]],product[[Mã sản phẩm]:[DS - ĐV]],3,0) -> Food Đức Việt
A62: =ROW()-1 -> 61 | B62: Post 10 | C62: Toàn bộ | D62: Toàn quốc | E62: 30/04/2026 | F62: 27/05/2026 | G62: 8935101600625 | H62: =VLOOKUP(gia_khuyen_mai[[#This Row],[Barcode]],'Giá gốc'!$A:$B,2,0) -> 2145689 | I62: =VLOOKUP(gia_khuyen_mai[[#This Row],[Mã sản phẩm]],'Giá gốc'!$B:$C,2,0) -> Xúc xích vườn bia 450g * 1EA | J62: =VLOOKUP(gia_khuyen_mai[[#This Row],[Mã sản phẩm]],'Giá gốc'!B:D,3,0) -> 84200 | K62: 0.22 | L62: =ROUND((1-gia_khuyen_mai[[#This Row],[% Giảm giá]]) * gia_khuyen_mai[[#This Row],[Giá gốc]], 0) -> 65676 | O62: =IFERROR(VLOOKUP(gia_khuyen_mai[[#This Row],[Mã hàng tặng]],'Giá gốc'!B:C,2,0),"") | Q62: =VLOOKUP(gia_khuyen_mai[[#This Row],[Mã sản phẩm]],product[[Mã sản phẩm]:[DS - ĐV]],3,0) -> Food Đức Việt
A63: =ROW()-1 -> 62 | B63: Post 10 | C63: Toàn bộ | D63: Toàn quốc | E63: 30/04/2026 | F63: 27/05/2026 | G63: 8935101600373 | H63: =VLOOKUP(gia_khuyen_mai[[#This Row],[Barcode]],'Giá gốc'!$A:$B,2,0) -> 2145714 | I63: =VLOOKUP(gia_khuyen_mai[[#This Row],[Mã sản phẩm]],'Giá gốc'!$B:$C,2,0) -> Xúc xích viên hong khói 200g | J63: =VLOOKUP(gia_khuyen_mai[[#This Row],[Mã sản phẩm]],'Giá gốc'!B:D,3,0) -> 38400 | K63: 0.2 | L63: =ROUND((1-gia_khuyen_mai[[#This Row],[% Giảm giá]]) * gia_khuyen_mai[[#This Row],[Giá gốc]], 0) -> 30720 | O63: =IFERROR(VLOOKUP(gia_khuyen_mai[[#This Row],[Mã hàng tặng]],'Giá gốc'!B:C,2,0),"") | Q63: =VLOOKUP(gia_khuyen_mai[[#This Row],[Mã sản phẩm]],product[[Mã sản phẩm]:[DS - ĐV]],3,0) -> Food Đức Việt
A64: =ROW()-1 -> 63 | B64: Post 10 | C64: Toàn bộ | D64: Toàn quốc | E64: 30/04/2026 | F64: 27/05/2026 | G64: 8935101604883 | H64: =VLOOKUP(gia_khuyen_mai[[#This Row],[Barcode]],'Giá gốc'!$A:$B,2,0) -> 2145765 | I64: =VLOOKUP(gia_khuyen_mai[[#This Row],[Mã sản phẩm]],'Giá gốc'!$B:$C,2,0) -> Xúc xích Hotdog 200g | J64: =VLOOKUP(gia_khuyen_mai[[#This Row],[Mã sản phẩm]],'Giá gốc'!B:D,3,0) -> 20100 | K64: 0.2 | L64: =ROUND((1-gia_khuyen_mai[[#This Row],[% Giảm giá]]) * gia_khuyen_mai[[#This Row],[Giá gốc]], 0) -> 16080 | O64: =IFERROR(VLOOKUP(gia_khuyen_mai[[#This Row],[Mã hàng tặng]],'Giá gốc'!B:C,2,0),"") | Q64: =VLOOKUP(gia_khuyen_mai[[#This Row],[Mã sản phẩm]],product[[Mã sản phẩm]:[DS - ĐV]],3,0) -> Food Đức Việt
A65: =ROW()-1 -> 64 | B65: Post 10 | C65: Toàn bộ | D65: Toàn quốc | E65: 30/04/2026 | F65: 27/05/2026 | G65: 8935101604913 | H65: =VLOOKUP(gia_khuyen_mai[[#This Row],[Barcode]],'Giá gốc'!$A:$B,2,0) -> 2145762 | I65: =VLOOKUP(gia_khuyen_mai[[#This Row],[Mã sản phẩm]],'Giá gốc'!$B:$C,2,0) -> Xúc xích Cocktail 200g | J65: =VLOOKUP(gia_khuyen_mai[[#This Row],[Mã sản phẩm]],'Giá gốc'!B:D,3,0) -> 21100 | K65: 0.2 | L65: =ROUND((1-gia_khuyen_mai[[#This Row],[% Giảm giá]]) * gia_khuyen_mai[[#This Row],[Giá gốc]], 0) -> 16880 | O65: =IFERROR(VLOOKUP(gia_khuyen_mai[[#This Row],[Mã hàng tặng]],'Giá gốc'!B:C,2,0),"") | Q65: =VLOOKUP(gia_khuyen_mai[[#This Row],[Mã sản phẩm]],product[[Mã sản phẩm]:[DS - ĐV]],3,0) -> Food Đức Việt
A66: =ROW()-1 -> 65 | B66: Post 10 | C66: Toàn bộ | D66: Toàn quốc | E66: 30/04/2026 | F66: 27/05/2026 | G66: 8935101608508 | H66: =VLOOKUP(gia_khuyen_mai[[#This Row],[Barcode]],'Giá gốc'!$A:$B,2,0) -> 2150771 | I66: =VLOOKUP(gia_khuyen_mai[[#This Row],[Mã sản phẩm]],'Giá gốc'!$B:$C,2,0) -> Lạp xưởng tươi (62g) 500g | J66: =VLOOKUP(gia_khuyen_mai[[#This Row],[Mã sản phẩm]],'Giá gốc'!B:D,3,0) -> 105000 | K66: 0.2 | L66: =ROUND((1-gia_khuyen_mai[[#This Row],[% Giảm giá]]) * gia_khuyen_mai[[#This Row],[Giá gốc]], 0) -> 84000 | O66: =IFERROR(VLOOKUP(gia_khuyen_mai[[#This Row],[Mã hàng tặng]],'Giá gốc'!B:C,2,0),"") | Q66: =VLOOKUP(gia_khuyen_mai[[#This Row],[Mã sản phẩm]],product[[Mã sản phẩm]:[DS - ĐV]],3,0) -> Food Đức Việt
A67: =ROW()-1 -> 66 | B67: Post 10 | C67: Toàn bộ | D67: Toàn quốc | E67: 30/04/2026 | F67: 27/05/2026 | G67: 8935101605804 | H67: =VLOOKUP(gia_khuyen_mai[[#This Row],[Barcode]],'Giá gốc'!$A:$B,2,0) -> 2145767 | I67: =VLOOKUP(gia_khuyen_mai[[#This Row],[Mã sản phẩm]],'Giá gốc'!$B:$C,2,0) -> Xúc xích Mỹ 500g | J67: =VLOOKUP(gia_khuyen_mai[[#This Row],[Mã sản phẩm]],'Giá gốc'!B:D,3,0) -> 55600 | K67: 0.2 | L67: =ROUND((1-gia_khuyen_mai[[#This Row],[% Giảm giá]]) * gia_khuyen_mai[[#This Row],[Giá gốc]], 0) -> 44480 | O67: =IFERROR(VLOOKUP(gia_khuyen_mai[[#This Row],[Mã hàng tặng]],'Giá gốc'!B:C,2,0),"") | Q67: =VLOOKUP(gia_khuyen_mai[[#This Row],[Mã sản phẩm]],product[[Mã sản phẩm]:[DS - ĐV]],3,0) -> Food Đức Việt
A68: =ROW()-1 -> 67 | B68: Post 10 | C68: Toàn bộ | D68: Toàn quốc | E68: 30/04/2026 | F68: 27/05/2026 | G68: 8935101607099 | H68: =VLOOKUP(gia_khuyen_mai[[#This Row],[Barcode]],'Giá gốc'!$A:$B,2,0) -> 2145697 | I68: =VLOOKUP(gia_khuyen_mai[[#This Row],[Mã sản phẩm]],'Giá gốc'!$B:$C,2,0) -> Seoul nhân phô mai 250g | J68: =VLOOKUP(gia_khuyen_mai[[#This Row],[Mã sản phẩm]],'Giá gốc'!B:D,3,0) -> 42000 | K68: 0.22 | L68: =ROUND((1-gia_khuyen_mai[[#This Row],[% Giảm giá]]) * gia_khuyen_mai[[#This Row],[Giá gốc]], 0) -> 32760 | O68: =IFERROR(VLOOKUP(gia_khuyen_mai[[#This Row],[Mã hàng tặng]],'Giá gốc'!B:C,2,0),"") | Q68: =VLOOKUP(gia_khuyen_mai[[#This Row],[Mã sản phẩm]],product[[Mã sản phẩm]:[DS - ĐV]],3,0) -> Food Đức Việt
A69: =ROW()-1 -> 68 | B69: Post 10 | C69: Toàn bộ | D69: Toàn quốc | E69: 30/04/2026 | F69: 27/05/2026 | G69: 8935101607105 | H69: =VLOOKUP(gia_khuyen_mai[[#This Row],[Barcode]],'Giá gốc'!$A:$B,2,0) -> 2145648 | I69: =VLOOKUP(gia_khuyen_mai[[#This Row],[Mã sản phẩm]],'Giá gốc'!$B:$C,2,0) -> Đức Việt Handy - xúc xích ăn liền vị heo 105g * 20EA | J69: =VLOOKUP(gia_khuyen_mai[[#This Row],[Mã sản phẩm]],'Giá gốc'!B:D,3,0) -> 9300 | K69: 0.2 | L69: =ROUND((1-gia_khuyen_mai[[#This Row],[% Giảm giá]]) * gia_khuyen_mai[[#This Row],[Giá gốc]], 0) -> 7440 | O69: =IFERROR(VLOOKUP(gia_khuyen_mai[[#This Row],[Mã hàng tặng]],'Giá gốc'!B:C,2,0),"") | Q69: =VLOOKUP(gia_khuyen_mai[[#This Row],[Mã sản phẩm]],product[[Mã sản phẩm]:[DS - ĐV]],3,0) -> Food Đức Việt
A70: =ROW()-1 -> 69 | B70: Post 10 | C70: Toàn bộ | D70: Toàn quốc | E70: 30/04/2026 | F70: 27/05/2026 | G70: 8935101607129 | H70: =VLOOKUP(gia_khuyen_mai[[#This Row],[Barcode]],'Giá gốc'!$A:$B,2,0) -> 2145657 | I70: =VLOOKUP(gia_khuyen_mai[[#This Row],[Mã sản phẩm]],'Giá gốc'!$B:$C,2,0) -> Đức Việt Handy - xúc xích ăn liền vị bò 105g * 20EA | J70: =VLOOKUP(gia_khuyen_mai[[#This Row],[Mã sản phẩm]],'Giá gốc'!B:D,3,0) -> 9300 | K70: 0.2 | L70: =ROUND((1-gia_khuyen_mai[[#This Row],[% Giảm giá]]) * gia_khuyen_mai[[#This Row],[Giá gốc]], 0) -> 7440 | O70: =IFERROR(VLOOKUP(gia_khuyen_mai[[#This Row],[Mã hàng tặng]],'Giá gốc'!B:C,2,0),"") | Q70: =VLOOKUP(gia_khuyen_mai[[#This Row],[Mã sản phẩm]],product[[Mã sản phẩm]:[DS - ĐV]],3,0) -> Food Đức Việt
A71: =ROW()-1 -> 70 | B71: Post 10 | C71: Toàn bộ | D71: Toàn quốc | E71: 30/04/2026 | F71: 27/05/2026 | G71: 8935101608409 | H71: =VLOOKUP(gia_khuyen_mai[[#This Row],[Barcode]],'Giá gốc'!$A:$B,2,0) -> 2148987 | I71: =VLOOKUP(gia_khuyen_mai[[#This Row],[Mã sản phẩm]],'Giá gốc'!$B:$C,2,0) -> Kimchi cải thảo cắt lát 150g * 30EA | J71: =VLOOKUP(gia_khuyen_mai[[#This Row],[Mã sản phẩm]],'Giá gốc'!B:D,3,0) -> 14200 | K71: 0.2 | L71: =ROUND((1-gia_khuyen_mai[[#This Row],[% Giảm giá]]) * gia_khuyen_mai[[#This Row],[Giá gốc]], 0) -> 11360 | O71: =IFERROR(VLOOKUP(gia_khuyen_mai[[#This Row],[Mã hàng tặng]],'Giá gốc'!B:C,2,0),"") | Q71: =VLOOKUP(gia_khuyen_mai[[#This Row],[Mã sản phẩm]],product[[Mã sản phẩm]:[DS - ĐV]],3,0) -> Food Đức Việt
A72: =ROW()-1 -> 71 | B72: Post 11 | C72: Toàn bộ | D72: Toàn quốc | E72: 14/05/2026 | F72: 10/06/2026 | G72: 8935101600250 | H72: =VLOOKUP(gia_khuyen_mai[[#This Row],[Barcode]],'Giá gốc'!$A:$B,2,0) -> 2145686 | I72: =VLOOKUP(gia_khuyen_mai[[#This Row],[Mã sản phẩm]],'Giá gốc'!$B:$C,2,0) -> Xúc xích hong khói 450g | J72: =VLOOKUP(gia_khuyen_mai[[#This Row],[Mã sản phẩm]],'Giá gốc'!B:D,3,0) -> 79100 | K72: 0.22 | L72: =ROUND((1-gia_khuyen_mai[[#This Row],[% Giảm giá]]) * gia_khuyen_mai[[#This Row],[Giá gốc]], 0) -> 61698 | O72: =IFERROR(VLOOKUP(gia_khuyen_mai[[#This Row],[Mã hàng tặng]],'Giá gốc'!B:C,2,0),"") | Q72: =VLOOKUP(gia_khuyen_mai[[#This Row],[Mã sản phẩm]],product[[Mã sản phẩm]:[DS - ĐV]],3,0) -> Food Đức Việt
A73: =ROW()-1 -> 72 | B73: Post 11 | C73: Toàn bộ | D73: Toàn quốc | E73: 14/05/2026 | F73: 10/06/2026 | G73: 8935101607938 | H73: =VLOOKUP(gia_khuyen_mai[[#This Row],[Barcode]],'Giá gốc'!$A:$B,2,0) -> 2145726 | I73: =VLOOKUP(gia_khuyen_mai[[#This Row],[Mã sản phẩm]],'Giá gốc'!$B:$C,2,0) -> Xúc xích phô mai Cheesy 250g | J73: =VLOOKUP(gia_khuyen_mai[[#This Row],[Mã sản phẩm]],'Giá gốc'!B:D,3,0) -> 49400 | K73: 0.25 | L73: =ROUND((1-gia_khuyen_mai[[#This Row],[% Giảm giá]]) * gia_khuyen_mai[[#This Row],[Giá gốc]], 0) -> 37050 | O73: =IFERROR(VLOOKUP(gia_khuyen_mai[[#This Row],[Mã hàng tặng]],'Giá gốc'!B:C,2,0),"") | Q73: =VLOOKUP(gia_khuyen_mai[[#This Row],[Mã sản phẩm]],product[[Mã sản phẩm]:[DS - ĐV]],3,0) -> Food Đức Việt
... A75: =ROW()-1 -> 74 | B75: Post 11 | C75: Toàn bộ | D75: Toàn quốc | E75: 14/05/2026 | F75: 10/06/2026 | G75: 8935101604937 | H75: =VLOOKUP(gia_khuyen_mai[[#This Row],[Barcode]],'Giá gốc'!$A:$B,2,0) -> 2145764 | I75: =VLOOKUP(gia_khuyen_mai[[#This Row],[Mã sản phẩm]],'Giá gốc'!$B:$C,2,0) -> Xúc xích Cocktail 500g | J75: =VLOOKUP(gia_khuyen_mai[[#This Row],[Mã sản phẩm]],'Giá gốc'!B:D,3,0) -> 52800 | K75: 0.2 | L75: =ROUND((1-gia_khuyen_mai[[#This Row],[% Giảm giá]]) * gia_khuyen_mai[[#This Row],[Giá gốc]], 0) -> 42240 | O75: =IFERROR(VLOOKUP(gia_khuyen_mai[[#This Row],[Mã hàng tặng]],'Giá gốc'!B:C,2,0),"") | Q75: =VLOOKUP(gia_khuyen_mai[[#This Row],[Mã sản phẩm]],product[[Mã sản phẩm]:[DS - ĐV]],3,0) -> Food Đức Việt
A76: =ROW()-1 -> 75 | B76: Post 11 | C76: Toàn bộ | D76: Toàn quốc | E76: 14/05/2026 | F76: 10/06/2026 | G76: 8935101607891 | H76: =VLOOKUP(gia_khuyen_mai[[#This Row],[Barcode]],'Giá gốc'!$A:$B,2,0) -> 2145680 | I76: =VLOOKUP(gia_khuyen_mai[[#This Row],[Mã sản phẩm]],'Giá gốc'!$B:$C,2,0) -> O'food Xúc xích Lắc Phô mai vị truyền thống 56g * 24EA | J76: =VLOOKUP(gia_khuyen_mai[[#This Row],[Mã sản phẩm]],'Giá gốc'!B:D,3,0) -> 9300 | K76: 0.2 | L76: 7069 | O76: =IFERROR(VLOOKUP(gia_khuyen_mai[[#This Row],[Mã hàng tặng]],'Giá gốc'!B:C,2,0),"") | Q76: =VLOOKUP(gia_khuyen_mai[[#This Row],[Mã sản phẩm]],product[[Mã sản phẩm]:[DS - ĐV]],3,0) -> Food Đức Việt
A77: =ROW()-1 -> 76 | B77: Post 11 | C77: Toàn bộ | D77: Toàn quốc | E77: 14/05/2026 | F77: 10/06/2026 | G77: 8935101607907 | H77: =VLOOKUP(gia_khuyen_mai[[#This Row],[Barcode]],'Giá gốc'!$A:$B,2,0) -> 2145681 | I77: =VLOOKUP(gia_khuyen_mai[[#This Row],[Mã sản phẩm]],'Giá gốc'!$B:$C,2,0) -> O'food Xúc xích Lắc Phô mai vị dâu tây 56g * 24EA | J77: =VLOOKUP(gia_khuyen_mai[[#This Row],[Mã sản phẩm]],'Giá gốc'!B:D,3,0) -> 9300 | K77: 0.2 | L77: 7069 | O77: =IFERROR(VLOOKUP(gia_khuyen_mai[[#This Row],[Mã hàng tặng]],'Giá gốc'!B:C,2,0),"") | Q77: =VLOOKUP(gia_khuyen_mai[[#This Row],[Mã sản phẩm]],product[[Mã sản phẩm]:[DS - ĐV]],3,0) -> Food Đức Việt
A78: =ROW()-1 -> 77 | B78: Post 11 | C78: Win+ | D78: Toàn quốc | E78: 14/05/2026 | F78: 10/06/2026 | G78: 8935101608461 | H78: =VLOOKUP(gia_khuyen_mai[[#This Row],[Barcode]],'Giá gốc'!$A:$B,2,0) -> 2150338 | I78: =VLOOKUP(gia_khuyen_mai[[#This Row],[Mã sản phẩm]],'Giá gốc'!$B:$C,2,0) -> O'food Chả giò da xốp hải sản 300g | J78: =VLOOKUP(gia_khuyen_mai[[#This Row],[Mã sản phẩm]],'Giá gốc'!B:D,3,0) -> 31524 | K78: 0.3 | L78: =ROUND((1-gia_khuyen_mai[[#This Row],[% Giảm giá]]) * gia_khuyen_mai[[#This Row],[Giá gốc]], 0) -> 22067 | O78: =IFERROR(VLOOKUP(gia_khuyen_mai[[#This Row],[Mã hàng tặng]],'Giá gốc'!B:C,2,0),"") | Q78: =VLOOKUP(gia_khuyen_mai[[#This Row],[Mã sản phẩm]],product[[Mã sản phẩm]:[DS - ĐV]],3,0) -> Food Đức Việt
A79: =ROW()-1 -> 78 | B79: Post 11 | C79: Toàn bộ | D79: Toàn quốc | E79: 14/05/2026 | F79: 10/06/2026 | G79: 8935101608102 | H79: =VLOOKUP(gia_khuyen_mai[[#This Row],[Barcode]],'Giá gốc'!$A:$B,2,0) -> 2145622 | I79: =VLOOKUP(gia_khuyen_mai[[#This Row],[Mã sản phẩm]],'Giá gốc'!$B:$C,2,0) -> Kim chi 450 | J79: =VLOOKUP(gia_khuyen_mai[[#This Row],[Mã sản phẩm]],'Giá gốc'!B:D,3,0) -> 35500 | K79: 0.3 | L79: =ROUND((1-gia_khuyen_mai[[#This Row],[% Giảm giá]]) * gia_khuyen_mai[[#This Row],[Giá gốc]], 0) -> 24850 | O79: =IFERROR(VLOOKUP(gia_khuyen_mai[[#This Row],[Mã hàng tặng]],'Giá gốc'!B:C,2,0),"") | Q79: =VLOOKUP(gia_khuyen_mai[[#This Row],[Mã sản phẩm]],product[[Mã sản phẩm]:[DS - ĐV]],3,0) -> Food Đức Việt
A80: =ROW()-1 -> 79 | B80: Bổ sung | C80: Win+ | D80: Toàn quốc | E80: 18/05/2026 | F80: 10/06/2026 | G80: 8935101608478 | H80: =VLOOKUP(gia_khuyen_mai[[#This Row],[Barcode]],'Giá gốc'!$A:$B,2,0) -> 2150337 | I80: =VLOOKUP(gia_khuyen_mai[[#This Row],[Mã sản phẩm]],'Giá gốc'!$B:$C,2,0) -> O'food Chả giò da xốp nhân thịt 300g | J80: =VLOOKUP(gia_khuyen_mai[[#This Row],[Mã sản phẩm]],'Giá gốc'!B:D,3,0) -> 31524 | L80: =ROUND((1-gia_khuyen_mai[[#This Row],[% Giảm giá]]) * gia_khuyen_mai[[#This Row],[Giá gốc]], 0) -> 31524 | M80: Mua 1 tặng 1 | N80: =VLOOKUP(gia_khuyen_mai[[#This Row],[Barcode]],'Giá gốc'!$A:$B,2,0) -> 2150337 | O80: =IFERROR(VLOOKUP(gia_khuyen_mai[[#This Row],[Mã hàng tặng]],'Giá gốc'!B:C,2,0),"") -> O'food Chả giò da xốp nhân thịt 300g | Q80: =VLOOKUP(gia_khuyen_mai[[#This Row],[Mã sản phẩm]],product[[Mã sản phẩm]:[DS - ĐV]],3,0) -> Food Đức Việt
A81: =ROW()-1 -> 80 | B81: Bổ sung | C81: Winmart | D81: Toàn quốc | E81: 08/05/2026 | F81: 10/06/2026 | G81: 8935101608478 | H81: =VLOOKUP(gia_khuyen_mai[[#This Row],[Barcode]],'Giá gốc'!$A:$B,2,0) -> 2150337 | I81: =VLOOKUP(gia_khuyen_mai[[#This Row],[Mã sản phẩm]],'Giá gốc'!$B:$C,2,0) -> O'food Chả giò da xốp nhân thịt 300g | J81: =VLOOKUP(gia_khuyen_mai[[#This Row],[Mã sản phẩm]],'Giá gốc'!B:D,3,0) -> 31524 | L81: =ROUND((1-gia_khuyen_mai[[#This Row],[% Giảm giá]]) * gia_khuyen_mai[[#This Row],[Giá gốc]], 0) -> 31524 | M81: Mua 1 tặng 1 | N81: =VLOOKUP(gia_khuyen_mai[[#This Row],[Barcode]],'Giá gốc'!$A:$B,2,0) -> 2150337 | O81: =IFERROR(VLOOKUP(gia_khuyen_mai[[#This Row],[Mã hàng tặng]],'Giá gốc'!B:C,2,0),"") -> O'food Chả giò da xốp nhân thịt 300g | Q81: =VLOOKUP(gia_khuyen_mai[[#This Row],[Mã sản phẩm]],product[[Mã sản phẩm]:[DS - ĐV]],3,0) -> Food Đức Việt
A82: =ROW()-1 -> 81 | B82: Bổ sung | C82: Winmart | D82: Toàn quốc | E82: 08/05/2026 | F82: 10/06/2026 | G82: 8935101608461 | H82: =VLOOKUP(gia_khuyen_mai[[#This Row],[Barcode]],'Giá gốc'!$A:$B,2,0) -> 2150338 | I82: =VLOOKUP(gia_khuyen_mai[[#This Row],[Mã sản phẩm]],'Giá gốc'!$B:$C,2,0) -> O'food Chả giò da xốp hải sản 300g | J82: =VLOOKUP(gia_khuyen_mai[[#This Row],[Mã sản phẩm]],'Giá gốc'!B:D,3,0) -> 31524 | L82: =ROUND((1-gia_khuyen_mai[[#This Row],[% Giảm giá]]) * gia_khuyen_mai[[#This Row],[Giá gốc]], 0) -> 31524 | M82: Mua 1 tặng 1 | N82: =VLOOKUP(gia_khuyen_mai[[#This Row],[Barcode]],'Giá gốc'!$A:$B,2,0) -> 2150338 | O82: =IFERROR(VLOOKUP(gia_khuyen_mai[[#This Row],[Mã hàng tặng]],'Giá gốc'!B:C,2,0),"") -> O'food Chả giò da xốp hải sản 300g | Q82: =VLOOKUP(gia_khuyen_mai[[#This Row],[Mã sản phẩm]],product[[Mã sản phẩm]:[DS - ĐV]],3,0) -> Food Đức Việt
A83: =ROW()-1 -> 82 | B83: Post 12 | C83: Toàn bộ | D83: Toàn quốc | E83: 27/05/2026 | F83: 24/06/2026 | G83: 8935101600427 | H83: =VLOOKUP(gia_khuyen_mai[[#This Row],[Barcode]],'Giá gốc'!$A:$B,2,0) -> 2145691 | I83: =VLOOKUP(gia_khuyen_mai[[#This Row],[Mã sản phẩm]],'Giá gốc'!$B:$C,2,0) -> Xúc xích viên hong khói 450g * 1EA | J83: =VLOOKUP(gia_khuyen_mai[[#This Row],[Mã sản phẩm]],'Giá gốc'!B:D,3,0) -> 84200 | L83: =ROUND((1-gia_khuyen_mai[[#This Row],[% Giảm giá]]) * gia_khuyen_mai[[#This Row],[Giá gốc]], 0) -> 84200 | M83: Mua 1 tặng 1 | N83: 2145765 | O83: =IFERROR(VLOOKUP(gia_khuyen_mai[[#This Row],[Mã hàng tặng]],'Giá gốc'!B:C,2,0),"") -> Xúc xích Hotdog 200g | Q83: =VLOOKUP(gia_khuyen_mai[[#This Row],[Mã sản phẩm]],product[[Mã sản phẩm]:[DS - ĐV]],3,0) -> Food Đức Việt
A84: =ROW()-1 -> 83 | B84: Post 12 | C84: Toàn bộ | D84: Toàn quốc | E84: 27/05/2026 | F84: 24/06/2026 | G84: 8935101600380 | H84: =VLOOKUP(gia_khuyen_mai[[#This Row],[Barcode]],'Giá gốc'!$A:$B,2,0) -> 2145690 | I84: =VLOOKUP(gia_khuyen_mai[[#This Row],[Mã sản phẩm]],'Giá gốc'!$B:$C,2,0) -> Xúc xích vườn bia 200g * 1EA | J84: =VLOOKUP(gia_khuyen_mai[[#This Row],[Mã sản phẩm]],'Giá gốc'!B:D,3,0) -> 38400 | K84: 0.2 | L84: =ROUND((1-gia_khuyen_mai[[#This Row],[% Giảm giá]]) * gia_khuyen_mai[[#This Row],[Giá gốc]], 0) -> 30720 | O84: =IFERROR(VLOOKUP(gia_khuyen_mai[[#This Row],[Mã hàng tặng]],'Giá gốc'!B:C,2,0),"") | Q84: =VLOOKUP(gia_khuyen_mai[[#This Row],[Mã sản phẩm]],product[[Mã sản phẩm]:[DS - ĐV]],3,0) -> Food Đức Việt
A85: =ROW()-1 -> 84 | B85: Post 12 | C85: Toàn bộ | D85: Toàn quốc | E85: 27/05/2026 | F85: 24/06/2026 | G85: 8935101607716 | H85: =VLOOKUP(gia_khuyen_mai[[#This Row],[Barcode]],'Giá gốc'!$A:$B,2,0) -> 2145679 | I85: =VLOOKUP(gia_khuyen_mai[[#This Row],[Mã sản phẩm]],'Giá gốc'!$B:$C,2,0) -> Đức Việt Handy- Xúc xích thịt heo muối hồng Himalaya 175g * 20EA | J85: =VLOOKUP(gia_khuyen_mai[[#This Row],[Mã sản phẩm]],'Giá gốc'!B:D,3,0) -> 18300 | K85: 0.25 | L85: =ROUND((1-gia_khuyen_mai[[#This Row],[% Giảm giá]]) * gia_khuyen_mai[[#This Row],[Giá gốc]], 0) -> 13725 | O85: =IFERROR(VLOOKUP(gia_khuyen_mai[[#This Row],[Mã hàng tặng]],'Giá gốc'!B:C,2,0),"") | Q85: =VLOOKUP(gia_khuyen_mai[[#This Row],[Mã sản phẩm]],product[[Mã sản phẩm]:[DS - ĐV]],3,0) -> Food Đức Việt
A86: =ROW()-1 -> 85 | B86: Post 12 | C86: Toàn bộ | D86: Toàn quốc | E86: 27/05/2026 | F86: 24/06/2026 | G86: 8935101606078 | H86: =VLOOKUP(gia_khuyen_mai[[#This Row],[Barcode]],'Giá gốc'!$A:$B,2,0) -> 2145695 | I86: =VLOOKUP(gia_khuyen_mai[[#This Row],[Mã sản phẩm]],'Giá gốc'!$B:$C,2,0) -> Seoul's Hotdog 350g | J86: =VLOOKUP(gia_khuyen_mai[[#This Row],[Mã sản phẩm]],'Giá gốc'!B:D,3,0) -> 48384 | K86: 0.25 | L86: =ROUND((1-gia_khuyen_mai[[#This Row],[% Giảm giá]]) * gia_khuyen_mai[[#This Row],[Giá gốc]], 0) -> 36288 | O86: =IFERROR(VLOOKUP(gia_khuyen_mai[[#This Row],[Mã hàng tặng]],'Giá gốc'!B:C,2,0),"") | Q86: =VLOOKUP(gia_khuyen_mai[[#This Row],[Mã sản phẩm]],product[[Mã sản phẩm]:[DS - ĐV]],3,0) -> Food Đức Việt
A87: =ROW()-1 -> 86 | B87: Post 12 | C87: Toàn bộ | D87: Toàn quốc | E87: 27/05/2026 | F87: 24/06/2026 | G87: 8935101605989 | H87: =VLOOKUP(gia_khuyen_mai[[#This Row],[Barcode]],'Giá gốc'!$A:$B,2,0) -> 2145774 | I87: =VLOOKUP(gia_khuyen_mai[[#This Row],[Mã sản phẩm]],'Giá gốc'!$B:$C,2,0) -> Xúc xích Pari (50g) 500g | J87: =VLOOKUP(gia_khuyen_mai[[#This Row],[Mã sản phẩm]],'Giá gốc'!B:D,3,0) -> 55600 | K87: 0.22 | L87: =ROUND((1-gia_khuyen_mai[[#This Row],[% Giảm giá]]) * gia_khuyen_mai[[#This Row],[Giá gốc]], 0) -> 43368 | O87: =IFERROR(VLOOKUP(gia_khuyen_mai[[#This Row],[Mã hàng tặng]],'Giá gốc'!B:C,2,0),"") | Q87: =VLOOKUP(gia_khuyen_mai[[#This Row],[Mã sản phẩm]],product[[Mã sản phẩm]:[DS - ĐV]],3,0) -> Food Đức Việt
A88: =ROW()-1 -> 87 | B88: Post 12 | C88: Toàn bộ | D88: Toàn quốc | E88: 27/05/2026 | F88: 24/06/2026 | G88: 8935101608348 | H88: =VLOOKUP(gia_khuyen_mai[[#This Row],[Barcode]],'Giá gốc'!$A:$B,2,0) -> 2145744 | I88: =VLOOKUP(gia_khuyen_mai[[#This Row],[Mã sản phẩm]],'Giá gốc'!$B:$C,2,0) -> Xúc xích bắp phô mai 250g | J88: =VLOOKUP(gia_khuyen_mai[[#This Row],[Mã sản phẩm]],'Giá gốc'!B:D,3,0) -> 49400 | K88: 0.25 | L88: =ROUND((1-gia_khuyen_mai[[#This Row],[% Giảm giá]]) * gia_khuyen_mai[[#This Row],[Giá gốc]], 0) -> 37050 | O88: =IFERROR(VLOOKUP(gia_khuyen_mai[[#This Row],[Mã hàng tặng]],'Giá gốc'!B:C,2,0),"") | Q88: =VLOOKUP(gia_khuyen_mai[[#This Row],[Mã sản phẩm]],product[[Mã sản phẩm]:[DS - ĐV]],3,0) -> Food Đức Việt
A89: =ROW()-1 -> 88 | B89: Post 12 | C89: Toàn bộ | D89: Toàn quốc | E89: 27/05/2026 | F89: 24/06/2026 | G89: 8935101608072 | H89: =VLOOKUP(gia_khuyen_mai[[#This Row],[Barcode]],'Giá gốc'!$A:$B,2,0) -> 2145743 | I89: =VLOOKUP(gia_khuyen_mai[[#This Row],[Mã sản phẩm]],'Giá gốc'!$B:$C,2,0) -> Xúc xích sụn nướng Bulgogi 450g | J89: =VLOOKUP(gia_khuyen_mai[[#This Row],[Mã sản phẩm]],'Giá gốc'!B:D,3,0) -> 74500 | K89: 0.3 | L89: =ROUND((1-gia_khuyen_mai[[#This Row],[% Giảm giá]]) * gia_khuyen_mai[[#This Row],[Giá gốc]], 0) -> 52150 | O89: =IFERROR(VLOOKUP(gia_khuyen_mai[[#This Row],[Mã hàng tặng]],'Giá gốc'!B:C,2,0),"") | Q89: =VLOOKUP(gia_khuyen_mai[[#This Row],[Mã sản phẩm]],product[[Mã sản phẩm]:[DS - ĐV]],3,0) -> Food Đức Việt
A90: =ROW()-1 -> 89 | B90: Post 12 | C90: Toàn bộ | D90: Toàn quốc | E90: 27/05/2026 | F90: 24/06/2026 | G90: 8935101604906 | H90: =VLOOKUP(gia_khuyen_mai[[#This Row],[Barcode]],'Giá gốc'!$A:$B,2,0) -> 2145768 | I90: =VLOOKUP(gia_khuyen_mai[[#This Row],[Mã sản phẩm]],'Giá gốc'!$B:$C,2,0) -> Xúc xích Hotdog 500g | J90: =VLOOKUP(gia_khuyen_mai[[#This Row],[Mã sản phẩm]],'Giá gốc'!B:D,3,0) -> 50200 | K90: 0.2 | L90: =ROUND((1-gia_khuyen_mai[[#This Row],[% Giảm giá]]) * gia_khuyen_mai[[#This Row],[Giá gốc]], 0) -> 40160 | O90: =IFERROR(VLOOKUP(gia_khuyen_mai[[#This Row],[Mã hàng tặng]],'Giá gốc'!B:C,2,0),"") | Q90: =VLOOKUP(gia_khuyen_mai[[#This Row],[Mã sản phẩm]],product[[Mã sản phẩm]:[DS - ĐV]],3,0) -> Food Đức Việt
A91: =ROW()-1 -> 90 | B91: Post 12 | C91: Toàn bộ | D91: Toàn quốc | E91: 11/06/2026 | F91: 24/06/2026 | G91: 8935101608478 | H91: =VLOOKUP(gia_khuyen_mai[[#This Row],[Barcode]],'Giá gốc'!$A:$B,2,0) -> 2150337 | I91: =VLOOKUP(gia_khuyen_mai[[#This Row],[Mã sản phẩm]],'Giá gốc'!$B:$C,2,0) -> O'food Chả giò da xốp nhân thịt 300g | J91: =VLOOKUP(gia_khuyen_mai[[#This Row],[Mã sản phẩm]],'Giá gốc'!B:D,3,0) -> 31524 | K91: 0.3 | L91: =ROUND((1-gia_khuyen_mai[[#This Row],[% Giảm giá]]) * gia_khuyen_mai[[#This Row],[Giá gốc]], 0) -> 22067 | O91: =IFERROR(VLOOKUP(gia_khuyen_mai[[#This Row],[Mã hàng tặng]],'Giá gốc'!B:C,2,0),"") | Q91: =VLOOKUP(gia_khuyen_mai[[#This Row],[Mã sản phẩm]],product[[Mã sản phẩm]:[DS - ĐV]],3,0) -> Food Đức Việt
A92: =ROW()-1 -> 91 | B92: Post 12 | C92: Toàn bộ | D92: Toàn quốc | E92: 27/05/2026 | F92: 23/06/2026 | G92: 8935101607877 | H92: =VLOOKUP(gia_khuyen_mai[[#This Row],[Barcode]],'Giá gốc'!$A:$B,2,0) -> 2145699 | I92: =VLOOKUP(gia_khuyen_mai[[#This Row],[Mã sản phẩm]],'Giá gốc'!$B:$C,2,0) -> Seoul's Hotdog Chiên xù 250g (Đ) | J92: =VLOOKUP(gia_khuyen_mai[[#This Row],[Mã sản phẩm]],'Giá gốc'!B:D,3,0) -> 39150 | K92: 0.22 | L92: =ROUND((1-gia_khuyen_mai[[#This Row],[% Giảm giá]]) * gia_khuyen_mai[[#This Row],[Giá gốc]], 0) -> 30537 | O92: =IFERROR(VLOOKUP(gia_khuyen_mai[[#This Row],[Mã hàng tặng]],'Giá gốc'!B:C,2,0),"") | Q92: =VLOOKUP(gia_khuyen_mai[[#This Row],[Mã sản phẩm]],product[[Mã sản phẩm]:[DS - ĐV]],3,0) -> Food Đức Việt
A93: =ROW()-1 -> 92 | B93: Post 12 | C93: Toàn bộ | D93: Toàn quốc | E93: 27/05/2026 | F93: 24/06/2026 | G93: 8935101604180 | H93: =VLOOKUP(gia_khuyen_mai[[#This Row],[Barcode]],'Giá gốc'!$A:$B,2,0) -> 2146417 | I93: =VLOOKUP(gia_khuyen_mai[[#This Row],[Mã sản phẩm]],'Giá gốc'!$B:$C,2,0) -> Chân giò hong khói rút xương 300g | J93: =VLOOKUP(gia_khuyen_mai[[#This Row],[Mã sản phẩm]],'Giá gốc'!B:D,3,0) -> 67700 | K93: 0.2 | L93: =ROUND((1-gia_khuyen_mai[[#This Row],[% Giảm giá]]) * gia_khuyen_mai[[#This Row],[Giá gốc]], 0) -> 54160 | O93: =IFERROR(VLOOKUP(gia_khuyen_mai[[#This Row],[Mã hàng tặng]],'Giá gốc'!B:C,2,0),"") | Q93: =VLOOKUP(gia_khuyen_mai[[#This Row],[Mã sản phẩm]],product[[Mã sản phẩm]:[DS - ĐV]],3,0) -> Food Đức Việt
A94: 93 | B94: Post bổ sung | C94: Winmart | D94: Toàn quốc | E94: 27/05/2026 | F94: 10/06/2026 | G94: 8935101608539 | H94: =VLOOKUP(gia_khuyen_mai[[#This Row],[Barcode]],'Giá gốc'!$A:$B,2,0) -> 2151323 | I94: =VLOOKUP(gia_khuyen_mai[[#This Row],[Mã sản phẩm]],'Giá gốc'!$B:$C,2,0) -> OFOOD Tteokgalbi chả nướng HQ 200g | J94: =VLOOKUP(gia_khuyen_mai[[#This Row],[Mã sản phẩm]],'Giá gốc'!B:D,3,0) -> 36000 | L94: =ROUND((1-gia_khuyen_mai[[#This Row],[% Giảm giá]]) * gia_khuyen_mai[[#This Row],[Giá gốc]], 0) -> 36000 | M94: Mua 1 tặng 1 | N94: =VLOOKUP(gia_khuyen_mai[[#This Row],[Barcode]],'Giá gốc'!$A:$B,2,0) -> 2151323 | O94: =IFERROR(VLOOKUP(gia_khuyen_mai[[#This Row],[Mã hàng tặng]],'Giá gốc'!B:C,2,0),"") -> OFOOD Tteokgalbi chả nướng HQ 200g | Q94: =VLOOKUP(gia_khuyen_mai[[#This Row],[Mã sản phẩm]],product[[Mã sản phẩm]:[DS - ĐV]],3,0) -> Food Đức Việt
A95: =ROW()-1 -> 94 | B95: Post 13 | C95: Toàn bộ | D95: Toàn quốc | E95: 10/06/2026 | F95: 08/07/2026 | G95: 8935101600625 | H95: =VLOOKUP(gia_khuyen_mai[[#This Row],[Barcode]],'Giá gốc'!$A:$B,2,0) -> 2145689 | I95: =VLOOKUP(gia_khuyen_mai[[#This Row],[Mã sản phẩm]],'Giá gốc'!$B:$C,2,0) -> Xúc xích vườn bia 450g * 1EA | J95: =VLOOKUP(gia_khuyen_mai[[#This Row],[Mã sản phẩm]],'Giá gốc'!B:D,3,0) -> 84200 | K95: 0.05 | L95: =ROUND((1-gia_khuyen_mai[[#This Row],[% Giảm giá]]) * gia_khuyen_mai[[#This Row],[Giá gốc]], 0) -> 79990 | M95: Mua 1 tặng 1 | N95: 2145765 | O95: =IFERROR(VLOOKUP(gia_khuyen_mai[[#This Row],[Mã hàng tặng]],'Giá gốc'!B:C,2,0),"") -> Xúc xích Hotdog 200g | Q95: =VLOOKUP(gia_khuyen_mai[[#This Row],[Mã sản phẩm]],product[[Mã sản phẩm]:[DS - ĐV]],3,0) -> Food Đức Việt
A96: =ROW()-1 -> 95 | B96: Post 13 | C96: Toàn bộ | D96: Toàn quốc | E96: 10/06/2026 | F96: 08/07/2026 | G96: 8935101600373 | H96: =VLOOKUP(gia_khuyen_mai[[#This Row],[Barcode]],'Giá gốc'!$A:$B,2,0) -> 2145714 | I96: =VLOOKUP(gia_khuyen_mai[[#This Row],[Mã sản phẩm]],'Giá gốc'!$B:$C,2,0) -> Xúc xích viên hong khói 200g | J96: =VLOOKUP(gia_khuyen_mai[[#This Row],[Mã sản phẩm]],'Giá gốc'!B:D,3,0) -> 38400 | K96: 0.2 | L96: =ROUND((1-gia_khuyen_mai[[#This Row],[% Giảm giá]]) * gia_khuyen_mai[[#This Row],[Giá gốc]], 0) -> 30720 | O96: =IFERROR(VLOOKUP(gia_khuyen_mai[[#This Row],[Mã hàng tặng]],'Giá gốc'!B:C,2,0),"") | Q96: =VLOOKUP(gia_khuyen_mai[[#This Row],[Mã sản phẩm]],product[[Mã sản phẩm]:[DS - ĐV]],3,0) -> Food Đức Việt
A97: =ROW()-1 -> 96 | B97: Post 13 | C97: Toàn bộ | D97: Toàn quốc | E97: 10/06/2026 | F97: 08/07/2026 | G97: 8935101605804 | H97: =VLOOKUP(gia_khuyen_mai[[#This Row],[Barcode]],'Giá gốc'!$A:$B,2,0) -> 2145767 | I97: =VLOOKUP(gia_khuyen_mai[[#This Row],[Mã sản phẩm]],'Giá gốc'!$B:$C,2,0) -> Xúc xích Mỹ 500g | J97: =VLOOKUP(gia_khuyen_mai[[#This Row],[Mã sản phẩm]],'Giá gốc'!B:D,3,0) -> 55600 | K97: 0.2 | L97: =ROUND((1-gia_khuyen_mai[[#This Row],[% Giảm giá]]) * gia_khuyen_mai[[#This Row],[Giá gốc]], 0) -> 44480 | O97: =IFERROR(VLOOKUP(gia_khuyen_mai[[#This Row],[Mã hàng tặng]],'Giá gốc'!B:C,2,0),"") | Q97: =VLOOKUP(gia_khuyen_mai[[#This Row],[Mã sản phẩm]],product[[Mã sản phẩm]:[DS - ĐV]],3,0) -> Food Đức Việt
A98: =ROW()-1 -> 97 | B98: Post 13 | C98: Toàn bộ | D98: Toàn quốc | E98: 10/06/2026 | F98: 08/07/2026 | G98: 8935101607129 | H98: =VLOOKUP(gia_khuyen_mai[[#This Row],[Barcode]],'Giá gốc'!$A:$B,2,0) -> 2145657 | I98: =VLOOKUP(gia_khuyen_mai[[#This Row],[Mã sản phẩm]],'Giá gốc'!$B:$C,2,0) -> Đức Việt Handy - xúc xích ăn liền vị bò 105g * 20EA | J98: =VLOOKUP(gia_khuyen_mai[[#This Row],[Mã sản phẩm]],'Giá gốc'!B:D,3,0) -> 9300 | K98: 0.2 | L98: =ROUND((1-gia_khuyen_mai[[#This Row],[% Giảm giá]]) * gia_khuyen_mai[[#This Row],[Giá gốc]], 0) -> 7440 | O98: =IFERROR(VLOOKUP(gia_khuyen_mai[[#This Row],[Mã hàng tặng]],'Giá gốc'!B:C,2,0),"") | Q98: =VLOOKUP(gia_khuyen_mai[[#This Row],[Mã sản phẩm]],product[[Mã sản phẩm]:[DS - ĐV]],3,0) -> Food Đức Việt
A99: =ROW()-1 -> 98 | B99: Post 13 | C99: Toàn bộ | D99: Toàn quốc | E99: 10/06/2026 | F99: 08/07/2026 | G99: 8935101607105 | H99: =VLOOKUP(gia_khuyen_mai[[#This Row],[Barcode]],'Giá gốc'!$A:$B,2,0) -> 2145648 | I99: =VLOOKUP(gia_khuyen_mai[[#This Row],[Mã sản phẩm]],'Giá gốc'!$B:$C,2,0) -> Đức Việt Handy - xúc xích ăn liền vị heo 105g * 20EA | J99: =VLOOKUP(gia_khuyen_mai[[#This Row],[Mã sản phẩm]],'Giá gốc'!B:D,3,0) -> 9300 | K99: 0.2 | L99: =ROUND((1-gia_khuyen_mai[[#This Row],[% Giảm giá]]) * gia_khuyen_mai[[#This Row],[Giá gốc]], 0) -> 7440 | O99: =IFERROR(VLOOKUP(gia_khuyen_mai[[#This Row],[Mã hàng tặng]],'Giá gốc'!B:C,2,0),"") | Q99: =VLOOKUP(gia_khuyen_mai[[#This Row],[Mã sản phẩm]],product[[Mã sản phẩm]:[DS - ĐV]],3,0) -> Food Đức Việt
A100: =ROW()-1 -> 99 | B100: Post 13 | C100: Toàn bộ | D100: Toàn quốc | E100: 10/06/2026 | F100: 08/07/2026 | G100: 8935101607099 | H100: =VLOOKUP(gia_khuyen_mai[[#This Row],[Barcode]],'Giá gốc'!$A:$B,2,0) -> 2145697 | I100: =VLOOKUP(gia_khuyen_mai[[#This Row],[Mã sản phẩm]],'Giá gốc'!$B:$C,2,0) -> Seoul nhân phô mai 250g | J100: =VLOOKUP(gia_khuyen_mai[[#This Row],[Mã sản phẩm]],'Giá gốc'!B:D,3,0) -> 42000 | K100: 0.22 | L100: =ROUND((1-gia_khuyen_mai[[#This Row],[% Giảm giá]]) * gia_khuyen_mai[[#This Row],[Giá gốc]], 0) -> 32760 | O100: =IFERROR(VLOOKUP(gia_khuyen_mai[[#This Row],[Mã hàng tặng]],'Giá gốc'!B:C,2,0),"") | Q100: =VLOOKUP(gia_khuyen_mai[[#This Row],[Mã sản phẩm]],product[[Mã sản phẩm]:[DS - ĐV]],3,0) -> Food Đức Việt
A101: =ROW()-1 -> 100 | B101: Post 13 | C101: Toàn bộ | D101: Toàn quốc | E101: 10/06/2026 | F101: 08/07/2026 | G101: 8935101608515 | H101: =VLOOKUP(gia_khuyen_mai[[#This Row],[Barcode]],'Giá gốc'!$A:$B,2,0) -> 2151032 | I101: =VLOOKUP(gia_khuyen_mai[[#This Row],[Mã sản phẩm]],'Giá gốc'!$B:$C,2,0) -> Jongga Kim chi Củ cải 450g | J101: =VLOOKUP(gia_khuyen_mai[[#This Row],[Mã sản phẩm]],'Giá gốc'!B:D,3,0) -> 42000 | K101: 0.3 | L101: =ROUND((1-gia_khuyen_mai[[#This Row],[% Giảm giá]]) * gia_khuyen_mai[[#This Row],[Giá gốc]], 0) -> 29400 | O101: =IFERROR(VLOOKUP(gia_khuyen_mai[[#This Row],[Mã hàng tặng]],'Giá gốc'!B:C,2,0),"") | Q101: =VLOOKUP(gia_khuyen_mai[[#This Row],[Mã sản phẩm]],product[[Mã sản phẩm]:[DS - ĐV]],3,0) -> Food Đức Việt
A102: =ROW()-1 -> 101 | B102: Post 13 | C102: Toàn bộ | D102: Toàn quốc | E102: 10/06/2026 | F102: 08/07/2026 | G102: 8935101608546 | H102: =VLOOKUP(gia_khuyen_mai[[#This Row],[Barcode]],'Giá gốc'!$A:$B,2,0) -> 2151765 | I102: =VLOOKUP(gia_khuyen_mai[[#This Row],[Mã sản phẩm]],'Giá gốc'!$B:$C,2,0) -> Ức gà hong khói 100g | J102: =VLOOKUP(gia_khuyen_mai[[#This Row],[Mã sản phẩm]],'Giá gốc'!B:D,3,0) -> 26000 | K102: 0.22 | L102: =ROUND((1-gia_khuyen_mai[[#This Row],[% Giảm giá]]) * gia_khuyen_mai[[#This Row],[Giá gốc]], 0) -> 20280 | O102: =IFERROR(VLOOKUP(gia_khuyen_mai[[#This Row],[Mã hàng tặng]],'Giá gốc'!B:C,2,0),"") | Q102: =VLOOKUP(gia_khuyen_mai[[#This Row],[Mã sản phẩm]],product[[Mã sản phẩm]:[DS - ĐV]],3,0) -> Food Đức Việt
A103: =ROW()-1 -> 102 | B103: Post 13 | C103: Toàn bộ | D103: Toàn quốc | E103: 10/06/2026 | F103: 08/07/2026 | G103: 8935101608508 | H103: =VLOOKUP(gia_khuyen_mai[[#This Row],[Barcode]],'Giá gốc'!$A:$B,2,0) -> 2150771 | I103: =VLOOKUP(gia_khuyen_mai[[#This Row],[Mã sản phẩm]],'Giá gốc'!$B:$C,2,0) -> Lạp xưởng tươi (62g) 500g | J103: =VLOOKUP(gia_khuyen_mai[[#This Row],[Mã sản phẩm]],'Giá gốc'!B:D,3,0) -> 105000 | K103: 0.25 | L103: =ROUND((1-gia_khuyen_mai[[#This Row],[% Giảm giá]]) * gia_khuyen_mai[[#This Row],[Giá gốc]], 0) -> 78750 | O103: =IFERROR(VLOOKUP(gia_khuyen_mai[[#This Row],[Mã hàng tặng]],'Giá gốc'!B:C,2,0),"") | Q103: =VLOOKUP(gia_khuyen_mai[[#This Row],[Mã sản phẩm]],product[[Mã sản phẩm]:[DS - ĐV]],3,0) -> Food Đức Việt
A104: =ROW()-1 -> 103 | B104: Post 13 | C104: Toàn bộ | D104: Toàn quốc | E104: 10/06/2026 | F104: 08/07/2026 | G104: 8935101608409 | H104: =VLOOKUP(gia_khuyen_mai[[#This Row],[Barcode]],'Giá gốc'!$A:$B,2,0) -> 2148987 | I104: =VLOOKUP(gia_khuyen_mai[[#This Row],[Mã sản phẩm]],'Giá gốc'!$B:$C,2,0) -> Kimchi cải thảo cắt lát 150g * 30EA | J104: =VLOOKUP(gia_khuyen_mai[[#This Row],[Mã sản phẩm]],'Giá gốc'!B:D,3,0) -> 14200 | K104: 0.25 | L104: =ROUND((1-gia_khuyen_mai[[#This Row],[% Giảm giá]]) * gia_khuyen_mai[[#This Row],[Giá gốc]], 0) -> 10650 | O104: =IFERROR(VLOOKUP(gia_khuyen_mai[[#This Row],[Mã hàng tặng]],'Giá gốc'!B:C,2,0),"") | Q104: =VLOOKUP(gia_khuyen_mai[[#This Row],[Mã sản phẩm]],product[[Mã sản phẩm]:[DS - ĐV]],3,0) -> Food Đức Việt
A105: =ROW()-1 -> 104 | B105: Post 13 | C105: Toàn bộ | D105: Toàn quốc | E105: 10/06/2026 | F105: 08/07/2026 | G105: 8935101608492 | H105: =VLOOKUP(gia_khuyen_mai[[#This Row],[Barcode]],'Giá gốc'!$A:$B,2,0) -> 2149794 | I105: =VLOOKUP(gia_khuyen_mai[[#This Row],[Mã sản phẩm]],'Giá gốc'!$B:$C,2,0) -> Xúc xích Romas Light 500g | J105: =VLOOKUP(gia_khuyen_mai[[#This Row],[Mã sản phẩm]],'Giá gốc'!B:D,3,0) -> 44000 | K105: 0.22 | L105: =ROUND((1-gia_khuyen_mai[[#This Row],[% Giảm giá]]) * gia_khuyen_mai[[#This Row],[Giá gốc]], 0) -> 34320 | O105: =IFERROR(VLOOKUP(gia_khuyen_mai[[#This Row],[Mã hàng tặng]],'Giá gốc'!B:C,2,0),"") | Q105: =VLOOKUP(gia_khuyen_mai[[#This Row],[Mã sản phẩm]],product[[Mã sản phẩm]:[DS - ĐV]],3,0) -> Food Đức Việt
A106: =ROW()-1 -> 105 | B106: Post 13 | C106: Toàn bộ | D106: Toàn quốc | E106: 10/06/2026 | F106: 08/07/2026 | G106: 8935101607068 | H106: =VLOOKUP(gia_khuyen_mai[[#This Row],[Barcode]],'Giá gốc'!$A:$B,2,0) -> 2145724 | I106: =VLOOKUP(gia_khuyen_mai[[#This Row],[Mã sản phẩm]],'Giá gốc'!$B:$C,2,0) -> ĐỨC VIỆT Xúc xích Keilbasa 200g | J106: =VLOOKUP(gia_khuyen_mai[[#This Row],[Mã sản phẩm]],'Giá gốc'!B:D,3,0) -> 52000 | K106: 0.3 | L106: =ROUND((1-gia_khuyen_mai[[#This Row],[% Giảm giá]]) * gia_khuyen_mai[[#This Row],[Giá gốc]], 0) -> 36400 | O106: =IFERROR(VLOOKUP(gia_khuyen_mai[[#This Row],[Mã hàng tặng]],'Giá gốc'!B:C,2,0),"") | Q106: =VLOOKUP(gia_khuyen_mai[[#This Row],[Mã sản phẩm]],product[[Mã sản phẩm]:[DS - ĐV]],3,0) -> Food Đức Việt
A107: =ROW()-1 -> 106 | B107: Post 13 | C107: Win+ | D107: Toàn quốc | E107: 11/06/2026 | F107: 08/07/2026 | G107: 8935101608102 | H107: =VLOOKUP(gia_khuyen_mai[[#This Row],[Barcode]],'Giá gốc'!$A:$B,2,0) -> 2145622 | I107: =VLOOKUP(gia_khuyen_mai[[#This Row],[Mã sản phẩm]],'Giá gốc'!$B:$C,2,0) -> Kim chi 450 | J107: =VLOOKUP(gia_khuyen_mai[[#This Row],[Mã sản phẩm]],'Giá gốc'!B:D,3,0) -> 35500 | L107: =ROUND((1-gia_khuyen_mai[[#This Row],[% Giảm giá]]) * gia_khuyen_mai[[#This Row],[Giá gốc]], 0) -> 35500 | M107: Mua 1 tặng 1 | N107: =VLOOKUP(gia_khuyen_mai[[#This Row],[Barcode]],'Giá gốc'!$A:$B,2,0) -> 2145622 | O107: =IFERROR(VLOOKUP(gia_khuyen_mai[[#This Row],[Mã hàng tặng]],'Giá gốc'!B:C,2,0),"") -> Kim chi 450 | Q107: =VLOOKUP(gia_khuyen_mai[[#This Row],[Mã sản phẩm]],product[[Mã sản phẩm]:[DS - ĐV]],3,0) -> Food Đức Việt
A108: =ROW()-1 -> 107 | B108: post 14 | C108: Win+ | D108: Toàn quốc | E108: 24/06/2026 | F108: 22/07/2026 | G108: 8935101600250 | H108: =VLOOKUP(gia_khuyen_mai[[#This Row],[Barcode]],'Giá gốc'!$A:$B,2,0) -> 2145686 | I108: =VLOOKUP(gia_khuyen_mai[[#This Row],[Mã sản phẩm]],'Giá gốc'!$B:$C,2,0) -> Xúc xích hong khói 450g | J108: =VLOOKUP(gia_khuyen_mai[[#This Row],[Mã sản phẩm]],'Giá gốc'!B:D,3,0) -> 79100 | L108: =ROUND((1-gia_khuyen_mai[[#This Row],[% Giảm giá]]) * gia_khuyen_mai[[#This Row],[Giá gốc]], 0) -> 79100 | M108: Mua 1 tặng 1 | N108: 2145762 | O108: =IFERROR(VLOOKUP(gia_khuyen_mai[[#This Row],[Mã hàng tặng]],'Giá gốc'!B:C,2,0),"") -> Xúc xích Cocktail 200g | Q108: =VLOOKUP(gia_khuyen_mai[[#This Row],[Mã sản phẩm]],product[[Mã sản phẩm]:[DS - ĐV]],3,0) -> Food Đức Việt
A109: =ROW()-1 -> 108 | B109: post 14 | C109: Win+ | D109: Toàn quốc | E109: 24/06/2026 | F109: 22/07/2026 | G109: 8935101604913 | H109: =VLOOKUP(gia_khuyen_mai[[#This Row],[Barcode]],'Giá gốc'!$A:$B,2,0) -> 2145762 | I109: =VLOOKUP(gia_khuyen_mai[[#This Row],[Mã sản phẩm]],'Giá gốc'!$B:$C,2,0) -> Xúc xích Cocktail 200g | J109: =VLOOKUP(gia_khuyen_mai[[#This Row],[Mã sản phẩm]],'Giá gốc'!B:D,3,0) -> 21100 | K109: 0.2 | L109: =ROUND((1-gia_khuyen_mai[[#This Row],[% Giảm giá]]) * gia_khuyen_mai[[#This Row],[Giá gốc]], 0) -> 16880 | O109: =IFERROR(VLOOKUP(gia_khuyen_mai[[#This Row],[Mã hàng tặng]],'Giá gốc'!B:C,2,0),"") | Q109: =VLOOKUP(gia_khuyen_mai[[#This Row],[Mã sản phẩm]],product[[Mã sản phẩm]:[DS - ĐV]],3,0) -> Food Đức Việt
A110: =ROW()-1 -> 109 | B110: post 14 | C110: Win+ | D110: Toàn quốc | E110: 24/06/2026 | F110: 22/07/2026 | G110: 8935101607945 | H110: =VLOOKUP(gia_khuyen_mai[[#This Row],[Barcode]],'Giá gốc'!$A:$B,2,0) -> 2145747 | I110: =VLOOKUP(gia_khuyen_mai[[#This Row],[Mã sản phẩm]],'Giá gốc'!$B:$C,2,0) -> Xúc xích thịt heo Bragenwurst 400g | J110: =VLOOKUP(gia_khuyen_mai[[#This Row],[Mã sản phẩm]],'Giá gốc'!B:D,3,0) -> 82080 | K110: 0.3 | L110: =ROUND((1-gia_khuyen_mai[[#This Row],[% Giảm giá]]) * gia_khuyen_mai[[#This Row],[Giá gốc]], 0) -> 57456 | O110: =IFERROR(VLOOKUP(gia_khuyen_mai[[#This Row],[Mã hàng tặng]],'Giá gốc'!B:C,2,0),"") | Q110: =VLOOKUP(gia_khuyen_mai[[#This Row],[Mã sản phẩm]],product[[Mã sản phẩm]:[DS - ĐV]],3,0) -> Food Đức Việt
A111: =ROW()-1 -> 110 | B111: post 14 | C111: Win+ | D111: Toàn quốc | E111: 24/06/2026 | F111: 22/07/2026 | G111: 8935101605118 | H111: =VLOOKUP(gia_khuyen_mai[[#This Row],[Barcode]],'Giá gốc'!$A:$B,2,0) -> 2145783 | I111: =VLOOKUP(gia_khuyen_mai[[#This Row],[Mã sản phẩm]],'Giá gốc'!$B:$C,2,0) -> Xúc xích Romas ( 50g) 500g | J111: =VLOOKUP(gia_khuyen_mai[[#This Row],[Mã sản phẩm]],'Giá gốc'!B:D,3,0) -> 53900 | K111: 0.22 | L111: =ROUND((1-gia_khuyen_mai[[#This Row],[% Giảm giá]]) * gia_khuyen_mai[[#This Row],[Giá gốc]], 0) -> 42042 | O111: =IFERROR(VLOOKUP(gia_khuyen_mai[[#This Row],[Mã hàng tặng]],'Giá gốc'!B:C,2,0),"") | Q111: =VLOOKUP(gia_khuyen_mai[[#This Row],[Mã sản phẩm]],product[[Mã sản phẩm]:[DS - ĐV]],3,0) -> Food Đức Việt
A112: =ROW()-1 -> 111 | B112: post 14 | C112: Win+ | D112: Toàn quốc | E112: 24/06/2026 | F112: 22/07/2026 | G112: 8935101607938 | H112: =VLOOKUP(gia_khuyen_mai[[#This Row],[Barcode]],'Giá gốc'!$A:$B,2,0) -> 2145726 | I112: =VLOOKUP(gia_khuyen_mai[[#This Row],[Mã sản phẩm]],'Giá gốc'!$B:$C,2,0) -> Xúc xích phô mai Cheesy 250g | J112: =VLOOKUP(gia_khuyen_mai[[#This Row],[Mã sản phẩm]],'Giá gốc'!B:D,3,0) -> 49400 | K112: 0.25 | L112: =ROUND((1-gia_khuyen_mai[[#This Row],[% Giảm giá]]) * gia_khuyen_mai[[#This Row],[Giá gốc]], 0) -> 37050 | O112: =IFERROR(VLOOKUP(gia_khuyen_mai[[#This Row],[Mã hàng tặng]],'Giá gốc'!B:C,2,0),"") | Q112: =VLOOKUP(gia_khuyen_mai[[#This Row],[Mã sản phẩm]],product[[Mã sản phẩm]:[DS - ĐV]],3,0) -> Food Đức Việt
A113: =ROW()-1 -> 112 | B113: post 14 | C113: Win+ | D113: Toàn quốc | E113: 24/06/2026 | F113: 22/07/2026 | G113: 8935101607877 | H113: =VLOOKUP(gia_khuyen_mai[[#This Row],[Barcode]],'Giá gốc'!$A:$B,2,0) -> 2145699 | I113: =VLOOKUP(gia_khuyen_mai[[#This Row],[Mã sản phẩm]],'Giá gốc'!$B:$C,2,0) -> Seoul's Hotdog Chiên xù 250g (Đ) | J113: =VLOOKUP(gia_khuyen_mai[[#This Row],[Mã sản phẩm]],'Giá gốc'!B:D,3,0) -> 39150 | K113: 0.25 | L113: =ROUND((1-gia_khuyen_mai[[#This Row],[% Giảm giá]]) * gia_khuyen_mai[[#This Row],[Giá gốc]], 0) -> 29363 | O113: =IFERROR(VLOOKUP(gia_khuyen_mai[[#This Row],[Mã hàng tặng]],'Giá gốc'!B:C,2,0),"") | Q113: =VLOOKUP(gia_khuyen_mai[[#This Row],[Mã sản phẩm]],product[[Mã sản phẩm]:[DS - ĐV]],3,0) -> Food Đức Việt
A114: =ROW()-1 -> 113 | B114: post 14 | C114: Win+ | D114: Toàn quốc | E114: 09/07/2026 | F114: 22/07/2026 | G114: 8935101608102 | H114: =VLOOKUP(gia_khuyen_mai[[#This Row],[Barcode]],'Giá gốc'!$A:$B,2,0) -> 2145622 | I114: =VLOOKUP(gia_khuyen_mai[[#This Row],[Mã sản phẩm]],'Giá gốc'!$B:$C,2,0) -> Kim chi 450 | J114: =VLOOKUP(gia_khuyen_mai[[#This Row],[Mã sản phẩm]],'Giá gốc'!B:D,3,0) -> 35500 | L114: =ROUND((1-gia_khuyen_mai[[#This Row],[% Giảm giá]]) * gia_khuyen_mai[[#This Row],[Giá gốc]], 0) -> 35500 | M114: Mua 1 tặng 1 | N114: 2151140 | O114: =IFERROR(VLOOKUP(gia_khuyen_mai[[#This Row],[Mã hàng tặng]],'Giá gốc'!B:C,2,0),"") -> Jongga Kim chi Củ cải 150g | Q114: =VLOOKUP(gia_khuyen_mai[[#This Row],[Mã sản phẩm]],product[[Mã sản phẩm]:[DS - ĐV]],3,0) -> Food Đức Việt
A115: =ROW()-1 -> 114 | B115: post 14 | C115: Win+ | D115: Toàn quốc | E115: 25/06/2026 | F115: 22/07/2026 | G115: 8935101608522 | H115: =VLOOKUP(gia_khuyen_mai[[#This Row],[Barcode]],'Giá gốc'!$A:$B,2,0) -> 2151140 | I115: =VLOOKUP(gia_khuyen_mai[[#This Row],[Mã sản phẩm]],'Giá gốc'!$B:$C,2,0) -> Jongga Kim chi Củ cải 150g | J115: =VLOOKUP(gia_khuyen_mai[[#This Row],[Mã sản phẩm]],'Giá gốc'!B:D,3,0) -> 16500 | K115: 0.25 | L115: =ROUND((1-gia_khuyen_mai[[#This Row],[% Giảm giá]]) * gia_khuyen_mai[[#This Row],[Giá gốc]], 0) -> 12375 | O115: =IFERROR(VLOOKUP(gia_khuyen_mai[[#This Row],[Mã hàng tặng]],'Giá gốc'!B:C,2,0),"") | Q115: =VLOOKUP(gia_khuyen_mai[[#This Row],[Mã sản phẩm]],product[[Mã sản phẩm]:[DS - ĐV]],3,0) -> Food Đức Việt
A116: =ROW()-1 -> 115 | B116: post 14 | C116: Win+ | D116: Toàn quốc | E116: 24/06/2026 | F116: 22/07/2026 | G116: 8935101608461 | H116: =VLOOKUP(gia_khuyen_mai[[#This Row],[Barcode]],'Giá gốc'!$A:$B,2,0) -> 2150338 | I116: =VLOOKUP(gia_khuyen_mai[[#This Row],[Mã sản phẩm]],'Giá gốc'!$B:$C,2,0) -> O'food Chả giò da xốp hải sản 300g | J116: =VLOOKUP(gia_khuyen_mai[[#This Row],[Mã sản phẩm]],'Giá gốc'!B:D,3,0) -> 31524 | K116: 0.25 | L116: =ROUND((1-gia_khuyen_mai[[#This Row],[% Giảm giá]]) * gia_khuyen_mai[[#This Row],[Giá gốc]], 0) -> 23643 | O116: =IFERROR(VLOOKUP(gia_khuyen_mai[[#This Row],[Mã hàng tặng]],'Giá gốc'!B:C,2,0),"") | Q116: =VLOOKUP(gia_khuyen_mai[[#This Row],[Mã sản phẩm]],product[[Mã sản phẩm]:[DS - ĐV]],3,0) -> Food Đức Việt
A117: =ROW()-1 -> 116 | B117: post 15 | C117: Toàn bộ | D117: Toàn quốc | E117: 09/07/2026 | F117: 05/08/2026 | G117: 8935101600625 | H117: =VLOOKUP(gia_khuyen_mai[[#This Row],[Barcode]],'Giá gốc'!$A:$B,2,0) -> 2145689 | I117: =VLOOKUP(gia_khuyen_mai[[#This Row],[Mã sản phẩm]],'Giá gốc'!$B:$C,2,0) -> Xúc xích vườn bia 450g * 1EA | J117: =VLOOKUP(gia_khuyen_mai[[#This Row],[Mã sản phẩm]],'Giá gốc'!B:D,3,0) -> 84200 | K117: 0.05 | L117: =ROUND((1-gia_khuyen_mai[[#This Row],[% Giảm giá]]) * gia_khuyen_mai[[#This Row],[Giá gốc]], 0) -> 79990 | M117: Mua 1 tặng 1 | N117: 2145762 | O117: =IFERROR(VLOOKUP(gia_khuyen_mai[[#This Row],[Mã hàng tặng]],'Giá gốc'!B:C,2,0),"") -> Xúc xích Cocktail 200g | Q117: =VLOOKUP(gia_khuyen_mai[[#This Row],[Mã sản phẩm]],product[[Mã sản phẩm]:[DS - ĐV]],3,0) -> Food Đức Việt
A118: =ROW()-1 -> 117 | B118: post 15 | C118: Toàn bộ | D118: Toàn quốc | E118: 09/07/2026 | F118: 05/08/2026 | G118: 8935101608515 | H118: =VLOOKUP(gia_khuyen_mai[[#This Row],[Barcode]],'Giá gốc'!$A:$B,2,0) -> 2151032 | I118: =VLOOKUP(gia_khuyen_mai[[#This Row],[Mã sản phẩm]],'Giá gốc'!$B:$C,2,0) -> Jongga Kim chi Củ cải 450g | J118: =VLOOKUP(gia_khuyen_mai[[#This Row],[Mã sản phẩm]],'Giá gốc'!B:D,3,0) -> 42000 | K118: 0.3 | L118: =ROUND((1-gia_khuyen_mai[[#This Row],[% Giảm giá]]) * gia_khuyen_mai[[#This Row],[Giá gốc]], 0) -> 29400 | O118: =IFERROR(VLOOKUP(gia_khuyen_mai[[#This Row],[Mã hàng tặng]],'Giá gốc'!B:C,2,0),"") | Q118: =VLOOKUP(gia_khuyen_mai[[#This Row],[Mã sản phẩm]],product[[Mã sản phẩm]:[DS - ĐV]],3,0) -> Food Đức Việt
...

Sheet Thông tin điểm giao
A1: Mã điểm giao | B1: Hệ thống | C1: Tên điểm giao | D1: Địa chỉ điểm giao | E1: Mã khách hàng | F1: Tên khách hàng | G1: Chi nhánh | H1: Nhóm hàng | I1: Mã kho
A2: 5858 | B2: Win+ | C2: #N/A | D2: Số nhà 297, Cụm 2, Xã Thọ Xuân, Huyện Đan Phượng, TP. Hà Nội Việt Nam | E2: 73002016 | F2: =VLOOKUP(Table8[[#This Row],[Mã khách hàng]],code_khach_hang[],2,0) -> CHI NHÁNH HẢI DƯƠNG - CÔNG TY CỔ PHẦN DỊCH VỤ THƯƠNG MẠI TỔNG HỢP WINCOMMERCE | G2: =VLOOKUP(Table8[[#This Row],[Mã khách hàng]],code_khach_hang[],3,0) -> Miền Bắc đặc biệt 3 | H2: =VLOOKUP(Table8[[#This Row],[Mã khách hàng]],'Khách hàng'!A:D,4,0) -> Food Đức Việt | I2: =VLOOKUP(Table8[[#This Row],[Mã khách hàng]],'Khách hàng'!A:E,5,0) -> HN0040
A3: 6337 | B3: Win+ | C3: WM+ BNH 12-14 Tân Dân | D3: Tầng L1, TTTM Vincom Plaza Bắc Giang thuộc dự án đầu tư xây dựng nhà ở thương mại, số 41 đường Ngô Gia Tự, phường Bắc Giang, Tỉnh Bắc Ninh Việt Nam | E3: 73002010 | F3: =VLOOKUP(Table8[[#This Row],[Mã khách hàng]],code_khach_hang[],2,0) -> CHI NHÁNH BẮC NINH - CÔNG TY CỔ PHẦN DỊCH VỤ THƯƠNG MẠI TỔNG HỢP WINCOMMERCE | G3: =VLOOKUP(Table8[[#This Row],[Mã khách hàng]],code_khach_hang[],3,0) -> Miền Bắc đặc biệt 2 | H3: =VLOOKUP(Table8[[#This Row],[Mã khách hàng]],'Khách hàng'!A:D,4,0) -> Food Đức Việt | I3: =VLOOKUP(Table8[[#This Row],[Mã khách hàng]],'Khách hàng'!A:E,5,0) -> HN0040
A4: 4238 | B4: Win+ | C4: WM+ BNH Giang Liễu | D4: Số 531-533 Phố Đồi Ngô, Xã Lục Nam, T. Bắc Ninh Việt Nam | E4: 73002010 | F4: =VLOOKUP(Table8[[#This Row],[Mã khách hàng]],code_khach_hang[],2,0) -> CHI NHÁNH BẮC NINH - CÔNG TY CỔ PHẦN DỊCH VỤ THƯƠNG MẠI TỔNG HỢP WINCOMMERCE | G4: =VLOOKUP(Table8[[#This Row],[Mã khách hàng]],code_khach_hang[],3,0) -> Miền Bắc đặc biệt 2 | H4: =VLOOKUP(Table8[[#This Row],[Mã khách hàng]],'Khách hàng'!A:D,4,0) -> Food Đức Việt | I4: =VLOOKUP(Table8[[#This Row],[Mã khách hàng]],'Khách hàng'!A:E,5,0) -> HN0040
A5: 5871 | B5: Win+ | C5: WM+ BNH Khu 1 Phố Mới | D5: Số 101–103, Thôn Đội Cấn, Xã Vĩnh Tường, Tỉnh Phú Thọ T. Phú Thọ Việt Nam | E5: 73002010 | F5: =VLOOKUP(Table8[[#This Row],[Mã khách hàng]],code_khach_hang[],2,0) -> CHI NHÁNH BẮC NINH - CÔNG TY CỔ PHẦN DỊCH VỤ THƯƠNG MẠI TỔNG HỢP WINCOMMERCE | G5: =VLOOKUP(Table8[[#This Row],[Mã khách hàng]],code_khach_hang[],3,0) -> Miền Bắc đặc biệt 2 | H5: =VLOOKUP(Table8[[#This Row],[Mã khách hàng]],'Khách hàng'!A:D,4,0) -> Food Đức Việt | I5: =VLOOKUP(Table8[[#This Row],[Mã khách hàng]],'Khách hàng'!A:E,5,0) -> HN0040
A6: 6149 | B6: Win+ | C6: WM+ BNH Mao Dộc, Quế Võ | D6: Tòa nhà CT1A- CT1B Khu đô thị Xa la-, Quận Hà Đông, TP. Hà Nội Việt Nam | E6: 73002010 | F6: =VLOOKUP(Table8[[#This Row],[Mã khách hàng]],code_khach_hang[],2,0) -> CHI NHÁNH BẮC NINH - CÔNG TY CỔ PHẦN DỊCH VỤ THƯƠNG MẠI TỔNG HỢP WINCOMMERCE | G6: =VLOOKUP(Table8[[#This Row],[Mã khách hàng]],code_khach_hang[],3,0) -> Miền Bắc đặc biệt 2 | H6: =VLOOKUP(Table8[[#This Row],[Mã khách hàng]],'Khách hàng'!A:D,4,0) -> Food Đức Việt | I6: =VLOOKUP(Table8[[#This Row],[Mã khách hàng]],'Khách hàng'!A:E,5,0) -> HN0040
A7: 5985 | B7: Win+ | C7: WM+ BNH 380 - 382 Âu Cơ | D7: Tổ hợp nhà ở 28 tầng, làng Quốc tế, Thăng Long, P. Dịch Vọng, Quận Cầu Giấy, TP. Hà Nội Việt Nam | E7: 73002010 | F7: =VLOOKUP(Table8[[#This Row],[Mã khách hàng]],code_khach_hang[],2,0) -> CHI NHÁNH BẮC NINH - CÔNG TY CỔ PHẦN DỊCH VỤ THƯƠNG MẠI TỔNG HỢP WINCOMMERCE | G7: =VLOOKUP(Table8[[#This Row],[Mã khách hàng]],code_khach_hang[],3,0) -> Miền Bắc đặc biệt 2 | H7: =VLOOKUP(Table8[[#This Row],[Mã khách hàng]],'Khách hàng'!A:D,4,0) -> Food Đức Việt | I7: =VLOOKUP(Table8[[#This Row],[Mã khách hàng]],'Khách hàng'!A:E,5,0) -> HN0040
A8: 6263 | B8: Win+ | C8: WM+ BNH Khương Tự, Thuận Thành | D8: Số 72A đường Nguyễn Trãi - P., Thượng Đình, Quận Thanh Xuân, TP. Hà Nội Việt Nam | E8: 73002010 | F8: =VLOOKUP(Table8[[#This Row],[Mã khách hàng]],code_khach_hang[],2,0) -> CHI NHÁNH BẮC NINH - CÔNG TY CỔ PHẦN DỊCH VỤ THƯƠNG MẠI TỔNG HỢP WINCOMMERCE | G8: =VLOOKUP(Table8[[#This Row],[Mã khách hàng]],code_khach_hang[],3,0) -> Miền Bắc đặc biệt 2 | H8: =VLOOKUP(Table8[[#This Row],[Mã khách hàng]],'Khách hàng'!A:D,4,0) -> Food Đức Việt | I8: =VLOOKUP(Table8[[#This Row],[Mã khách hàng]],'Khách hàng'!A:E,5,0) -> HN0040
A9: 6386 | B9: Win+ | C9: WM+ BNH Ấp Đông Côi, TT Hồ | D9: TTTM Ocean Mall Trung Hòa - Đường, Hoàng Đạo Thúy, Quận Cầu Giấy, TP. Hà Nội Việt Nam | E9: 73002010 | F9: =VLOOKUP(Table8[[#This Row],[Mã khách hàng]],code_khach_hang[],2,0) -> CHI NHÁNH BẮC NINH - CÔNG TY CỔ PHẦN DỊCH VỤ THƯƠNG MẠI TỔNG HỢP WINCOMMERCE | G9: =VLOOKUP(Table8[[#This Row],[Mã khách hàng]],code_khach_hang[],3,0) -> Miền Bắc đặc biệt 2 | H9: =VLOOKUP(Table8[[#This Row],[Mã khách hàng]],'Khách hàng'!A:D,4,0) -> Food Đức Việt | I9: =VLOOKUP(Table8[[#This Row],[Mã khách hàng]],'Khách hàng'!A:E,5,0) -> HN0040
A10: 6433 | B10: Win+ | C10: WM+ BNH Mão Điền, Thuận Thành | D10: B1-C55 Khu đô thị Times City, 458 Minh Khai , P. Minh Khai, , Quận Hai Bà Trưng , TP. Hà Nội, Việt Nam | E10: 73002010 | F10: =VLOOKUP(Table8[[#This Row],[Mã khách hàng]],code_khach_hang[],2,0) -> CHI NHÁNH BẮC NINH - CÔNG TY CỔ PHẦN DỊCH VỤ THƯƠNG MẠI TỔNG HỢP WINCOMMERCE | G10: =VLOOKUP(Table8[[#This Row],[Mã khách hàng]],code_khach_hang[],3,0) -> Miền Bắc đặc biệt 2 | H10: =VLOOKUP(Table8[[#This Row],[Mã khách hàng]],'Khách hàng'!A:D,4,0) -> Food Đức Việt | I10: =VLOOKUP(Table8[[#This Row],[Mã khách hàng]],'Khách hàng'!A:E,5,0) -> HN0040
A11: 6622 | B11: Win+ | C11: WM+ BNH Đông Ngoại, Thuận Thành | D11: Tầng 1, TTTM Vincom Center, 191 Bà, Triệu, P. Lê Đại Hành, Quận Hai Bà Trưng, TP. Hà Nội Việt Nam | E11: 73002010 | F11: =VLOOKUP(Table8[[#This Row],[Mã khách hàng]],code_khach_hang[],2,0) -> CHI NHÁNH BẮC NINH - CÔNG TY CỔ PHẦN DỊCH VỤ THƯƠNG MẠI TỔNG HỢP WINCOMMERCE | G11: =VLOOKUP(Table8[[#This Row],[Mã khách hàng]],code_khach_hang[],3,0) -> Miền Bắc đặc biệt 2 | H11: =VLOOKUP(Table8[[#This Row],[Mã khách hàng]],'Khách hàng'!A:D,4,0) -> Food Đức Việt | I11: =VLOOKUP(Table8[[#This Row],[Mã khách hàng]],'Khách hàng'!A:E,5,0) -> HN0040
A12: 5128 | B12: Win+ | C12: WM+ BNH Số 74 Đường Nguyễn Đăng Đạo | D12: TTTM Vincom center Long Biên , Quận Long Biên , TP. Hà Nội, Việt Nam | E12: 73002010 | F12: =VLOOKUP(Table8[[#This Row],[Mã khách hàng]],code_khach_hang[],2,0) -> CHI NHÁNH BẮC NINH - CÔNG TY CỔ PHẦN DỊCH VỤ THƯƠNG MẠI TỔNG HỢP WINCOMMERCE | G12: =VLOOKUP(Table8[[#This Row],[Mã khách hàng]],code_khach_hang[],3,0) -> Miền Bắc đặc biệt 2 | H12: =VLOOKUP(Table8[[#This Row],[Mã khách hàng]],'Khách hàng'!A:D,4,0) -> Food Đức Việt | I12: =VLOOKUP(Table8[[#This Row],[Mã khách hàng]],'Khách hàng'!A:E,5,0) -> HN0040
A13: 5226 | B13: Win+ | C13: WM+ BNH Thôn Đại Thượng | D13: Tầng 1 nhà CT7A, khu đô thị mới văn, quán, Yên Phúc, P. Phúc La, Quận Hà Đông, TP. Hà Nội Việt Nam | E13: 73002010 | F13: =VLOOKUP(Table8[[#This Row],[Mã khách hàng]],code_khach_hang[],2,0) -> CHI NHÁNH BẮC NINH - CÔNG TY CỔ PHẦN DỊCH VỤ THƯƠNG MẠI TỔNG HỢP WINCOMMERCE | G13: =VLOOKUP(Table8[[#This Row],[Mã khách hàng]],code_khach_hang[],3,0) -> Miền Bắc đặc biệt 2 | H13: =VLOOKUP(Table8[[#This Row],[Mã khách hàng]],'Khách hàng'!A:D,4,0) -> Food Đức Việt | I13: =VLOOKUP(Table8[[#This Row],[Mã khách hàng]],'Khách hàng'!A:E,5,0) -> HN0040
A14: 5433 | B14: Win+ | C14: WM+ BNH Thôn Dương Húc | D14: 54A Nguyễn Chí Thanh, Quận Đống Đa, TP. Hà Nội Việt Nam | E14: 73002010 | F14: =VLOOKUP(Table8[[#This Row],[Mã khách hàng]],code_khach_hang[],2,0) -> CHI NHÁNH BẮC NINH - CÔNG TY CỔ PHẦN DỊCH VỤ THƯƠNG MẠI TỔNG HỢP WINCOMMERCE | G14: =VLOOKUP(Table8[[#This Row],[Mã khách hàng]],code_khach_hang[],3,0) -> Miền Bắc đặc biệt 2 | H14: =VLOOKUP(Table8[[#This Row],[Mã khách hàng]],'Khách hàng'!A:D,4,0) -> Food Đức Việt | I14: =VLOOKUP(Table8[[#This Row],[Mã khách hàng]],'Khách hàng'!A:E,5,0) -> HN0040
... A107: 5885 | B107: Win+ | C107: WM+ QNH 221 Nguyễn Bình | D107: 138 Phú Diễn, P. Phú Diễn, Quận, Quận Bắc Từ Liêm, TP. Hà Nội Việt Nam | E107: 73001998 | F107: =VLOOKUP(Table8[[#This Row],[Mã khách hàng]],code_khach_hang[],2,0) -> CHI NHÁNH QUẢNG NINH - CÔNG TY CỔ PHẦN DỊCH VỤ THƯƠNG MẠI TỔNG HỢP WINCOMMERCE | G107: =VLOOKUP(Table8[[#This Row],[Mã khách hàng]],code_khach_hang[],3,0) -> Miền Bắc đặc biệt 3 | H107: =VLOOKUP(Table8[[#This Row],[Mã khách hàng]],'Khách hàng'!A:D,4,0) -> Food Đức Việt | I107: =VLOOKUP(Table8[[#This Row],[Mã khách hàng]],'Khách hàng'!A:E,5,0) -> HN0040
A108: 5933 | B108: Win+ | C108: #N/A | D108: Số 17A Hàn Thuyên, Tổ 2, Phường Phạm, m Đình Hổ, Quận Hai Bà Trưng, TP. Hà Nội Việt Nam | E108: 73001998 | F108: =VLOOKUP(Table8[[#This Row],[Mã khách hàng]],code_khach_hang[],2,0) -> CHI NHÁNH QUẢNG NINH - CÔNG TY CỔ PHẦN DỊCH VỤ THƯƠNG MẠI TỔNG HỢP WINCOMMERCE | G108: =VLOOKUP(Table8[[#This Row],[Mã khách hàng]],code_khach_hang[],3,0) -> Miền Bắc đặc biệt 3 | H108: =VLOOKUP(Table8[[#This Row],[Mã khách hàng]],'Khách hàng'!A:D,4,0) -> Food Đức Việt | I108: =VLOOKUP(Table8[[#This Row],[Mã khách hàng]],'Khách hàng'!A:E,5,0) -> HN0040
A109: 6023 | B109: Win+ | C109: WM+ QNH Kim Sơn, Đông Triều | D109: Số 47 Phó Đức Chính, Phường Trúc Bạch, Quận Ba Đình, TP. Hà Nội Việt Nam | E109: 73001998 | F109: =VLOOKUP(Table8[[#This Row],[Mã khách hàng]],code_khach_hang[],2,0) -> CHI NHÁNH QUẢNG NINH - CÔNG TY CỔ PHẦN DỊCH VỤ THƯƠNG MẠI TỔNG HỢP WINCOMMERCE | G109: =VLOOKUP(Table8[[#This Row],[Mã khách hàng]],code_khach_hang[],3,0) -> Miền Bắc đặc biệt 3 | H109: =VLOOKUP(Table8[[#This Row],[Mã khách hàng]],'Khách hàng'!A:D,4,0) -> Food Đức Việt | I109: =VLOOKUP(Table8[[#This Row],[Mã khách hàng]],'Khách hàng'!A:E,5,0) -> HN0040
A110: 6130 | B110: Win+ | C110: WM+ QNH 708 Khu Mễ Xá 2 | D110: Căn 22 Lô 1 khu Lạc Trung, Phường, Vĩnh Tuy, Quận Hai Bà Trưng, TP. Hà Nội Việt Nam | E110: 73001998 | F110: =VLOOKUP(Table8[[#This Row],[Mã khách hàng]],code_khach_hang[],2,0) -> CHI NHÁNH QUẢNG NINH - CÔNG TY CỔ PHẦN DỊCH VỤ THƯƠNG MẠI TỔNG HỢP WINCOMMERCE | G110: =VLOOKUP(Table8[[#This Row],[Mã khách hàng]],code_khach_hang[],3,0) -> Miền Bắc đặc biệt 3 | H110: =VLOOKUP(Table8[[#This Row],[Mã khách hàng]],'Khách hàng'!A:D,4,0) -> Food Đức Việt | I110: =VLOOKUP(Table8[[#This Row],[Mã khách hàng]],'Khách hàng'!A:E,5,0) -> HN0040
A111: 6681 | B111: Win+ | C111: #N/A | D111: Số 41, Tổ 5, Phố Trung Kính , Phường Trung Hòa, Quận Cầu Giấy , TP. Hà Nội, Việt Nam | E111: 73001998 | F111: =VLOOKUP(Table8[[#This Row],[Mã khách hàng]],code_khach_hang[],2,0) -> CHI NHÁNH QUẢNG NINH - CÔNG TY CỔ PHẦN DỊCH VỤ THƯƠNG MẠI TỔNG HỢP WINCOMMERCE | G111: =VLOOKUP(Table8[[#This Row],[Mã khách hàng]],code_khach_hang[],3,0) -> Miền Bắc đặc biệt 3 | H111: =VLOOKUP(Table8[[#This Row],[Mã khách hàng]],'Khách hàng'!A:D,4,0) -> Food Đức Việt | I111: =VLOOKUP(Table8[[#This Row],[Mã khách hàng]],'Khách hàng'!A:E,5,0) -> HN0040
A112: 6708 | B112: Win+ | C112: WM+ QNH 103 Hoàng Hoa Thám | D112: Số 210 Bis phố Đội Cấn, Phường Đội, Cấn, Quận Ba Đình, TP. Hà Nội Việt Nam | E112: 73001998 | F112: =VLOOKUP(Table8[[#This Row],[Mã khách hàng]],code_khach_hang[],2,0) -> CHI NHÁNH QUẢNG NINH - CÔNG TY CỔ PHẦN DỊCH VỤ THƯƠNG MẠI TỔNG HỢP WINCOMMERCE | G112: =VLOOKUP(Table8[[#This Row],[Mã khách hàng]],code_khach_hang[],3,0) -> Miền Bắc đặc biệt 3 | H112: =VLOOKUP(Table8[[#This Row],[Mã khách hàng]],'Khách hàng'!A:D,4,0) -> Food Đức Việt | I112: =VLOOKUP(Table8[[#This Row],[Mã khách hàng]],'Khách hàng'!A:E,5,0) -> HN0040
A113: 5958 | B113: Win+ | C113: WM+ QNH Khu 7, Nam Hòa | D113: Số 50 đường Nguyễn Hoàng Tôn, phường Xuân La, Quận Tây Hồ, TP. Hà Nội Việt Nam | E113: 73001998 | F113: =VLOOKUP(Table8[[#This Row],[Mã khách hàng]],code_khach_hang[],2,0) -> CHI NHÁNH QUẢNG NINH - CÔNG TY CỔ PHẦN DỊCH VỤ THƯƠNG MẠI TỔNG HỢP WINCOMMERCE | G113: =VLOOKUP(Table8[[#This Row],[Mã khách hàng]],code_khach_hang[],3,0) -> Miền Bắc đặc biệt 3 | H113: =VLOOKUP(Table8[[#This Row],[Mã khách hàng]],'Khách hàng'!A:D,4,0) -> Food Đức Việt | I113: =VLOOKUP(Table8[[#This Row],[Mã khách hàng]],'Khách hàng'!A:E,5,0) -> HN0040
A114: 6787 | B114: Win+ | C114: WM+ QNH 998 Khu Đường Ngang | D114: Số 55 Thụy Khuê, Phường Thụy Khuê, Quận Tây Hồ, TP. Hà Nội Việt Nam | E114: 73001998 | F114: =VLOOKUP(Table8[[#This Row],[Mã khách hàng]],code_khach_hang[],2,0) -> CHI NHÁNH QUẢNG NINH - CÔNG TY CỔ PHẦN DỊCH VỤ THƯƠNG MẠI TỔNG HỢP WINCOMMERCE | G114: =VLOOKUP(Table8[[#This Row],[Mã khách hàng]],code_khach_hang[],3,0) -> Miền Bắc đặc biệt 3 | H114: =VLOOKUP(Table8[[#This Row],[Mã khách hàng]],'Khách hàng'!A:D,4,0) -> Food Đức Việt | I114: =VLOOKUP(Table8[[#This Row],[Mã khách hàng]],'Khách hàng'!A:E,5,0) -> HN0040
A115: 6949 | B115: Win+ | C115: WM+ QNH 225 Lê Lợi | D115: Số 35B, đường Xuân La, Phường Xuân, La, Quận Tây Hồ, TP. Hà Nội Việt Nam | E115: 73001998 | F115: =VLOOKUP(Table8[[#This Row],[Mã khách hàng]],code_khach_hang[],2,0) -> CHI NHÁNH QUẢNG NINH - CÔNG TY CỔ PHẦN DỊCH VỤ THƯƠNG MẠI TỔNG HỢP WINCOMMERCE | G115: =VLOOKUP(Table8[[#This Row],[Mã khách hàng]],code_khach_hang[],3,0) -> Miền Bắc đặc biệt 3 | H115: =VLOOKUP(Table8[[#This Row],[Mã khách hàng]],'Khách hàng'!A:D,4,0) -> Food Đức Việt | I115: =VLOOKUP(Table8[[#This Row],[Mã khách hàng]],'Khách hàng'!A:E,5,0) -> HN0040
A116: 6899 | B116: Win+ | C116: WM+ QNH Tiền An, Quảng Yên | D116: Số 16 Võ Văn Dũng, Phường Ô Chợ, Dừa, Quận Đống Đa, TP. Hà Nội Việt Nam | E116: 73001998 | F116: =VLOOKUP(Table8[[#This Row],[Mã khách hàng]],code_khach_hang[],2,0) -> CHI NHÁNH QUẢNG NINH - CÔNG TY CỔ PHẦN DỊCH VỤ THƯƠNG MẠI TỔNG HỢP WINCOMMERCE | G116: =VLOOKUP(Table8[[#This Row],[Mã khách hàng]],code_khach_hang[],3,0) -> Miền Bắc đặc biệt 3 | H116: =VLOOKUP(Table8[[#This Row],[Mã khách hàng]],'Khách hàng'!A:D,4,0) -> Food Đức Việt | I116: =VLOOKUP(Table8[[#This Row],[Mã khách hàng]],'Khách hàng'!A:E,5,0) -> HN0040
A117: 6986 | B117: Win+ | C117: WM+ QNH 161 Lê Lợi | D117: Số 3, dãy N1, Học viện Chính trị qu, ân sự, Phường Trung Văn, Quận Nam Từ Liêm, TP. Hà Nội Việt Nam | E117: 73001998 | F117: =VLOOKUP(Table8[[#This Row],[Mã khách hàng]],code_khach_hang[],2,0) -> CHI NHÁNH QUẢNG NINH - CÔNG TY CỔ PHẦN DỊCH VỤ THƯƠNG MẠI TỔNG HỢP WINCOMMERCE | G117: =VLOOKUP(Table8[[#This Row],[Mã khách hàng]],code_khach_hang[],3,0) -> Miền Bắc đặc biệt 3 | H117: =VLOOKUP(Table8[[#This Row],[Mã khách hàng]],'Khách hàng'!A:D,4,0) -> Food Đức Việt | I117: =VLOOKUP(Table8[[#This Row],[Mã khách hàng]],'Khách hàng'!A:E,5,0) -> HN0040
A118: 6576 | B118: Win+ | C118: WM+ QNH 268 Trần Khánh Dư | D118: Số 10 Ngõ 118 Nguyễn Khánh Toàn, ph, ường Quan Hoa, Quận Cầu Giấy, TP. Hà Nội Việt Nam | E118: 73001998 | F118: =VLOOKUP(Table8[[#This Row],[Mã khách hàng]],code_khach_hang[],2,0) -> CHI NHÁNH QUẢNG NINH - CÔNG TY CỔ PHẦN DỊCH VỤ THƯƠNG MẠI TỔNG HỢP WINCOMMERCE | G118: =VLOOKUP(Table8[[#This Row],[Mã khách hàng]],code_khach_hang[],3,0) -> Miền Bắc đặc biệt 3 | H118: =VLOOKUP(Table8[[#This Row],[Mã khách hàng]],'Khách hàng'!A:D,4,0) -> Food Đức Việt | I118: =VLOOKUP(Table8[[#This Row],[Mã khách hàng]],'Khách hàng'!A:E,5,0) -> HN0040
A119: 2AB5 | B119: Win+ | C119: WM+ QNH 189 Tổ 18, Khu 3 Trưng Vươn | D119: Số 57 Phố 8/3, Phường Quỳnh Mai, Qu, ận Hai Bà Trưng, TP. Hà Nội Việt Nam | E119: 73001998 | F119: =VLOOKUP(Table8[[#This Row],[Mã khách hàng]],code_khach_hang[],2,0) -> CHI NHÁNH QUẢNG NINH - CÔNG TY CỔ PHẦN DỊCH VỤ THƯƠNG MẠI TỔNG HỢP WINCOMMERCE | G119: =VLOOKUP(Table8[[#This Row],[Mã khách hàng]],code_khach_hang[],3,0) -> Miền Bắc đặc biệt 3 | H119: =VLOOKUP(Table8[[#This Row],[Mã khách hàng]],'Khách hàng'!A:D,4,0) -> Food Đức Việt | I119: =VLOOKUP(Table8[[#This Row],[Mã khách hàng]],'Khách hàng'!A:E,5,0) -> HN0040
A120: 2AL2 | B120: Win+ | C120: WM+ QNH 352 Trần Phú | D120: Số 133 Phố Thụy Khuê, Phường Thụy Khuê, Quận Tây Hồ, TP. Hà Nội Việt Nam | E120: 73001998 | F120: =VLOOKUP(Table8[[#This Row],[Mã khách hàng]],code_khach_hang[],2,0) -> CHI NHÁNH QUẢNG NINH - CÔNG TY CỔ PHẦN DỊCH VỤ THƯƠNG MẠI TỔNG HỢP WINCOMMERCE | G120: =VLOOKUP(Table8[[#This Row],[Mã khách hàng]],code_khach_hang[],3,0) -> Miền Bắc đặc biệt 3 | H120: =VLOOKUP(Table8[[#This Row],[Mã khách hàng]],'Khách hàng'!A:D,4,0) -> Food Đức Việt | I120: =VLOOKUP(Table8[[#This Row],[Mã khách hàng]],'Khách hàng'!A:E,5,0) -> HN0040
A121: 1647 | B121: Winmart | C121: WM VCP QNH Móng Cái | D121: Số 409 Bạch Mai, Phường Bạch Mai, Q, uận Hai Bà Trưng, TP. Hà Nội Việt Nam | E121: 73001998 | F121: =VLOOKUP(Table8[[#This Row],[Mã khách hàng]],code_khach_hang[],2,0) -> CHI NHÁNH QUẢNG NINH - CÔNG TY CỔ PHẦN DỊCH VỤ THƯƠNG MẠI TỔNG HỢP WINCOMMERCE | G121: =VLOOKUP(Table8[[#This Row],[Mã khách hàng]],code_khach_hang[],3,0) -> Miền Bắc đặc biệt 3 | H121: =VLOOKUP(Table8[[#This Row],[Mã khách hàng]],'Khách hàng'!A:D,4,0) -> Food Đức Việt | I121: =VLOOKUP(Table8[[#This Row],[Mã khách hàng]],'Khách hàng'!A:E,5,0) -> HN0040
A122: 1605 | B122: Winmart | C122: WM VC+ QNH Uông Bí | D122: Số 18B Nguyễn Biểu, Phường Quán Thánh, Quận Ba Đình, TP. Hà Nội Việt Nam | E122: 73001998 | F122: =VLOOKUP(Table8[[#This Row],[Mã khách hàng]],code_khach_hang[],2,0) -> CHI NHÁNH QUẢNG NINH - CÔNG TY CỔ PHẦN DỊCH VỤ THƯƠNG MẠI TỔNG HỢP WINCOMMERCE | G122: =VLOOKUP(Table8[[#This Row],[Mã khách hàng]],code_khach_hang[],3,0) -> Miền Bắc đặc biệt 3 | H122: =VLOOKUP(Table8[[#This Row],[Mã khách hàng]],'Khách hàng'!A:D,4,0) -> Food Đức Việt | I122: =VLOOKUP(Table8[[#This Row],[Mã khách hàng]],'Khách hàng'!A:E,5,0) -> HN0040
A123: 5401 | B123: Win+ | C123: WM+ HPG 309 Trường Sơn | D123: 102 Lê Thanh Nghị, Phường Bách K, hoa, Quận Hai Bà Trưng, TP. Hà Nội Việt Nam | E123: 73002017 | F123: =VLOOKUP(Table8[[#This Row],[Mã khách hàng]],code_khach_hang[],2,0) -> CHI NHÁNH HẢI PHÒNG - CÔNG TY CỔ PHẦN DỊCH VỤ THƯƠNG MẠI TỔNG HỢP WINCOMMERCE | G123: =VLOOKUP(Table8[[#This Row],[Mã khách hàng]],code_khach_hang[],3,0) -> Miền Bắc đặc biệt 3 | H123: =VLOOKUP(Table8[[#This Row],[Mã khách hàng]],'Khách hàng'!A:D,4,0) -> Food Đức Việt | I123: =VLOOKUP(Table8[[#This Row],[Mã khách hàng]],'Khách hàng'!A:E,5,0) -> HN0040
... A145: 3233 | B145: Win+ | C145: WM+ HPG 118 Hùng Vương | D145: 20 Ngô Thì Nhậm, P. Hà Cầu, Quận Hà Đông, TP. Hà Nội Việt Nam | E145: 73002017 | F145: =VLOOKUP(Table8[[#This Row],[Mã khách hàng]],code_khach_hang[],2,0) -> CHI NHÁNH HẢI PHÒNG - CÔNG TY CỔ PHẦN DỊCH VỤ THƯƠNG MẠI TỔNG HỢP WINCOMMERCE | G145: =VLOOKUP(Table8[[#This Row],[Mã khách hàng]],code_khach_hang[],3,0) -> Miền Bắc đặc biệt 3 | H145: =VLOOKUP(Table8[[#This Row],[Mã khách hàng]],'Khách hàng'!A:D,4,0) -> Food Đức Việt | I145: =VLOOKUP(Table8[[#This Row],[Mã khách hàng]],'Khách hàng'!A:E,5,0) -> HN0040
A146: 3031 | B146: Win+ | C146: #N/A | D146: 129 Pháo Đài Láng, P. Láng Thượng, Đống Đa, TP. Hà Nội Việt Nam | E146: 73002017 | F146: =VLOOKUP(Table8[[#This Row],[Mã khách hàng]],code_khach_hang[],2,0) -> CHI NHÁNH HẢI PHÒNG - CÔNG TY CỔ PHẦN DỊCH VỤ THƯƠNG MẠI TỔNG HỢP WINCOMMERCE | G146: =VLOOKUP(Table8[[#This Row],[Mã khách hàng]],code_khach_hang[],3,0) -> Miền Bắc đặc biệt 3 | H146: =VLOOKUP(Table8[[#This Row],[Mã khách hàng]],'Khách hàng'!A:D,4,0) -> Food Đức Việt | I146: =VLOOKUP(Table8[[#This Row],[Mã khách hàng]],'Khách hàng'!A:E,5,0) -> HN0040
A147: 3787 | B147: Win+ | C147: WM+ HPG Club House Imperia | D147: 166 Kim Hoa, P. Phương Liên, Đống Đa, TP. Hà Nội Việt Nam | E147: 73002017 | F147: =VLOOKUP(Table8[[#This Row],[Mã khách hàng]],code_khach_hang[],2,0) -> CHI NHÁNH HẢI PHÒNG - CÔNG TY CỔ PHẦN DỊCH VỤ THƯƠNG MẠI TỔNG HỢP WINCOMMERCE | G147: =VLOOKUP(Table8[[#This Row],[Mã khách hàng]],code_khach_hang[],3,0) -> Miền Bắc đặc biệt 3 | H147: =VLOOKUP(Table8[[#This Row],[Mã khách hàng]],'Khách hàng'!A:D,4,0) -> Food Đức Việt | I147: =VLOOKUP(Table8[[#This Row],[Mã khách hàng]],'Khách hàng'!A:E,5,0) -> HN0040
A148: 5092 | B148: Win+ | C148: WM+ HPG Số 46 Bãi Sậy-Trại Chuối | D148: 66 Đại Cồ Việt, P. Lê Đại Hành, Q., Quận Hai Bà Trưng, TP. Hà Nội Việt Nam | E148: 73002017 | F148: =VLOOKUP(Table8[[#This Row],[Mã khách hàng]],code_khach_hang[],2,0) -> CHI NHÁNH HẢI PHÒNG - CÔNG TY CỔ PHẦN DỊCH VỤ THƯƠNG MẠI TỔNG HỢP WINCOMMERCE | G148: =VLOOKUP(Table8[[#This Row],[Mã khách hàng]],code_khach_hang[],3,0) -> Miền Bắc đặc biệt 3 | H148: =VLOOKUP(Table8[[#This Row],[Mã khách hàng]],'Khách hàng'!A:D,4,0) -> Food Đức Việt | I148: =VLOOKUP(Table8[[#This Row],[Mã khách hàng]],'Khách hàng'!A:E,5,0) -> HN0040
A149: 5307 | B149: Win+ | C149: WM+ HPG BH 03-11 KĐT Xi Măng HP | D149: Ô 58 lô 6 tổ 44 Đền Lừ II, P.Hoàng, Văn Thụ, Q. Hoàng Mai, TP. Hà Nội Việt Nam | E149: 73002017 | F149: =VLOOKUP(Table8[[#This Row],[Mã khách hàng]],code_khach_hang[],2,0) -> CHI NHÁNH HẢI PHÒNG - CÔNG TY CỔ PHẦN DỊCH VỤ THƯƠNG MẠI TỔNG HỢP WINCOMMERCE | G149: =VLOOKUP(Table8[[#This Row],[Mã khách hàng]],code_khach_hang[],3,0) -> Miền Bắc đặc biệt 3 | H149: =VLOOKUP(Table8[[#This Row],[Mã khách hàng]],'Khách hàng'!A:D,4,0) -> Food Đức Việt | I149: =VLOOKUP(Table8[[#This Row],[Mã khách hàng]],'Khách hàng'!A:E,5,0) -> HN0040
A150: 6083 | B150: Win+ | C150: WM+ HPG 5/4 Quán Toan | D150: 121B Quan Hoa, P. Quan Hoa, Quận Cầu Giấy, TP. Hà Nội Việt Nam | E150: 73002017 | F150: =VLOOKUP(Table8[[#This Row],[Mã khách hàng]],code_khach_hang[],2,0) -> CHI NHÁNH HẢI PHÒNG - CÔNG TY CỔ PHẦN DỊCH VỤ THƯƠNG MẠI TỔNG HỢP WINCOMMERCE | G150: =VLOOKUP(Table8[[#This Row],[Mã khách hàng]],code_khach_hang[],3,0) -> Miền Bắc đặc biệt 3 | H150: =VLOOKUP(Table8[[#This Row],[Mã khách hàng]],'Khách hàng'!A:D,4,0) -> Food Đức Việt | I150: =VLOOKUP(Table8[[#This Row],[Mã khách hàng]],'Khách hàng'!A:E,5,0) -> HN0040
A151: 6362 | B151: Win+ | C151: WM+ HPG 42 Trương Văn Lực | D151: Số 1 Ngõ 12 Chính Kinh, Phường Nhân Chính, Quận Thanh Xuân, TP. Hà Nội Việt Nam | E151: 73002017 | F151: =VLOOKUP(Table8[[#This Row],[Mã khách hàng]],code_khach_hang[],2,0) -> CHI NHÁNH HẢI PHÒNG - CÔNG TY CỔ PHẦN DỊCH VỤ THƯƠNG MẠI TỔNG HỢP WINCOMMERCE | G151: =VLOOKUP(Table8[[#This Row],[Mã khách hàng]],code_khach_hang[],3,0) -> Miền Bắc đặc biệt 3 | H151: =VLOOKUP(Table8[[#This Row],[Mã khách hàng]],'Khách hàng'!A:D,4,0) -> Food Đức Việt | I151: =VLOOKUP(Table8[[#This Row],[Mã khách hàng]],'Khách hàng'!A:E,5,0) -> HN0040
A152: 2861 | B152: Win+ | C152: WM+ HPG 12 Lê Duẩn | D152: B15 Bồ Hỏa, Quận Hà Đông, TP. Hà Nội Việt Nam | E152: 73002017 | F152: =VLOOKUP(Table8[[#This Row],[Mã khách hàng]],code_khach_hang[],2,0) -> CHI NHÁNH HẢI PHÒNG - CÔNG TY CỔ PHẦN DỊCH VỤ THƯƠNG MẠI TỔNG HỢP WINCOMMERCE | G152: =VLOOKUP(Table8[[#This Row],[Mã khách hàng]],code_khach_hang[],3,0) -> Miền Bắc đặc biệt 3 | H152: =VLOOKUP(Table8[[#This Row],[Mã khách hàng]],'Khách hàng'!A:D,4,0) -> Food Đức Việt | I152: =VLOOKUP(Table8[[#This Row],[Mã khách hàng]],'Khách hàng'!A:E,5,0) -> HN0040
A153: 3606 | B153: Win+ | C153: WM+ HPG 80 Trường Chinh | D153: 668 Lạc Long Quân, Quận Tây Hồ, TP. Hà Nội Việt Nam | E153: 73002017 | F153: =VLOOKUP(Table8[[#This Row],[Mã khách hàng]],code_khach_hang[],2,0) -> CHI NHÁNH HẢI PHÒNG - CÔNG TY CỔ PHẦN DỊCH VỤ THƯƠNG MẠI TỔNG HỢP WINCOMMERCE | G153: =VLOOKUP(Table8[[#This Row],[Mã khách hàng]],code_khach_hang[],3,0) -> Miền Bắc đặc biệt 3 | H153: =VLOOKUP(Table8[[#This Row],[Mã khách hàng]],'Khách hàng'!A:D,4,0) -> Food Đức Việt | I153: =VLOOKUP(Table8[[#This Row],[Mã khách hàng]],'Khách hàng'!A:E,5,0) -> HN0040
A154: 3943 | B154: Win+ | C154: WM+ HPG 177 Trần Nhân Tông | D154: 164 Trương Định- quận Hoàng Mai, TP. Hà Nội Việt Nam | E154: 73002017 | F154: =VLOOKUP(Table8[[#This Row],[Mã khách hàng]],code_khach_hang[],2,0) -> CHI NHÁNH HẢI PHÒNG - CÔNG TY CỔ PHẦN DỊCH VỤ THƯƠNG MẠI TỔNG HỢP WINCOMMERCE | G154: =VLOOKUP(Table8[[#This Row],[Mã khách hàng]],code_khach_hang[],3,0) -> Miền Bắc đặc biệt 3 | H154: =VLOOKUP(Table8[[#This Row],[Mã khách hàng]],'Khách hàng'!A:D,4,0) -> Food Đức Việt | I154: =VLOOKUP(Table8[[#This Row],[Mã khách hàng]],'Khách hàng'!A:E,5,0) -> HN0040
A155: 4010 | B155: Win+ | C155: WM+ HPG 42 Trần Tất Văn | D155: 27 Ngô Thì Nhậm, Quận Hai Bà Trưng, TP. Hà Nội Việt Nam | E155: 73002017 | F155: =VLOOKUP(Table8[[#This Row],[Mã khách hàng]],code_khach_hang[],2,0) -> CHI NHÁNH HẢI PHÒNG - CÔNG TY CỔ PHẦN DỊCH VỤ THƯƠNG MẠI TỔNG HỢP WINCOMMERCE | G155: =VLOOKUP(Table8[[#This Row],[Mã khách hàng]],code_khach_hang[],3,0) -> Miền Bắc đặc biệt 3 | H155: =VLOOKUP(Table8[[#This Row],[Mã khách hàng]],'Khách hàng'!A:D,4,0) -> Food Đức Việt | I155: =VLOOKUP(Table8[[#This Row],[Mã khách hàng]],'Khách hàng'!A:E,5,0) -> HN0040
A156: 4533 | B156: Win+ | C156: WM+ HPG 172 - 174 Trần Tất Văn | D156: 38 Trường Lâm, P. Đức Giang, Q. Lon, g Biên, TP. Hà Nội Việt Nam | E156: 73002017 | F156: =VLOOKUP(Table8[[#This Row],[Mã khách hàng]],code_khach_hang[],2,0) -> CHI NHÁNH HẢI PHÒNG - CÔNG TY CỔ PHẦN DỊCH VỤ THƯƠNG MẠI TỔNG HỢP WINCOMMERCE | G156: =VLOOKUP(Table8[[#This Row],[Mã khách hàng]],code_khach_hang[],3,0) -> Miền Bắc đặc biệt 3 | H156: =VLOOKUP(Table8[[#This Row],[Mã khách hàng]],'Khách hàng'!A:D,4,0) -> Food Đức Việt | I156: =VLOOKUP(Table8[[#This Row],[Mã khách hàng]],'Khách hàng'!A:E,5,0) -> HN0040
A157: 4598 | B157: Win+ | C157: WM+ HPG 1171 Trần Nhân Tông | D157: 272 Thụy Phương, P. Thụy Phương, Quận Bắc Từ Liêm, TP. Hà Nội Việt Nam | E157: 73002017 | F157: =VLOOKUP(Table8[[#This Row],[Mã khách hàng]],code_khach_hang[],2,0) -> CHI NHÁNH HẢI PHÒNG - CÔNG TY CỔ PHẦN DỊCH VỤ THƯƠNG MẠI TỔNG HỢP WINCOMMERCE | G157: =VLOOKUP(Table8[[#This Row],[Mã khách hàng]],code_khach_hang[],3,0) -> Miền Bắc đặc biệt 3 | H157: =VLOOKUP(Table8[[#This Row],[Mã khách hàng]],'Khách hàng'!A:D,4,0) -> Food Đức Việt | I157: =VLOOKUP(Table8[[#This Row],[Mã khách hàng]],'Khách hàng'!A:E,5,0) -> HN0040
A158: 4736 | B158: Win+ | C158: WM+ HPG 680 Trần Tất Văn | D158: 16X5 tái định cư 7.3 và 8.1 Mỹ Đình, 2, Q. Nam Từ Liêm, TP. Hà Nội Việt Nam | E158: 73002017 | F158: =VLOOKUP(Table8[[#This Row],[Mã khách hàng]],code_khach_hang[],2,0) -> CHI NHÁNH HẢI PHÒNG - CÔNG TY CỔ PHẦN DỊCH VỤ THƯƠNG MẠI TỔNG HỢP WINCOMMERCE | G158: =VLOOKUP(Table8[[#This Row],[Mã khách hàng]],code_khach_hang[],3,0) -> Miền Bắc đặc biệt 3 | H158: =VLOOKUP(Table8[[#This Row],[Mã khách hàng]],'Khách hàng'!A:D,4,0) -> Food Đức Việt | I158: =VLOOKUP(Table8[[#This Row],[Mã khách hàng]],'Khách hàng'!A:E,5,0) -> HN0040
... A174: 3648 | B174: Win+ | C174: WM+ HPG 239 Nguyễn Công Hòa | D174: Số 7 Nguyễn Cao, tổ 14, Phường Đống, Mác, Quận Hai Bà Trưng, TP. Hà Nội Việt Nam | E174: 73002017 | F174: =VLOOKUP(Table8[[#This Row],[Mã khách hàng]],code_khach_hang[],2,0) -> CHI NHÁNH HẢI PHÒNG - CÔNG TY CỔ PHẦN DỊCH VỤ THƯƠNG MẠI TỔNG HỢP WINCOMMERCE | G174: =VLOOKUP(Table8[[#This Row],[Mã khách hàng]],code_khach_hang[],3,0) -> Miền Bắc đặc biệt 3 | H174: =VLOOKUP(Table8[[#This Row],[Mã khách hàng]],'Khách hàng'!A:D,4,0) -> Food Đức Việt | I174: =VLOOKUP(Table8[[#This Row],[Mã khách hàng]],'Khách hàng'!A:E,5,0) -> HN0040
A175: 4635 | B175: Win+ | C175: #N/A | D175: Số 70 Vạn Kiếp, tổ 58A, Phường Bạch, Đằng, Quận Hai Bà Trưng, TP. Hà Nội Việt Nam | E175: 73002017 | F175: =VLOOKUP(Table8[[#This Row],[Mã khách hàng]],code_khach_hang[],2,0) -> CHI NHÁNH HẢI PHÒNG - CÔNG TY CỔ PHẦN DỊCH VỤ THƯƠNG MẠI TỔNG HỢP WINCOMMERCE | G175: =VLOOKUP(Table8[[#This Row],[Mã khách hàng]],code_khach_hang[],3,0) -> Miền Bắc đặc biệt 3 | H175: =VLOOKUP(Table8[[#This Row],[Mã khách hàng]],'Khách hàng'!A:D,4,0) -> Food Đức Việt | I175: =VLOOKUP(Table8[[#This Row],[Mã khách hàng]],'Khách hàng'!A:E,5,0) -> HN0040
A176: 4039 | B176: Win+ | C176: WM+ HPG 85 Đình Đông | D176: Số 41 Nguyễn Ngọc Vũ, Phường Trung, Hòa, Quận Cầu Giấy, TP. Hà Nội Việt Nam | E176: 73002017 | F176: =VLOOKUP(Table8[[#This Row],[Mã khách hàng]],code_khach_hang[],2,0) -> CHI NHÁNH HẢI PHÒNG - CÔNG TY CỔ PHẦN DỊCH VỤ THƯƠNG MẠI TỔNG HỢP WINCOMMERCE | G176: =VLOOKUP(Table8[[#This Row],[Mã khách hàng]],code_khach_hang[],3,0) -> Miền Bắc đặc biệt 3 | H176: =VLOOKUP(Table8[[#This Row],[Mã khách hàng]],'Khách hàng'!A:D,4,0) -> Food Đức Việt | I176: =VLOOKUP(Table8[[#This Row],[Mã khách hàng]],'Khách hàng'!A:E,5,0) -> HN0040
A177: 5523 | B177: Win+ | C177: #N/A | D177: Số 103 Thanh Đàm, Phường Thanh Trì, Quận Hoàng Mai, TP. Hà Nội Việt Nam | E177: 73002017 | F177: =VLOOKUP(Table8[[#This Row],[Mã khách hàng]],code_khach_hang[],2,0) -> CHI NHÁNH HẢI PHÒNG - CÔNG TY CỔ PHẦN DỊCH VỤ THƯƠNG MẠI TỔNG HỢP WINCOMMERCE | G177: =VLOOKUP(Table8[[#This Row],[Mã khách hàng]],code_khach_hang[],3,0) -> Miền Bắc đặc biệt 3 | H177: =VLOOKUP(Table8[[#This Row],[Mã khách hàng]],'Khách hàng'!A:D,4,0) -> Food Đức Việt | I177: =VLOOKUP(Table8[[#This Row],[Mã khách hàng]],'Khách hàng'!A:E,5,0) -> HN0040
A178: 4514 | B178: Win+ | C178: WM+ HPG 137 Chùa Hàng | D178: Số 19 Nguyễn Văn Huyên kéo dài, phường Quan Hoa, Quận Cầu Giấy, TP. Hà Nội Việt Nam | E178: 73002017 | F178: =VLOOKUP(Table8[[#This Row],[Mã khách hàng]],code_khach_hang[],2,0) -> CHI NHÁNH HẢI PHÒNG - CÔNG TY CỔ PHẦN DỊCH VỤ THƯƠNG MẠI TỔNG HỢP WINCOMMERCE | G178: =VLOOKUP(Table8[[#This Row],[Mã khách hàng]],code_khach_hang[],3,0) -> Miền Bắc đặc biệt 3 | H178: =VLOOKUP(Table8[[#This Row],[Mã khách hàng]],'Khách hàng'!A:D,4,0) -> Food Đức Việt | I178: =VLOOKUP(Table8[[#This Row],[Mã khách hàng]],'Khách hàng'!A:E,5,0) -> HN0040
A179: 4643 | B179: Win+ | C179: WM+ HPG 4 Cát Cụt | D179: Số 353 đường Nam Dư, Phường Trần Phú, Quận Hoàng Mai, TP. Hà Nội Việt Nam | E179: 73002017 | F179: =VLOOKUP(Table8[[#This Row],[Mã khách hàng]],code_khach_hang[],2,0) -> CHI NHÁNH HẢI PHÒNG - CÔNG TY CỔ PHẦN DỊCH VỤ THƯƠNG MẠI TỔNG HỢP WINCOMMERCE | G179: =VLOOKUP(Table8[[#This Row],[Mã khách hàng]],code_khach_hang[],3,0) -> Miền Bắc đặc biệt 3 | H179: =VLOOKUP(Table8[[#This Row],[Mã khách hàng]],'Khách hàng'!A:D,4,0) -> Food Đức Việt | I179: =VLOOKUP(Table8[[#This Row],[Mã khách hàng]],'Khách hàng'!A:E,5,0) -> HN0040
A180: 4817 | B180: Win+ | C180: WM+ HPG 129-131 Chợ Hàng | D180: 31 đường Bờ Sông hoặc 20 Nghĩa Dũng, , Phường Phúc Xá, Quận Ba Đình, TP. Hà Nội Việt Nam | E180: 73002017 | F180: =VLOOKUP(Table8[[#This Row],[Mã khách hàng]],code_khach_hang[],2,0) -> CHI NHÁNH HẢI PHÒNG - CÔNG TY CỔ PHẦN DỊCH VỤ THƯƠNG MẠI TỔNG HỢP WINCOMMERCE | G180: =VLOOKUP(Table8[[#This Row],[Mã khách hàng]],code_khach_hang[],3,0) -> Miền Bắc đặc biệt 3 | H180: =VLOOKUP(Table8[[#This Row],[Mã khách hàng]],'Khách hàng'!A:D,4,0) -> Food Đức Việt | I180: =VLOOKUP(Table8[[#This Row],[Mã khách hàng]],'Khách hàng'!A:E,5,0) -> HN0040
A181: 5091 | B181: Win+ | C181: WM+ HPG 251-253 Đào Nhuận | D181: Căn hộ số 102-104, Nhà K9, Đô thị mới Việt Hưng, Phường Việt Hưng, TP. Hà Nội Việt Nam | E181: 73002017 | F181: =VLOOKUP(Table8[[#This Row],[Mã khách hàng]],code_khach_hang[],2,0) -> CHI NHÁNH HẢI PHÒNG - CÔNG TY CỔ PHẦN DỊCH VỤ THƯƠNG MẠI TỔNG HỢP WINCOMMERCE | G181: =VLOOKUP(Table8[[#This Row],[Mã khách hàng]],code_khach_hang[],3,0) -> Miền Bắc đặc biệt 3 | H181: =VLOOKUP(Table8[[#This Row],[Mã khách hàng]],'Khách hàng'!A:D,4,0) -> Food Đức Việt | I181: =VLOOKUP(Table8[[#This Row],[Mã khách hàng]],'Khách hàng'!A:E,5,0) -> HN0040
A182: 2635 | B182: Win+ | C182: #N/A | D182: Số 67 ngõ 213 đường Giáp Nhất, Phường Nhân Chính, Quận Thanh Xuân, TP. Hà Nội Việt Nam | E182: 73002017 | F182: =VLOOKUP(Table8[[#This Row],[Mã khách hàng]],code_khach_hang[],2,0) -> CHI NHÁNH HẢI PHÒNG - CÔNG TY CỔ PHẦN DỊCH VỤ THƯƠNG MẠI TỔNG HỢP WINCOMMERCE | G182: =VLOOKUP(Table8[[#This Row],[Mã khách hàng]],code_khach_hang[],3,0) -> Miền Bắc đặc biệt 3 | H182: =VLOOKUP(Table8[[#This Row],[Mã khách hàng]],'Khách hàng'!A:D,4,0) -> Food Đức Việt | I182: =VLOOKUP(Table8[[#This Row],[Mã khách hàng]],'Khách hàng'!A:E,5,0) -> HN0040
A183: 5486 | B183: Win+ | C183: WM+ HPG 379 Miếu Hai Xã | D183: Số 1 ngõ 250 đường Kim Giang, phườn, g Đại Kim, Quận Hoàng Mai, TP. Hà Nội Việt Nam | E183: 73002017 | F183: =VLOOKUP(Table8[[#This Row],[Mã khách hàng]],code_khach_hang[],2,0) -> CHI NHÁNH HẢI PHÒNG - CÔNG TY CỔ PHẦN DỊCH VỤ THƯƠNG MẠI TỔNG HỢP WINCOMMERCE | G183: =VLOOKUP(Table8[[#This Row],[Mã khách hàng]],code_khach_hang[],3,0) -> Miền Bắc đặc biệt 3 | H183: =VLOOKUP(Table8[[#This Row],[Mã khách hàng]],'Khách hàng'!A:D,4,0) -> Food Đức Việt | I183: =VLOOKUP(Table8[[#This Row],[Mã khách hàng]],'Khách hàng'!A:E,5,0) -> HN0040
A184: 5748 | B184: Win+ | C184: WM+ HPG 136 Hồ Sen | D184: 79 ngõ 1194 Đường Láng, Phường Láng, Thượng, Quận Đống Đa, TP. Hà Nội Việt Nam | E184: 73002017 | F184: =VLOOKUP(Table8[[#This Row],[Mã khách hàng]],code_khach_hang[],2,0) -> CHI NHÁNH HẢI PHÒNG - CÔNG TY CỔ PHẦN DỊCH VỤ THƯƠNG MẠI TỔNG HỢP WINCOMMERCE | G184: =VLOOKUP(Table8[[#This Row],[Mã khách hàng]],code_khach_hang[],3,0) -> Miền Bắc đặc biệt 3 | H184: =VLOOKUP(Table8[[#This Row],[Mã khách hàng]],'Khách hàng'!A:D,4,0) -> Food Đức Việt | I184: =VLOOKUP(Table8[[#This Row],[Mã khách hàng]],'Khách hàng'!A:E,5,0) -> HN0040
A185: 5988 | B185: Win+ | C185: WM+ HPG HD 78 Vinhomes Marina | D185: Số 211 đường Thạch Bàn, Phường Thạc, h Bàn, Quận Long Biên, TP. Hà Nội Việt Nam | E185: 73002017 | F185: =VLOOKUP(Table8[[#This Row],[Mã khách hàng]],code_khach_hang[],2,0) -> CHI NHÁNH HẢI PHÒNG - CÔNG TY CỔ PHẦN DỊCH VỤ THƯƠNG MẠI TỔNG HỢP WINCOMMERCE | G185: =VLOOKUP(Table8[[#This Row],[Mã khách hàng]],code_khach_hang[],3,0) -> Miền Bắc đặc biệt 3 | H185: =VLOOKUP(Table8[[#This Row],[Mã khách hàng]],'Khách hàng'!A:D,4,0) -> Food Đức Việt | I185: =VLOOKUP(Table8[[#This Row],[Mã khách hàng]],'Khách hàng'!A:E,5,0) -> HN0040
A186: 6451 | B186: Win+ | C186: WM+ HPG 158 Vũ Chí Thắng | D186: Chung cư cao tầng CT2A, khu nhà ở Xuân, La, Phường Xuân La, TP. Hà Nội Việt Nam | E186: 73002017 | F186: =VLOOKUP(Table8[[#This Row],[Mã khách hàng]],code_khach_hang[],2,0) -> CHI NHÁNH HẢI PHÒNG - CÔNG TY CỔ PHẦN DỊCH VỤ THƯƠNG MẠI TỔNG HỢP WINCOMMERCE | G186: =VLOOKUP(Table8[[#This Row],[Mã khách hàng]],code_khach_hang[],3,0) -> Miền Bắc đặc biệt 3 | H186: =VLOOKUP(Table8[[#This Row],[Mã khách hàng]],'Khách hàng'!A:D,4,0) -> Food Đức Việt | I186: =VLOOKUP(Table8[[#This Row],[Mã khách hàng]],'Khách hàng'!A:E,5,0) -> HN0040
A187: 3189 | B187: Win+ | C187: WM+ HPG 33 Lê Lai | D187: Số 56 ngõ 143 Nguyễn Chính, Phường, Thịnh Liệt, Quận Hoàng Mai, TP. Hà Nội Việt Nam | E187: 73002017 | F187: =VLOOKUP(Table8[[#This Row],[Mã khách hàng]],code_khach_hang[],2,0) -> CHI NHÁNH HẢI PHÒNG - CÔNG TY CỔ PHẦN DỊCH VỤ THƯƠNG MẠI TỔNG HỢP WINCOMMERCE | G187: =VLOOKUP(Table8[[#This Row],[Mã khách hàng]],code_khach_hang[],3,0) -> Miền Bắc đặc biệt 3 | H187: =VLOOKUP(Table8[[#This Row],[Mã khách hàng]],'Khách hàng'!A:D,4,0) -> Food Đức Việt | I187: =VLOOKUP(Table8[[#This Row],[Mã khách hàng]],'Khách hàng'!A:E,5,0) -> HN0040
A188: 3263 | B188: Win+ | C188: WM+ HPG 252 Đông Khê | D188: Số 31 Mạc Thị Bưởi, P. Vĩnh Tuy, Q., Quận Hai Bà Trưng, TP. Hà Nội Việt Nam | E188: 73002017 | F188: =VLOOKUP(Table8[[#This Row],[Mã khách hàng]],code_khach_hang[],2,0) -> CHI NHÁNH HẢI PHÒNG - CÔNG TY CỔ PHẦN DỊCH VỤ THƯƠNG MẠI TỔNG HỢP WINCOMMERCE | G188: =VLOOKUP(Table8[[#This Row],[Mã khách hàng]],code_khach_hang[],3,0) -> Miền Bắc đặc biệt 3 | H188: =VLOOKUP(Table8[[#This Row],[Mã khách hàng]],'Khách hàng'!A:D,4,0) -> Food Đức Việt | I188: =VLOOKUP(Table8[[#This Row],[Mã khách hàng]],'Khách hàng'!A:E,5,0) -> HN0040
A189: 3267 | B189: Win+ | C189: WM+ HPG 21 Lê Hồng Phong | D189: Số 19B đường Tô Ngọc Vân, Phường, Quảng An, Quận Tây Hồ, TP. Hà Nội Việt Nam | E189: 73002017 | F189: =VLOOKUP(Table8[[#This Row],[Mã khách hàng]],code_khach_hang[],2,0) -> CHI NHÁNH HẢI PHÒNG - CÔNG TY CỔ PHẦN DỊCH VỤ THƯƠNG MẠI TỔNG HỢP WINCOMMERCE | G189: =VLOOKUP(Table8[[#This Row],[Mã khách hàng]],code_khach_hang[],3,0) -> Miền Bắc đặc biệt 3 | H189: =VLOOKUP(Table8[[#This Row],[Mã khách hàng]],'Khách hàng'!A:D,4,0) -> Food Đức Việt | I189: =VLOOKUP(Table8[[#This Row],[Mã khách hàng]],'Khách hàng'!A:E,5,0) -> HN0040
A190: 5520 | B190: Win+ | C190: #N/A | D190: Số 6-8 Phố Vọng, Phường Phương Mai, Quận Đống Đa, TP. Hà Nội Việt Nam | E190: 73002017 | F190: =VLOOKUP(Table8[[#This Row],[Mã khách hàng]],code_khach_hang[],2,0) -> CHI NHÁNH HẢI PHÒNG - CÔNG TY CỔ PHẦN DỊCH VỤ THƯƠNG MẠI TỔNG HỢP WINCOMMERCE | G190: =VLOOKUP(Table8[[#This Row],[Mã khách hàng]],code_khach_hang[],3,0) -> Miền Bắc đặc biệt 3 | H190: =VLOOKUP(Table8[[#This Row],[Mã khách hàng]],'Khách hàng'!A:D,4,0) -> Food Đức Việt | I190: =VLOOKUP(Table8[[#This Row],[Mã khách hàng]],'Khách hàng'!A:E,5,0) -> HN0040
A191: 3023 | B191: Win+ | C191: #N/A | D191: Số 11 Ngô Sỹ Liên, Phường Văn Miếu, Quận Đống Đa, TP. Hà Nội Việt Nam | E191: 73002017 | F191: =VLOOKUP(Table8[[#This Row],[Mã khách hàng]],code_khach_hang[],2,0) -> CHI NHÁNH HẢI PHÒNG - CÔNG TY CỔ PHẦN DỊCH VỤ THƯƠNG MẠI TỔNG HỢP WINCOMMERCE | G191: =VLOOKUP(Table8[[#This Row],[Mã khách hàng]],code_khach_hang[],3,0) -> Miền Bắc đặc biệt 3 | H191: =VLOOKUP(Table8[[#This Row],[Mã khách hàng]],'Khách hàng'!A:D,4,0) -> Food Đức Việt | I191: =VLOOKUP(Table8[[#This Row],[Mã khách hàng]],'Khách hàng'!A:E,5,0) -> HN0040
A192: 3909 | B192: Win+ | C192: WM+ HPG 24A An Đà | D192: Số 354-356 Mỹ Đình, Phường Mỹ Đình 1, Quận Nam Từ Liêm, TP. Hà Nội Việt Nam | E192: 73002017 | F192: =VLOOKUP(Table8[[#This Row],[Mã khách hàng]],code_khach_hang[],2,0) -> CHI NHÁNH HẢI PHÒNG - CÔNG TY CỔ PHẦN DỊCH VỤ THƯƠNG MẠI TỔNG HỢP WINCOMMERCE | G192: =VLOOKUP(Table8[[#This Row],[Mã khách hàng]],code_khach_hang[],3,0) -> Miền Bắc đặc biệt 3 | H192: =VLOOKUP(Table8[[#This Row],[Mã khách hàng]],'Khách hàng'!A:D,4,0) -> Food Đức Việt | I192: =VLOOKUP(Table8[[#This Row],[Mã khách hàng]],'Khách hàng'!A:E,5,0) -> HN0040
A193: 5552 | B193: Win+ | C193: #N/A | D193: Số 123 phố Trịnh Công Sơn, Phường N, hật Tân, Quận Tây Hồ, TP. Hà Nội Việt Nam | E193: 73002017 | F193: =VLOOKUP(Table8[[#This Row],[Mã khách hàng]],code_khach_hang[],2,0) -> CHI NHÁNH HẢI PHÒNG - CÔNG TY CỔ PHẦN DỊCH VỤ THƯƠNG MẠI TỔNG HỢP WINCOMMERCE | G193: =VLOOKUP(Table8[[#This Row],[Mã khách hàng]],code_khach_hang[],3,0) -> Miền Bắc đặc biệt 3 | H193: =VLOOKUP(Table8[[#This Row],[Mã khách hàng]],'Khách hàng'!A:D,4,0) -> Food Đức Việt | I193: =VLOOKUP(Table8[[#This Row],[Mã khách hàng]],'Khách hàng'!A:E,5,0) -> HN0040
A194: 5541 | B194: Win+ | C194: #N/A | D194: Số 158 phố Thái Thịnh, Phường Láng, Hạ, Quận Đống Đa, TP. Hà Nội Việt Nam | E194: 73002017 | F194: =VLOOKUP(Table8[[#This Row],[Mã khách hàng]],code_khach_hang[],2,0) -> CHI NHÁNH HẢI PHÒNG - CÔNG TY CỔ PHẦN DỊCH VỤ THƯƠNG MẠI TỔNG HỢP WINCOMMERCE | G194: =VLOOKUP(Table8[[#This Row],[Mã khách hàng]],code_khach_hang[],3,0) -> Miền Bắc đặc biệt 3 | H194: =VLOOKUP(Table8[[#This Row],[Mã khách hàng]],'Khách hàng'!A:D,4,0) -> Food Đức Việt | I194: =VLOOKUP(Table8[[#This Row],[Mã khách hàng]],'Khách hàng'!A:E,5,0) -> HN0040
A195: 4644 | B195: Win+ | C195: WM+ HPG 25 Điện Biên Phủ | D195: Số 101 Hương Viên, Phường Đống Mác, Quận Hai Bà Trưng, TP. Hà Nội Việt Nam | E195: 73002017 | F195: =VLOOKUP(Table8[[#This Row],[Mã khách hàng]],code_khach_hang[],2,0) -> CHI NHÁNH HẢI PHÒNG - CÔNG TY CỔ PHẦN DỊCH VỤ THƯƠNG MẠI TỔNG HỢP WINCOMMERCE | G195: =VLOOKUP(Table8[[#This Row],[Mã khách hàng]],code_khach_hang[],3,0) -> Miền Bắc đặc biệt 3 | H195: =VLOOKUP(Table8[[#This Row],[Mã khách hàng]],'Khách hàng'!A:D,4,0) -> Food Đức Việt | I195: =VLOOKUP(Table8[[#This Row],[Mã khách hàng]],'Khách hàng'!A:E,5,0) -> HN0040
A196: 4839 | B196: Win+ | C196: WM+ HPG 149 Phố Cấm | D196: Số 33 Lương Khánh Thiện, tổ 62 phườ, ng Tương Mai, Quận Hoàng Mai, TP. Hà Nội Việt Nam | E196: 73002017 | F196: =VLOOKUP(Table8[[#This Row],[Mã khách hàng]],code_khach_hang[],2,0) -> CHI NHÁNH HẢI PHÒNG - CÔNG TY CỔ PHẦN DỊCH VỤ THƯƠNG MẠI TỔNG HỢP WINCOMMERCE | G196: =VLOOKUP(Table8[[#This Row],[Mã khách hàng]],code_khach_hang[],3,0) -> Miền Bắc đặc biệt 3 | H196: =VLOOKUP(Table8[[#This Row],[Mã khách hàng]],'Khách hàng'!A:D,4,0) -> Food Đức Việt | I196: =VLOOKUP(Table8[[#This Row],[Mã khách hàng]],'Khách hàng'!A:E,5,0) -> HN0040
A197: 5801 | B197: Win+ | C197: WM+ HPG 154 Lương Khánh Thiện | D197: Số 17 ngõ 77 Đặng Xuân Bảng, Phường, Đại Kim, Quận Hoàng Mai, TP. Hà Nội Việt Nam | E197: 73002017 | F197: =VLOOKUP(Table8[[#This Row],[Mã khách hàng]],code_khach_hang[],2,0) -> CHI NHÁNH HẢI PHÒNG - CÔNG TY CỔ PHẦN DỊCH VỤ THƯƠNG MẠI TỔNG HỢP WINCOMMERCE | G197: =VLOOKUP(Table8[[#This Row],[Mã khách hàng]],code_khach_hang[],3,0) -> Miền Bắc đặc biệt 3 | H197: =VLOOKUP(Table8[[#This Row],[Mã khách hàng]],'Khách hàng'!A:D,4,0) -> Food Đức Việt | I197: =VLOOKUP(Table8[[#This Row],[Mã khách hàng]],'Khách hàng'!A:E,5,0) -> HN0040
A198: 6224 | B198: Win+ | C198: WM+ HPG 415-416 Lô 22C Lê Hồng Phon | D198: 51 ngõ 53 Vũ Xuân Thiều, P. Sài Đồn, g, Q. Long Biên, TP. Hà Nội Việt Nam | E198: 73002017 | F198: =VLOOKUP(Table8[[#This Row],[Mã khách hàng]],code_khach_hang[],2,0) -> CHI NHÁNH HẢI PHÒNG - CÔNG TY CỔ PHẦN DỊCH VỤ THƯƠNG MẠI TỔNG HỢP WINCOMMERCE | G198: =VLOOKUP(Table8[[#This Row],[Mã khách hàng]],code_khach_hang[],3,0) -> Miền Bắc đặc biệt 3 | H198: =VLOOKUP(Table8[[#This Row],[Mã khách hàng]],'Khách hàng'!A:D,4,0) -> Food Đức Việt | I198: =VLOOKUP(Table8[[#This Row],[Mã khách hàng]],'Khách hàng'!A:E,5,0) -> HN0040
A199: 3450 | B199: Win+ | C199: WM+ HPG 261 Tôn Đức Thắng | D199: 10 tổ 30 Thịnh Liệt - KĐT Đồng Tàu, P. Thịnh Liệt, Q. Hoàng Mai, TP. Hà Nội Việt Nam | E199: 73002017 | F199: =VLOOKUP(Table8[[#This Row],[Mã khách hàng]],code_khach_hang[],2,0) -> CHI NHÁNH HẢI PHÒNG - CÔNG TY CỔ PHẦN DỊCH VỤ THƯƠNG MẠI TỔNG HỢP WINCOMMERCE | G199: =VLOOKUP(Table8[[#This Row],[Mã khách hàng]],code_khach_hang[],3,0) -> Miền Bắc đặc biệt 3 | H199: =VLOOKUP(Table8[[#This Row],[Mã khách hàng]],'Khách hàng'!A:D,4,0) -> Food Đức Việt | I199: =VLOOKUP(Table8[[#This Row],[Mã khách hàng]],'Khách hàng'!A:E,5,0) -> HN0040
A200: 3989 | B200: Win+ | C200: WM+ HPG LK03 – KĐT Golden Land | D200: Số 17B Đoàn Thị Điểm, Phường Quốc Tử Giám, Quận Đống Đa, TP. Hà Nội Việt Nam | E200: 73002017 | F200: =VLOOKUP(Table8[[#This Row],[Mã khách hàng]],code_khach_hang[],2,0) -> CHI NHÁNH HẢI PHÒNG - CÔNG TY CỔ PHẦN DỊCH VỤ THƯƠNG MẠI TỔNG HỢP WINCOMMERCE | G200: =VLOOKUP(Table8[[#This Row],[Mã khách hàng]],code_khach_hang[],3,0) -> Miền Bắc đặc biệt 3 | H200: =VLOOKUP(Table8[[#This Row],[Mã khách hàng]],'Khách hàng'!A:D,4,0) -> Food Đức Việt | I200: =VLOOKUP(Table8[[#This Row],[Mã khách hàng]],'Khách hàng'!A:E,5,0) -> HN0040
A201: 5249 | B201: Win+ | C201: WM+ HPG 196 Tổ 3 TT An Dương | D201: 16/12 Trần Quý Kiên, Tổ 58A, P. Dịch, Vọng, Q. Cầu Giấy, TP. Hà Nội Việt Nam | E201: 73002017 | F201: =VLOOKUP(Table8[[#This Row],[Mã khách hàng]],code_khach_hang[],2,0) -> CHI NHÁNH HẢI PHÒNG - CÔNG TY CỔ PHẦN DỊCH VỤ THƯƠNG MẠI TỔNG HỢP WINCOMMERCE | G201: =VLOOKUP(Table8[[#This Row],[Mã khách hàng]],code_khach_hang[],3,0) -> Miền Bắc đặc biệt 3 | H201: =VLOOKUP(Table8[[#This Row],[Mã khách hàng]],'Khách hàng'!A:D,4,0) -> Food Đức Việt | I201: =VLOOKUP(Table8[[#This Row],[Mã khách hàng]],'Khách hàng'!A:E,5,0) -> HN0040
A202: 5565 | B202: Win+ | C202: WM+ HPG 15 Lô L2, KĐT PG An Đồng | D202: 17 Trần Quốc Hoàn, P. Dịch Vọng, Q., Cầu Giấy, TP. Hà Nội Việt Nam | E202: 73002017 | F202: =VLOOKUP(Table8[[#This Row],[Mã khách hàng]],code_khach_hang[],2,0) -> CHI NHÁNH HẢI PHÒNG - CÔNG TY CỔ PHẦN DỊCH VỤ THƯƠNG MẠI TỔNG HỢP WINCOMMERCE | G202: =VLOOKUP(Table8[[#This Row],[Mã khách hàng]],code_khach_hang[],3,0) -> Miền Bắc đặc biệt 3 | H202: =VLOOKUP(Table8[[#This Row],[Mã khách hàng]],'Khách hàng'!A:D,4,0) -> Food Đức Việt | I202: =VLOOKUP(Table8[[#This Row],[Mã khách hàng]],'Khách hàng'!A:E,5,0) -> HN0040
A203: 5751 | B203: Win+ | C203: WM+ HPG Thôn Vĩnh Khê, An Dương | D203: Số 310 đường Minh Khai, P. Minh Khai, Quận Hai Bà Trưng, TP. Hà Nội Việt Nam | E203: 73002017 | F203: =VLOOKUP(Table8[[#This Row],[Mã khách hàng]],code_khach_hang[],2,0) -> CHI NHÁNH HẢI PHÒNG - CÔNG TY CỔ PHẦN DỊCH VỤ THƯƠNG MẠI TỔNG HỢP WINCOMMERCE | G203: =VLOOKUP(Table8[[#This Row],[Mã khách hàng]],code_khach_hang[],3,0) -> Miền Bắc đặc biệt 3 | H203: =VLOOKUP(Table8[[#This Row],[Mã khách hàng]],'Khách hàng'!A:D,4,0) -> Food Đức Việt | I203: =VLOOKUP(Table8[[#This Row],[Mã khách hàng]],'Khách hàng'!A:E,5,0) -> HN0040
A204: 5892 | B204: Win+ | C204: WM+ HPG 29 Trang Quan | D204: 101-A1 Tập thể Thanh Xuân, P. Thanh Xuân Bắc, Quận Thanh Xuân, TP. Hà Nội Việt Nam | E204: 73002017 | F204: =VLOOKUP(Table8[[#This Row],[Mã khách hàng]],code_khach_hang[],2,0) -> CHI NHÁNH HẢI PHÒNG - CÔNG TY CỔ PHẦN DỊCH VỤ THƯƠNG MẠI TỔNG HỢP WINCOMMERCE | G204: =VLOOKUP(Table8[[#This Row],[Mã khách hàng]],code_khach_hang[],3,0) -> Miền Bắc đặc biệt 3 | H204: =VLOOKUP(Table8[[#This Row],[Mã khách hàng]],'Khách hàng'!A:D,4,0) -> Food Đức Việt | I204: =VLOOKUP(Table8[[#This Row],[Mã khách hàng]],'Khách hàng'!A:E,5,0) -> HN0040
A205: 5941 | B205: Win+ | C205: WM+ HPG Khu Phố 1, An Dương | D205: 116-118 Cầu Diễn, Quận Bắc Từ Liêm, TP. Hà Nội Việt Nam | E205: 73002017 | F205: =VLOOKUP(Table8[[#This Row],[Mã khách hàng]],code_khach_hang[],2,0) -> CHI NHÁNH HẢI PHÒNG - CÔNG TY CỔ PHẦN DỊCH VỤ THƯƠNG MẠI TỔNG HỢP WINCOMMERCE | G205: =VLOOKUP(Table8[[#This Row],[Mã khách hàng]],code_khach_hang[],3,0) -> Miền Bắc đặc biệt 3 | H205: =VLOOKUP(Table8[[#This Row],[Mã khách hàng]],'Khách hàng'!A:D,4,0) -> Food Đức Việt | I205: =VLOOKUP(Table8[[#This Row],[Mã khách hàng]],'Khách hàng'!A:E,5,0) -> HN0040
A206: 6311 | B206: Win+ | C206: WM+ HPG Kiều Đông, An Dương | D206: Số 70B phố Đội Cấn, Quận Ba Đình, TP. Hà Nội Việt Nam | E206: 73002017 | F206: =VLOOKUP(Table8[[#This Row],[Mã khách hàng]],code_khach_hang[],2,0) -> CHI NHÁNH HẢI PHÒNG - CÔNG TY CỔ PHẦN DỊCH VỤ THƯƠNG MẠI TỔNG HỢP WINCOMMERCE | G206: =VLOOKUP(Table8[[#This Row],[Mã khách hàng]],code_khach_hang[],3,0) -> Miền Bắc đặc biệt 3 | H206: =VLOOKUP(Table8[[#This Row],[Mã khách hàng]],'Khách hàng'!A:D,4,0) -> Food Đức Việt | I206: =VLOOKUP(Table8[[#This Row],[Mã khách hàng]],'Khách hàng'!A:E,5,0) -> HN0040
... A270: 2752 | B270: Win+ | C270: WM+ HNI 109 Trần Huy Liệu | D270: Số 85 Yên Sở, Phường Yên Sở, Quận Hoàng Mai, TP. Hà Nội Việt Nam | E270: 73002014 | F270: =VLOOKUP(Table8[[#This Row],[Mã khách hàng]],code_khach_hang[],2,0) -> CHI NHÁNH HÀ NỘI - CÔNG TY CỔ PHẦN DỊCH VỤ THƯƠNG MẠI TỔNG HỢP WINCOMMERCE | G270: =VLOOKUP(Table8[[#This Row],[Mã khách hàng]],code_khach_hang[],3,0) -> Miền Bắc đặc biệt 1 | H270: =VLOOKUP(Table8[[#This Row],[Mã khách hàng]],'Khách hàng'!A:D,4,0) -> Food Đức Việt | I270: =VLOOKUP(Table8[[#This Row],[Mã khách hàng]],'Khách hàng'!A:E,5,0) -> HN0040
A271: 2777 | B271: Win+ | C271: #N/A | D271: Số 231B Trần Nguyên Hãn, Phường Niệm Nghĩa, Quận Lê Chân, TP. Hải Phòng Việt Nam | E271: 73002014 | F271: =VLOOKUP(Table8[[#This Row],[Mã khách hàng]],code_khach_hang[],2,0) -> CHI NHÁNH HÀ NỘI - CÔNG TY CỔ PHẦN DỊCH VỤ THƯƠNG MẠI TỔNG HỢP WINCOMMERCE | G271: =VLOOKUP(Table8[[#This Row],[Mã khách hàng]],code_khach_hang[],3,0) -> Miền Bắc đặc biệt 1 | H271: =VLOOKUP(Table8[[#This Row],[Mã khách hàng]],'Khách hàng'!A:D,4,0) -> Food Đức Việt | I271: =VLOOKUP(Table8[[#This Row],[Mã khách hàng]],'Khách hàng'!A:E,5,0) -> HN0040
A272: 2808 | B272: Win+ | C272: WM+ HNI 27 Phạm Hồng Thái | D272: Số 12 Lê Duẩn, tổ 52 khu 6, Phường Quán Trữ, Quận Kiến An, TP. Hải Phòng Việt Nam | E272: 73002014 | F272: =VLOOKUP(Table8[[#This Row],[Mã khách hàng]],code_khach_hang[],2,0) -> CHI NHÁNH HÀ NỘI - CÔNG TY CỔ PHẦN DỊCH VỤ THƯƠNG MẠI TỔNG HỢP WINCOMMERCE | G272: =VLOOKUP(Table8[[#This Row],[Mã khách hàng]],code_khach_hang[],3,0) -> Miền Bắc đặc biệt 1 | H272: =VLOOKUP(Table8[[#This Row],[Mã khách hàng]],'Khách hàng'!A:D,4,0) -> Food Đức Việt | I272: =VLOOKUP(Table8[[#This Row],[Mã khách hàng]],'Khách hàng'!A:E,5,0) -> HN0040
A273: 3027 | B273: Win+ | C273: WM+ HNI 27 ngách 254/1 đường Bưởi | D273: Số 38 ngõ 76 Mai Dịch, Phường, Mai Dịch, Quận Cầu Giấy, TP. Hà Nội Việt Nam | E273: 73002014 | F273: =VLOOKUP(Table8[[#This Row],[Mã khách hàng]],code_khach_hang[],2,0) -> CHI NHÁNH HÀ NỘI - CÔNG TY CỔ PHẦN DỊCH VỤ THƯƠNG MẠI TỔNG HỢP WINCOMMERCE | G273: =VLOOKUP(Table8[[#This Row],[Mã khách hàng]],code_khach_hang[],3,0) -> Miền Bắc đặc biệt 1 | H273: =VLOOKUP(Table8[[#This Row],[Mã khách hàng]],'Khách hàng'!A:D,4,0) -> Food Đức Việt | I273: =VLOOKUP(Table8[[#This Row],[Mã khách hàng]],'Khách hàng'!A:E,5,0) -> HN0040
A274: 3183 | B274: Win+ | C274: WM+ HNI 443 Đội Cấn | D274: Số 5 Nhật Tảo, P. Đông Ngạc, Quận Bắc Từ Liêm, TP. Hà Nội Việt Nam | E274: 73002014 | F274: =VLOOKUP(Table8[[#This Row],[Mã khách hàng]],code_khach_hang[],2,0) -> CHI NHÁNH HÀ NỘI - CÔNG TY CỔ PHẦN DỊCH VỤ THƯƠNG MẠI TỔNG HỢP WINCOMMERCE | G274: =VLOOKUP(Table8[[#This Row],[Mã khách hàng]],code_khach_hang[],3,0) -> Miền Bắc đặc biệt 1 | H274: =VLOOKUP(Table8[[#This Row],[Mã khách hàng]],'Khách hàng'!A:D,4,0) -> Food Đức Việt | I274: =VLOOKUP(Table8[[#This Row],[Mã khách hàng]],'Khách hàng'!A:E,5,0) -> HN0040
A275: 3434 | B275: Win+ | C275: WM+ HNI 91 Đốc Ngữ | D275: Số 96 Lán Bè, P.Lam Sơn, Quận Lê Chân, TP. Hải Phòng Việt Nam | E275: 73002014 | F275: =VLOOKUP(Table8[[#This Row],[Mã khách hàng]],code_khach_hang[],2,0) -> CHI NHÁNH HÀ NỘI - CÔNG TY CỔ PHẦN DỊCH VỤ THƯƠNG MẠI TỔNG HỢP WINCOMMERCE | G275: =VLOOKUP(Table8[[#This Row],[Mã khách hàng]],code_khach_hang[],3,0) -> Miền Bắc đặc biệt 1 | H275: =VLOOKUP(Table8[[#This Row],[Mã khách hàng]],'Khách hàng'!A:D,4,0) -> Food Đức Việt | I275: =VLOOKUP(Table8[[#This Row],[Mã khách hàng]],'Khách hàng'!A:E,5,0) -> HN0040
A276: 3465 | B276: Win+ | C276: WM+ HNI 671 Hoàng Hoa Thám | D276: Số 391 Ngô Xuân Quảng, TT. Trâu Quỳ, Huyện Gia Lâm, TP. Hà Nội Việt Nam | E276: 73002014 | F276: =VLOOKUP(Table8[[#This Row],[Mã khách hàng]],code_khach_hang[],2,0) -> CHI NHÁNH HÀ NỘI - CÔNG TY CỔ PHẦN DỊCH VỤ THƯƠNG MẠI TỔNG HỢP WINCOMMERCE | G276: =VLOOKUP(Table8[[#This Row],[Mã khách hàng]],code_khach_hang[],3,0) -> Miền Bắc đặc biệt 1 | H276: =VLOOKUP(Table8[[#This Row],[Mã khách hàng]],'Khách hàng'!A:D,4,0) -> Food Đức Việt | I276: =VLOOKUP(Table8[[#This Row],[Mã khách hàng]],'Khách hàng'!A:E,5,0) -> HN0040
A277: 4125 | B277: Win+ | C277: WM+ HNI CC Trung Ương Đảng | D277: 848 Trương Định, P. Giáp Bát, Quận Hoàng Mai, TP. Hà Nội Việt Nam | E277: 73002014 | F277: =VLOOKUP(Table8[[#This Row],[Mã khách hàng]],code_khach_hang[],2,0) -> CHI NHÁNH HÀ NỘI - CÔNG TY CỔ PHẦN DỊCH VỤ THƯƠNG MẠI TỔNG HỢP WINCOMMERCE | G277: =VLOOKUP(Table8[[#This Row],[Mã khách hàng]],code_khach_hang[],3,0) -> Miền Bắc đặc biệt 1 | H277: =VLOOKUP(Table8[[#This Row],[Mã khách hàng]],'Khách hàng'!A:D,4,0) -> Food Đức Việt | I277: =VLOOKUP(Table8[[#This Row],[Mã khách hàng]],'Khách hàng'!A:E,5,0) -> HN0040
A278: 5439 | B278: Win+ | C278: WM+ HNI 17A ngõ 9 Nguyễn Tri Phương | D278: Căn RA1 Ecopark, Ecopark, Huyện Văn Giang, T. Hưng Yên Việt Nam | E278: 73002014 | F278: =VLOOKUP(Table8[[#This Row],[Mã khách hàng]],code_khach_hang[],2,0) -> CHI NHÁNH HÀ NỘI - CÔNG TY CỔ PHẦN DỊCH VỤ THƯƠNG MẠI TỔNG HỢP WINCOMMERCE | G278: =VLOOKUP(Table8[[#This Row],[Mã khách hàng]],code_khach_hang[],3,0) -> Miền Bắc đặc biệt 1 | H278: =VLOOKUP(Table8[[#This Row],[Mã khách hàng]],'Khách hàng'!A:D,4,0) -> Food Đức Việt | I278: =VLOOKUP(Table8[[#This Row],[Mã khách hàng]],'Khách hàng'!A:E,5,0) -> HN0040
A279: 5504 | B279: Win+ | C279: WM+ HNI 105 Thành Công | D279: Lô 8-3A, KCN Q. Hoàng Mai, Phường Hoàng Văn Thụ, Quận Hoàng Mai, TP. Hà Nội Việt Nam | E279: 73002014 | F279: =VLOOKUP(Table8[[#This Row],[Mã khách hàng]],code_khach_hang[],2,0) -> CHI NHÁNH HÀ NỘI - CÔNG TY CỔ PHẦN DỊCH VỤ THƯƠNG MẠI TỔNG HỢP WINCOMMERCE | G279: =VLOOKUP(Table8[[#This Row],[Mã khách hàng]],code_khach_hang[],3,0) -> Miền Bắc đặc biệt 1 | H279: =VLOOKUP(Table8[[#This Row],[Mã khách hàng]],'Khách hàng'!A:D,4,0) -> Food Đức Việt | I279: =VLOOKUP(Table8[[#This Row],[Mã khách hàng]],'Khách hàng'!A:E,5,0) -> HN0040
A280: 5505 | B280: Win+ | C280: WM+ HNI 106 Dốc Chợ Thành Công | D280: Số 12 ngõ 253 Nguyễn Văn Linh, Số 12 ngõ 253 Nguyễn Văn Linh, phường Phúc Đồng, TP. Hà Nội Việt Nam | E280: 73002014 | F280: =VLOOKUP(Table8[[#This Row],[Mã khách hàng]],code_khach_hang[],2,0) -> CHI NHÁNH HÀ NỘI - CÔNG TY CỔ PHẦN DỊCH VỤ THƯƠNG MẠI TỔNG HỢP WINCOMMERCE | G280: =VLOOKUP(Table8[[#This Row],[Mã khách hàng]],code_khach_hang[],3,0) -> Miền Bắc đặc biệt 1 | H280: =VLOOKUP(Table8[[#This Row],[Mã khách hàng]],'Khách hàng'!A:D,4,0) -> Food Đức Việt | I280: =VLOOKUP(Table8[[#This Row],[Mã khách hàng]],'Khách hàng'!A:E,5,0) -> HN0040
A281: 5614 | B281: Win+ | C281: WM+ HNI 78 ngõ 189 Hoàng Hoa Thám | D281: Thôn Vĩnh Ninh, Xã Vĩnh Quỳnh, Huyện Thanh Trì TP. Hà Nội Việt Nam | E281: 73002014 | F281: =VLOOKUP(Table8[[#This Row],[Mã khách hàng]],code_khach_hang[],2,0) -> CHI NHÁNH HÀ NỘI - CÔNG TY CỔ PHẦN DỊCH VỤ THƯƠNG MẠI TỔNG HỢP WINCOMMERCE | G281: =VLOOKUP(Table8[[#This Row],[Mã khách hàng]],code_khach_hang[],3,0) -> Miền Bắc đặc biệt 1 | H281: =VLOOKUP(Table8[[#This Row],[Mã khách hàng]],'Khách hàng'!A:D,4,0) -> Food Đức Việt | I281: =VLOOKUP(Table8[[#This Row],[Mã khách hàng]],'Khách hàng'!A:E,5,0) -> HN0040
A282: 5644 | B282: Win+ | C282: WM+ HNI Số 1 B5 Giảng Võ (8 Núi Trú | D282: Tổ dân phố Mậu Thông, P. Khai Quang, Tp. Vĩnh Yên T. Vĩnh Phúc Việt Nam | E282: 73002014 | F282: =VLOOKUP(Table8[[#This Row],[Mã khách hàng]],code_khach_hang[],2,0) -> CHI NHÁNH HÀ NỘI - CÔNG TY CỔ PHẦN DỊCH VỤ THƯƠNG MẠI TỔNG HỢP WINCOMMERCE | G282: =VLOOKUP(Table8[[#This Row],[Mã khách hàng]],code_khach_hang[],3,0) -> Miền Bắc đặc biệt 1 | H282: =VLOOKUP(Table8[[#This Row],[Mã khách hàng]],'Khách hàng'!A:D,4,0) -> Food Đức Việt | I282: =VLOOKUP(Table8[[#This Row],[Mã khách hàng]],'Khách hàng'!A:E,5,0) -> HN0040
A283: 5714 | B283: Win+ | C283: WM+ HNI 25 Ngõ 173/24 Hoàng Hoa Thá | D283: Đường Trần Hưng Đạo, Xã Bảo Ninh, Thành phố Đồng Hới, T. Quảng Bình Việt Nam | E283: 73002014 | F283: =VLOOKUP(Table8[[#This Row],[Mã khách hàng]],code_khach_hang[],2,0) -> CHI NHÁNH HÀ NỘI - CÔNG TY CỔ PHẦN DỊCH VỤ THƯƠNG MẠI TỔNG HỢP WINCOMMERCE | G283: =VLOOKUP(Table8[[#This Row],[Mã khách hàng]],code_khach_hang[],3,0) -> Miền Bắc đặc biệt 1 | H283: =VLOOKUP(Table8[[#This Row],[Mã khách hàng]],'Khách hàng'!A:D,4,0) -> Food Đức Việt | I283: =VLOOKUP(Table8[[#This Row],[Mã khách hàng]],'Khách hàng'!A:E,5,0) -> HN0040
... A307: 2758 | B307: Win+ | C307: WM+ HNI 167 Tr Đại Nghĩa | D307: Số 170-172 Đường vòng Vạn Mỹ, P. Vạn Mỹ, Q. Ngô Quyền TP. Hải Phòng Việt Nam | E307: 73002014 | F307: =VLOOKUP(Table8[[#This Row],[Mã khách hàng]],code_khach_hang[],2,0) -> CHI NHÁNH HÀ NỘI - CÔNG TY CỔ PHẦN DỊCH VỤ THƯƠNG MẠI TỔNG HỢP WINCOMMERCE | G307: =VLOOKUP(Table8[[#This Row],[Mã khách hàng]],code_khach_hang[],3,0) -> Miền Bắc đặc biệt 1 | H307: =VLOOKUP(Table8[[#This Row],[Mã khách hàng]],'Khách hàng'!A:D,4,0) -> Food Đức Việt | I307: =VLOOKUP(Table8[[#This Row],[Mã khách hàng]],'Khách hàng'!A:E,5,0) -> HN0040
A308: 2776 | B308: Win+ | C308: #N/A | D308: Thôn Bến, Xã Dị Nậu, Huyện Thạch Thất TP. Hà Nội Việt Nam | E308: 73002014 | F308: =VLOOKUP(Table8[[#This Row],[Mã khách hàng]],code_khach_hang[],2,0) -> CHI NHÁNH HÀ NỘI - CÔNG TY CỔ PHẦN DỊCH VỤ THƯƠNG MẠI TỔNG HỢP WINCOMMERCE | G308: =VLOOKUP(Table8[[#This Row],[Mã khách hàng]],code_khach_hang[],3,0) -> Miền Bắc đặc biệt 1 | H308: =VLOOKUP(Table8[[#This Row],[Mã khách hàng]],'Khách hàng'!A:D,4,0) -> Food Đức Việt | I308: =VLOOKUP(Table8[[#This Row],[Mã khách hàng]],'Khách hàng'!A:E,5,0) -> HN0040
A309: 2792 | B309: Win+ | C309: WM+ HNI 38 Đê Tô Hoàng | D309: Thôn Đồng Lý, Thị Trấn Lương Bằng, Huyện Kim Động T. Hưng Yên Việt Nam | E309: 73002014 | F309: =VLOOKUP(Table8[[#This Row],[Mã khách hàng]],code_khach_hang[],2,0) -> CHI NHÁNH HÀ NỘI - CÔNG TY CỔ PHẦN DỊCH VỤ THƯƠNG MẠI TỔNG HỢP WINCOMMERCE | G309: =VLOOKUP(Table8[[#This Row],[Mã khách hàng]],code_khach_hang[],3,0) -> Miền Bắc đặc biệt 1 | H309: =VLOOKUP(Table8[[#This Row],[Mã khách hàng]],'Khách hàng'!A:D,4,0) -> Food Đức Việt | I309: =VLOOKUP(Table8[[#This Row],[Mã khách hàng]],'Khách hàng'!A:E,5,0) -> HN0040
A310: 3015 | B310: Win+ | C310: WM+ HNI N3 Nguyễn Công Trứ | D310: Số 118-120 Khu Lãm Làng, P. Vân Dương, TP. Bắc Ninh T. Bắc Ninh Việt Nam | E310: 73002014 | F310: =VLOOKUP(Table8[[#This Row],[Mã khách hàng]],code_khach_hang[],2,0) -> CHI NHÁNH HÀ NỘI - CÔNG TY CỔ PHẦN DỊCH VỤ THƯƠNG MẠI TỔNG HỢP WINCOMMERCE | G310: =VLOOKUP(Table8[[#This Row],[Mã khách hàng]],code_khach_hang[],3,0) -> Miền Bắc đặc biệt 1 | H310: =VLOOKUP(Table8[[#This Row],[Mã khách hàng]],'Khách hàng'!A:D,4,0) -> Food Đức Việt | I310: =VLOOKUP(Table8[[#This Row],[Mã khách hàng]],'Khách hàng'!A:E,5,0) -> HN0040
A311: 3227 | B311: Win+ | C311: WM+ HNI 15 Trần Khánh Dư | D311: Số 51, TDP số 4, P. Phú Đô, Q. Nam Từ Liêm TP. Hà Nội Việt Nam | E311: 73002014 | F311: =VLOOKUP(Table8[[#This Row],[Mã khách hàng]],code_khach_hang[],2,0) -> CHI NHÁNH HÀ NỘI - CÔNG TY CỔ PHẦN DỊCH VỤ THƯƠNG MẠI TỔNG HỢP WINCOMMERCE | G311: =VLOOKUP(Table8[[#This Row],[Mã khách hàng]],code_khach_hang[],3,0) -> Miền Bắc đặc biệt 1 | H311: =VLOOKUP(Table8[[#This Row],[Mã khách hàng]],'Khách hàng'!A:D,4,0) -> Food Đức Việt | I311: =VLOOKUP(Table8[[#This Row],[Mã khách hàng]],'Khách hàng'!A:E,5,0) -> HN0040
A312: 3350 | B312: Win+ | C312: WM+ HNI 777 Bạch Đằng | D312: Số 251 Đường Lý Thường Kiệt, Tổ 8, Thị Trấn Mậu A, Huyện Văn Yên T. Yên Bái Việt Nam | E312: 73002014 | F312: =VLOOKUP(Table8[[#This Row],[Mã khách hàng]],code_khach_hang[],2,0) -> CHI NHÁNH HÀ NỘI - CÔNG TY CỔ PHẦN DỊCH VỤ THƯƠNG MẠI TỔNG HỢP WINCOMMERCE | G312: =VLOOKUP(Table8[[#This Row],[Mã khách hàng]],code_khach_hang[],3,0) -> Miền Bắc đặc biệt 1 | H312: =VLOOKUP(Table8[[#This Row],[Mã khách hàng]],'Khách hàng'!A:D,4,0) -> Food Đức Việt | I312: =VLOOKUP(Table8[[#This Row],[Mã khách hàng]],'Khách hàng'!A:E,5,0) -> HN0040
A313: 3641 | B313: Win+ | C313: WM+ HNI 25 Lãng Yên | D313: Số 105A Nguyễn Trãi, Lô 45+46 MBQH số 109 XD/UBTH, P. Ba Đình, TP. Thanh Hóa T. Thanh Hóa Việt Nam | E313: 73002014 | F313: =VLOOKUP(Table8[[#This Row],[Mã khách hàng]],code_khach_hang[],2,0) -> CHI NHÁNH HÀ NỘI - CÔNG TY CỔ PHẦN DỊCH VỤ THƯƠNG MẠI TỔNG HỢP WINCOMMERCE | G313: =VLOOKUP(Table8[[#This Row],[Mã khách hàng]],code_khach_hang[],3,0) -> Miền Bắc đặc biệt 1 | H313: =VLOOKUP(Table8[[#This Row],[Mã khách hàng]],'Khách hàng'!A:D,4,0) -> Food Đức Việt | I313: =VLOOKUP(Table8[[#This Row],[Mã khách hàng]],'Khách hàng'!A:E,5,0) -> HN0040
A314: 4023 | B314: Win+ | C314: WM+ HNI 42 Vĩnh Tuy | D314: Đường 308, Xóm 11, Thôn Phú Mỹ, Xã Tự Lập, Huyện Mê Linh TP. Hà Nội Việt Nam | E314: 73002014 | F314: =VLOOKUP(Table8[[#This Row],[Mã khách hàng]],code_khach_hang[],2,0) -> CHI NHÁNH HÀ NỘI - CÔNG TY CỔ PHẦN DỊCH VỤ THƯƠNG MẠI TỔNG HỢP WINCOMMERCE | G314: =VLOOKUP(Table8[[#This Row],[Mã khách hàng]],code_khach_hang[],3,0) -> Miền Bắc đặc biệt 1 | H314: =VLOOKUP(Table8[[#This Row],[Mã khách hàng]],'Khách hàng'!A:D,4,0) -> Food Đức Việt | I314: =VLOOKUP(Table8[[#This Row],[Mã khách hàng]],'Khách hàng'!A:E,5,0) -> HN0040
...

Sheet Khách hàng
A1: Mã khách hàng | B1: Tên khách hàng | C1: Chi nhánh | D1: Nhóm hàng | E1: Mã kho
A2: 73002010 | B2: CHI NHÁNH BẮC NINH - CÔNG TY CỔ PHẦN DỊCH VỤ THƯƠNG MẠI TỔNG HỢP WINCOMMERCE | C2: Miền Bắc đặc biệt 2 | D2: Food Đức Việt | E2: HN0040
A3: 73002005 | B3: CHI NHÁNH VĨNH PHÚC - CÔNG TY CỔ PHẦN DỊCH VỤ THƯƠNG MẠI TỔNG HỢP WINCOMMERCE | C3: Miền Bắc đặc biệt 2 | D3: Food Đức Việt | E3: HN0040
A4: 73002776 | B4: CHI NHÁNH HÀ NỘI - CÔNG TY CỔ PHẦN DỊCH VỤ THƯƠNG MẠI TỔNG HỢP WINCOMMERCE | C4: Miền Bắc đặc biệt 2 | D4: Food Đức Việt | E4: HN0040
A5: 73002019 | B5: CHI NHÁNH HƯNG YÊN - CÔNG TY CỔ PHẦN DỊCH VỤ THƯƠNG MẠI TỔNG HỢP WINCOMMERCE | C5: Miền Bắc đặc biệt 1 | D5: Food Đức Việt | E5: HN0040
A6: 73002017 | B6: CHI NHÁNH HẢI PHÒNG - CÔNG TY CỔ PHẦN DỊCH VỤ THƯƠNG MẠI TỔNG HỢP WINCOMMERCE | C6: Miền Bắc đặc biệt 3 | D6: Food Đức Việt | E6: HN0040
A7: 73001997 | B7: CHI NHÁNH QUẢNG BÌNH - CÔNG TY CỔ PHẦN DỊCH VỤ THƯƠNG MẠI TỔNG HỢP WINCOMMERCE | C7: Miền Trung đặc biệt 1 | D7: Food Đức Việt | E7: HN0040
A8: 73002015 | B8: CHI NHÁNH HÀ TĨNH - CÔNG TY CỔ PHẦN DỊCH VỤ THƯƠNG MẠI TỔNG HỢP WINCOMMERCE | C8: Miền Trung đặc biệt 1 | D8: Food Đức Việt | E8: HN0040
A9: 73001994 | B9: CHI NHÁNH NGHỆ AN - CÔNG TY CỔ PHẦN DỊCH VỤ THƯƠNG MẠI TỔNG HỢP WINCOMMERCE | C9: Miền Trung đặc biệt 1 | D9: Food Đức Việt | E9: HN0040
A10: 73002000 | B10: CHI NHÁNH THÁI BÌNH - CÔNG TY CỔ PHẦN DỊCH VỤ THƯƠNG MẠI TỔNG HỢP WINCOMMERCE | C10: Miền Bắc đặc biệt 3 | D10: Food Đức Việt | E10: HN0040
A11: 73002008 | B11: CHI NHÁNH BẮC GIANG - CÔNG TY CỔ PHẦN DỊCH VỤ THƯƠNG MẠI TỔNG HỢP WINCOMMERCE | C11: Miền Bắc đặc biệt 2 | D11: Food Đức Việt | E11: HN0040
A12: 73002002 | B12: CHI NHÁNH THANH HÓA - CÔNG TY CỔ PHẦN DỊCH VỤ THƯƠNG MẠI TỔNG HỢP WINCOMMERCE | C12: Miền Trung đặc biệt 1 | D12: Food Đức Việt | E12: HN0040
... A50: 73002044 | B50: CHI NHÁNH PHÚ YÊN - CÔNG TY CỔ PHẦN DỊCH VỤ THƯƠNG MẠI TỔNG HỢP WINCOMMERCE | C50: Miền Trung đặc biệt 2 | D50: Food Đức Việt | E50: QNTV50

Sheet Cost Center
A1: Nhóm sản phẩm | B1: Chi nhánh | C1: Cost center | D1: Tên
A2: MSG | B2: Miền Bắc đặc biệt 1 | C2: B_77BDBM | D2: CN MB Đặc biệt 1 (MSG)
A3: Food Daesang | B3: Miền Bắc đặc biệt 1 | C3: B_78BDBF | D3: CN MB Đặc biệt 1(O'Food)
A4: Food Nhập Khẩu | B4: Miền Bắc đặc biệt 1 | C4: B_107BDB | D4: CN Miền bắc ĐB 1 ( Food NK)
A5: Food Đức Việt | B5: Miền Bắc đặc biệt 1 | C5: B_157DB1 | D5: CN MBDB1_hàng TM đức việt
A6: MSG | B6: Miền Bắc đặc biệt 2 | C6: B126BDBM | D6: CN MB Đặc biệt 2 (MSG)
A7: Food Daesang | B7: Miền Bắc đặc biệt 2 | C7: B127BDBF | D7: CN MB Đặc biệt 2 (O'Food)
A8: Food Nhập Khẩu | B8: Miền Bắc đặc biệt 2 | C8: B129BDBN | D8: CN Miền bắc ĐB 2 ( Food NK)
A9: Food Đức Việt | B9: Miền Bắc đặc biệt 2 | C9: B_156DB2 | D9: CN MBDB2_hàng TM đức việt
A10: MSG | B10: Miền Bắc đặc biệt 3 | C10: B156NB3M | D10: CN MN Đặc biệt 3 ( MSG)
A11: Food Daesang | B11: Miền Nam đặc biệt 3 | C11: B157NB3F | D11: CN MN Đặc biệt 3 (Food)
A12: Food Nhập Khẩu | B12: Miền Nam đặc biệt 3 | C12: B158NB3N | D12: CN MN Đặc biệt 3 ( Food Nk)
... A15: Food Đức Việt | B15: Miền Trung đặc biệt 1 | C15: B_163DB1 | D15: CN MTDB1_hàng TM đức việt

Sheet Data Validation
A1: Phạm vi | C1: Hệ thống | E1: Chương trình KM | G1: DS-DV | I1: MSG - DS - NK - ĐV | K1: Chi nhánh | M1: Mã kho | N1: Tên kho
A2: Toàn quốc | C2: Toàn bộ | E2: Mua 1 tặng 1 | G2: Food Đức Việt | I2: Food Đức Việt | K2: Miền Bắc đặc biệt 1 | M2: HN0040
A3: Miền Bắc | C3: Win+ | E3: Mua 2 tặng 1 | G3: Food Daesang | I3: Food Daesang | K3: Miền Bắc đặc biệt 2 | M3: HN-HD110
A4: Miền Nam | C4: Winmart | I4: MSG | K4: Miền Bắc đặc biệt 3 | M4: HNTG100
A5: Miền Trung | I5: Food Nhập Khẩu | K5: Miền Trung đặc biệt 1 | M5: HN-VH110
K6: Miền Trung đặc biệt 2 | M6: DNTG100
K7: Miền Nam đặc biệt 1 | M7: QNTV50
K8: Miền Nam đặc biệt 2
K9: Miền Nam đặc biệt 3
